Workbook
Name valuevx: Calculator!$A$1
Name strategy: Calculator!$F$52
Name creditor_table: Calculator!$B$7:$E$30
Name snowball: Calculator!$F$53

Sheet Nov 2024
A1: Budget Calendar with Daily Balance
A2: Year: | B2: 2024 | D2: Month: | E2: 11 | G2: Start Day: | H2: 1 | I2: 1=Sun, 2=Mon … | T2: © 2020 Vertex42 LLC
T3: https://www.vertex42.com/calendars/budget-calendar.html
A5: =UPPER(TEXT(B8,"mmmm yyyy")) -> NOVEMBER 2024 | L5: Start Balance | M5: 2147 | R5: Cash In | S5: =SUMIF(A18:N21,">0")+SUMIF(A24:N27,">0")+SUMIF(A30:N33,">0")+SUMIF(A36:N39,">0")+SUMIF(A42:D45,">0")+SUMIF(S12:S45,">0")+SUMIF(A12:N15,">0") -> 7638.25 | V5: =sum(S5+S6) -> 2595.997
L6: End Balance | M6: =D46 -> 4742.997 | R6: Cash Out | S6: =SUMIF(A18:N21,"<0")+SUMIF(A24:N27,"<0")+SUMIF(A30:N33,"<0")+SUMIF(A36:N39,"<0")+SUMIF(A42:D45,"<0")+SUMIF(S12:S199,"<0")+SUMIF(A12:N15,"<0") -> -5042.253
A8: Date: | B8: =DATE(B2,E2,1) -> 45597
A9: =A17 -> 45599 | C9: =C17 -> 45600 | E9: =E17 -> 45601 | G9: =G17 -> 45602 | I9: =I17 -> 45603 | K9: =K17 -> 45604 | M9: =M17 -> 45605 | P9: MONTHLY BUDGET (EVERYDOLLAR)
A11: =IF(WEEKDAY($B$8,1)=$H$2,$B$8,"") | B11: =SUMIF($T$11:$T$127,A11,$S$11:$S$87) -> 0 | C11: =IF(A11="",IF(WEEKDAY($B$8,1)=MOD($H$2,7)+1,$B$8,""),A11+1) | D11: =SUMIF($T$11:$T$127,C11,$S$11:$S$87) -> 0 | E11: =IF(C11="",IF(WEEKDAY($B$8,1)=MOD($H$2+1,7)+1,$B$8,""),C11+1) | F11: =SUMIF($T$11:$T$127,E11,$S$11:$S$87) -> 0 | G11: =IF(E11="",IF(WEEKDAY($B$8,1)=MOD($H$2+2,7)+1,$B$8,""),E11+1) | H11: =SUMIF($T$11:$T$127,G11,$S$11:$S$87) -> 0 | I11: =IF(G11="",IF(WEEKDAY($B$8,1)=MOD($H$2+3,7)+1,$B$8,""),G11+1) | J11: =SUMIF($T$11:$T$127,I11,$S$11:$S$87) -> 0 | K11: =IF(I11="",IF(WEEKDAY($B$8,1)=MOD($H$2+4,7)+1,$B$8,""),I11+1) -> 45597 | L11: =SUMIF($T$11:$T$127,K11,$S$11:$S$87) -> 337.067 | M11: =IF(K11="",IF(WEEKDAY($B$8,1)=MOD($H$2+5,7)+1,$B$8,""),K11+1) -> 45598 | N11: =SUMIF($T$11:$T$127,M11,$S$11:$S$87) -> 0 | P11: BILL | Q11: ✔ | R11: DAY | S11: AMOUNT | T11: DUE DATE
P12: Check # 1 | R12: 1 | S12: 2004.44 | T12: =IF(ISBLANK(R12),"-",IF(R12>DAY(EOMONTH(DATE($B$2,$E$2,1),0)),EOMONTH(DATE($B$2,$E$2,1),0),DATE($B$2,$E$2,R12))) -> 45597
P13: Check #2 | R13: 1 | S13: 800 | T13: =IF(ISBLANK(R13),"-",IF(R13>DAY(EOMONTH(DATE($B$2,$E$2,1),0)),EOMONTH(DATE($B$2,$E$2,1),0),DATE($B$2,$E$2,R13))) -> 45597
P14: Mortgage | R14: 1 | S14: -1561 | T14: =IF(ISBLANK(R14),"-",IF(R14>DAY(EOMONTH(DATE($B$2,$E$2,1),0)),EOMONTH(DATE($B$2,$E$2,1),0),DATE($B$2,$E$2,R14))) -> 45597
P15: Pay Off Mats | R15: 1 | S15: -185 | T15: =IF(ISBLANK(R15),"-",IF(R15>DAY(EOMONTH(DATE($B$2,$E$2,1),0)),EOMONTH(DATE($B$2,$E$2,1),0),DATE($B$2,$E$2,R15))) -> 45597
A16: BAL: | B16: =$M$5+SUM(B11:B15) -> 2147 | D16: =B16+SUM(D11:D15) -> 2147 | F16: =D16+SUM(F11:F15) -> 2147 | H16: =F16+SUM(H11:H15) -> 2147 | J16: =H16+SUM(J11:J15) -> 2147 | L16: =J16+SUM(L11:L15) -> 2484.067 | N16: =L16+SUM(N11:N15) -> 2484.067 | P16: Pay off Phone | R16: 1 | S16: -566.373 | T16: =IF(ISBLANK(R16),"-",IF(R16>DAY(EOMONTH(DATE($B$2,$E$2,1),0)),EOMONTH(DATE($B$2,$E$2,1),0),DATE($B$2,$E$2,R16))) -> 45597
A17: =IF(M11="","",IF(MONTH(M11+1)<>MONTH(M11),"",M11+1)) -> 45599 | B17: =SUMIF($T$11:$T$127,A17,$S$11:$S$87) -> -33 | C17: =IF(A17="","",IF(MONTH(A17+1)<>MONTH(A17),"",A17+1)) -> 45600 | D17: =SUMIF($T$11:$T$127,C17,$S$11:$S$87) -> -150 | E17: =IF(C17="","",IF(MONTH(C17+1)<>MONTH(C17),"",C17+1)) -> 45601 | F17: =SUMIF($T$11:$T$127,E17,$S$11:$S$87) -> -1088.19 | G17: =IF(E17="","",IF(MONTH(E17+1)<>MONTH(E17),"",E17+1)) -> 45602 | H17: =SUMIF($T$11:$T$127,G17,$S$11:$S$87) -> 0 | I17: =IF(G17="","",IF(MONTH(G17+1)<>MONTH(G17),"",G17+1)) -> 45603 | J17: =SUMIF($T$11:$T$127,I17,$S$11:$S$87) -> 0 | K17: =IF(I17="","",IF(MONTH(I17+1)<>MONTH(I17),"",I17+1)) -> 45604 | L17: =SUMIF($T$11:$T$127,K17,$S$11:$S$87) -> -35 | M17: =IF(K17="","",IF(MONTH(K17+1)<>MONTH(K17),"",K17+1)) -> 45605 | N17: =SUMIF($T$11:$T$127,M17,$S$11:$S$87) -> -451 | P17: YMCA | R17: 1 | S17: -57 | T17: =IF(ISBLANK(R17),"-",IF(R17>DAY(EOMONTH(DATE($B$2,$E$2,1),0)),EOMONTH(DATE($B$2,$E$2,1),0),DATE($B$2,$E$2,R17))) -> 45597 | V17: Emergency Loan | X17: 739
P18: YMCA After School | R18: 1 | S18: -98 | T18: =IF(ISBLANK(R18),"-",IF(R18>DAY(EOMONTH(DATE($B$2,$E$2,1),0)),EOMONTH(DATE($B$2,$E$2,1),0),DATE($B$2,$E$2,R18))) -> 45597
P19: Pest Control | R19: 3 | S19: -33 | T19: =IF(ISBLANK(R19),"-",IF(R19>DAY(EOMONTH(DATE($B$2,$E$2,1),0)),EOMONTH(DATE($B$2,$E$2,1),0),DATE($B$2,$E$2,R19))) -> 45599
P20: Vegas | R20: 4 | S20: -150 | T20: =IF(ISBLANK(R20),"-",IF(R20>DAY(EOMONTH(DATE($B$2,$E$2,1),0)),EOMONTH(DATE($B$2,$E$2,1),0),DATE($B$2,$E$2,R20))) -> 45600
P21: Amazon Prime | R21: 5 | S21: -16.19 | T21: =IF(ISBLANK(R21),"-",IF(R21>DAY(EOMONTH(DATE($B$2,$E$2,1),0)),EOMONTH(DATE($B$2,$E$2,1),0),DATE($B$2,$E$2,R21))) -> 45601
A22: BAL: | B22: =N16+SUM(B17:B21) -> 2451.067 | D22: =B22+SUM(D17:D21) -> 2301.067 | F22: =D22+SUM(F17:F21) -> 1212.877 | H22: =F22+SUM(H17:H21) -> 1212.877 | J22: =H22+SUM(J17:J21) -> 1212.877 | L22: =J22+SUM(L17:L21) -> 1177.877 | N22: =L22+SUM(N17:N21) -> 726.877 | P22: Car Insurance | R22: 5 | S22: -184 | T22: =IF(ISBLANK(R22),"-",IF(R22>DAY(EOMONTH(DATE($B$2,$E$2,1),0)),EOMONTH(DATE($B$2,$E$2,1),0),DATE($B$2,$E$2,R22))) -> 45601 | V22: AA | W22: Account Adjustment
A23: =IF(M17="","",IF(MONTH(M17+1)<>MONTH(M17),"",M17+1)) -> 45606 | B23: =SUMIF($T$11:$T$127,A23,$S$11:$S$87) -> 0 | C23: =IF(A23="","",IF(MONTH(A23+1)<>MONTH(A23),"",A23+1)) -> 45607 | D23: =SUMIF($T$11:$T$127,C23,$S$11:$S$87) -> -228 | E23: =IF(C23="","",IF(MONTH(C23+1)<>MONTH(C23),"",C23+1)) -> 45608 | F23: =SUMIF($T$11:$T$127,E23,$S$11:$S$87) -> -102 | G23: =IF(E23="","",IF(MONTH(E23+1)<>MONTH(E23),"",E23+1)) -> 45609 | H23: =SUMIF($T$11:$T$127,G23,$S$11:$S$87) -> 1906.44 | I23: =IF(G23="","",IF(MONTH(G23+1)<>MONTH(G23),"",G23+1)) -> 45610 | J23: =SUMIF($T$11:$T$127,I23,$S$11:$S$87) -> 0 | K23: =IF(I23="","",IF(MONTH(I23+1)<>MONTH(I23),"",I23+1)) -> 45611 | L23: =SUMIF($T$11:$T$127,K23,$S$11:$S$87) -> 0 | M23: =IF(K23="","",IF(MONTH(K23+1)<>MONTH(K23),"",K23+1)) -> 45612 | N23: =SUMIF($T$11:$T$127,M23,$S$11:$S$87) -> 0 | P23: John Cap One | R23: 5 | S23: -96 | T23: =IF(ISBLANK(R23),"-",IF(R23>DAY(EOMONTH(DATE($B$2,$E$2,1),0)),EOMONTH(DATE($B$2,$E$2,1),0),DATE($B$2,$E$2,R23))) -> 45601
E24: Greenlight | F24: -4.16 | K24: AA | L24: 74.93 | P24: Kia Car Payment | R24: 5 | S24: -792 | T24: =IF(ISBLANK(R24),"-",IF(R24>DAY(EOMONTH(DATE($B$2,$E$2,1),0)),EOMONTH(DATE($B$2,$E$2,1),0),DATE($B$2,$E$2,R24))) -> 45601
P25: Emergency Loan | R25: 8 | S25: -35 | T25: =IF(ISBLANK(R25),"-",IF(R25>DAY(EOMONTH(DATE($B$2,$E$2,1),0)),EOMONTH(DATE($B$2,$E$2,1),0),DATE($B$2,$E$2,R25))) -> 45604
P26: Upgrade Loan | R26: 9 | S26: -451 | T26: =IF(ISBLANK(R26),"-",IF(R26>DAY(EOMONTH(DATE($B$2,$E$2,1),0)),EOMONTH(DATE($B$2,$E$2,1),0),DATE($B$2,$E$2,R26))) -> 45605
P27: Tia Cap One | R27: 11 | S27: -80 | T27: =IF(ISBLANK(R27),"-",IF(R27>DAY(EOMONTH(DATE($B$2,$E$2,1),0)),EOMONTH(DATE($B$2,$E$2,1),0),DATE($B$2,$E$2,R27))) -> 45607
A28: BAL: | B28: =N22+SUM(B23:B27) -> 726.877 | D28: =B28+SUM(D23:D27) -> 498.877 | F28: =D28+SUM(F23:F27) -> 392.717 | H28: =F28+SUM(H23:H27) -> 2299.157 | J28: =H28+SUM(J23:J27) -> 2299.157 | L28: =J28+SUM(L23:L27) -> 2374.087 | N28: =L28+SUM(N23:N27) -> 2374.087 | P28: Tidal Wave | R28: 11 | S28: -50 | T28: =IF(ISBLANK(R28),"-",IF(R28>DAY(EOMONTH(DATE($B$2,$E$2,1),0)),EOMONTH(DATE($B$2,$E$2,1),0),DATE($B$2,$E$2,R28))) -> 45607
A29: =IF(M23="","",IF(MONTH(M23+1)<>MONTH(M23),"",M23+1)) -> 45613 | B29: =SUMIF($T$11:$T$127,A29,$S$11:$S$87) -> -9.99 | C29: =IF(A29="","",IF(MONTH(A29+1)<>MONTH(A29),"",A29+1)) -> 45614 | D29: =SUMIF($T$11:$T$127,C29,$S$11:$S$87) -> -150 | E29: =IF(C29="","",IF(MONTH(C29+1)<>MONTH(C29),"",C29+1)) -> 45615 | F29: =SUMIF($T$11:$T$127,E29,$S$11:$S$87) -> 0 | G29: =IF(E29="","",IF(MONTH(E29+1)<>MONTH(E29),"",E29+1)) -> 45616 | H29: =SUMIF($T$11:$T$127,G29,$S$11:$S$87) -> 0 | I29: =IF(G29="","",IF(MONTH(G29+1)<>MONTH(G29),"",G29+1)) -> 45617 | J29: =SUMIF($T$11:$T$127,I29,$S$11:$S$87) -> 0 | K29: =IF(I29="","",IF(MONTH(I29+1)<>MONTH(I29),"",I29+1)) -> 45618 | L29: =SUMIF($T$11:$T$127,K29,$S$11:$S$87) -> 0 | M29: =IF(K29="","",IF(MONTH(K29+1)<>MONTH(K29),"",K29+1)) -> 45619 | N29: =SUMIF($T$11:$T$127,M29,$S$11:$S$87) -> 0 | P29: YMCA After School | R29: 11 | S29: -98 | T29: =IF(ISBLANK(R29),"-",IF(R29>DAY(EOMONTH(DATE($B$2,$E$2,1),0)),EOMONTH(DATE($B$2,$E$2,1),0),DATE($B$2,$E$2,R29))) -> 45607
G30: Cheer | H30: -42.96 | P30: Google | R30: 12 | S30: -102 | T30: =IF(ISBLANK(R30),"-",IF(R30>DAY(EOMONTH(DATE($B$2,$E$2,1),0)),EOMONTH(DATE($B$2,$E$2,1),0),DATE($B$2,$E$2,R30))) -> 45608
P31: Check # 3 | R31: 13 | S31: 2004.44 | T31: =IF(ISBLANK(R31),"-",IF(R31>DAY(EOMONTH(DATE($B$2,$E$2,1),0)),EOMONTH(DATE($B$2,$E$2,1),0),DATE($B$2,$E$2,R31))) -> 45609 | V31: Vegas | X31: 750
P32: YMCA After School | R32: 13 | S32: -98 | T32: =IF(ISBLANK(R32),"-",IF(R32>DAY(EOMONTH(DATE($B$2,$E$2,1),0)),EOMONTH(DATE($B$2,$E$2,1),0),DATE($B$2,$E$2,R32))) -> 45609 | W32: Plane Ticket | X32: -600
P33: Apple | R33: 17 | S33: -9.99 | T33: =IF(ISBLANK(R33),"-",IF(R33>DAY(EOMONTH(DATE($B$2,$E$2,1),0)),EOMONTH(DATE($B$2,$E$2,1),0),DATE($B$2,$E$2,R33))) -> 45613 | X33: =sum(X31:X32) -> 150
A34: BAL: | B34: =N28+SUM(B29:B33) -> 2364.097 | D34: =B34+SUM(D29:D33) -> 2214.097 | F34: =D34+SUM(F29:F33) -> 2214.097 | H34: =F34+SUM(H29:H33) -> 2171.137 | J34: =H34+SUM(J29:J33) -> 2171.137 | L34: =J34+SUM(L29:L33) -> 2171.137 | N34: =L34+SUM(N29:N33) -> 2171.137 | P34: Vegas | R34: 18 | S34: -150 | T34: =IF(ISBLANK(R34),"-",IF(R34>DAY(EOMONTH(DATE($B$2,$E$2,1),0)),EOMONTH(DATE($B$2,$E$2,1),0),DATE($B$2,$E$2,R34))) -> 45614
A35: =IF(M29="","",IF(MONTH(M29+1)<>MONTH(M29),"",M29+1)) -> 45620 | B35: =SUMIF($T$11:$T$127,A35,$S$11:$S$87) -> 0 | C35: =IF(A35="","",IF(MONTH(A35+1)<>MONTH(A35),"",A35+1)) -> 45621 | D35: =SUMIF($T$11:$T$127,C35,$S$11:$S$87) -> -29.34 | E35: =IF(C35="","",IF(MONTH(C35+1)<>MONTH(C35),"",C35+1)) -> 45622 | F35: =SUMIF($T$11:$T$127,E35,$S$11:$S$87) -> 2754.44 | G35: =IF(E35="","",IF(MONTH(E35+1)<>MONTH(E35),"",E35+1)) -> 45623 | H35: =SUMIF($T$11:$T$127,G35,$S$11:$S$87) -> -98 | I35: =IF(G35="","",IF(MONTH(G35+1)<>MONTH(G35),"",G35+1)) -> 45624 | J35: =SUMIF($T$11:$T$127,I35,$S$11:$S$87) -> -40.55 | K35: =IF(I35="","",IF(MONTH(I35+1)<>MONTH(I35),"",I35+1)) -> 45625 | L35: =SUMIF($T$11:$T$127,K35,$S$11:$S$87) -> 0 | M35: =IF(K35="","",IF(MONTH(K35+1)<>MONTH(K35),"",K35+1)) -> 45626 | N35: =SUMIF($T$11:$T$127,M35,$S$11:$S$87) -> -11 | P35: Dribble Up | R35: 25 | S35: -18.35 | T35: =IF(ISBLANK(R35),"-",IF(R35>DAY(EOMONTH(DATE($B$2,$E$2,1),0)),EOMONTH(DATE($B$2,$E$2,1),0),DATE($B$2,$E$2,R35))) -> 45621
A36: Apl | B36: -3.26 | L36: -0.43 | P36: Disney/Hulu | R36: 25 | S36: -10.99 | T36: =IF(ISBLANK(R36),"-",IF(R36>DAY(EOMONTH(DATE($B$2,$E$2,1),0)),EOMONTH(DATE($B$2,$E$2,1),0),DATE($B$2,$E$2,R36))) -> 45621
P37: Check #1 | R37: 26 | S37: 750 | T37: =IF(ISBLANK(R37),"-",IF(R37>DAY(EOMONTH(DATE($B$2,$E$2,1),0)),EOMONTH(DATE($B$2,$E$2,1),0),DATE($B$2,$E$2,R37))) -> 45622
P38: Check #4 | R38: 26 | S38: 2004.44 | T38: =IF(ISBLANK(R38),"-",IF(R38>DAY(EOMONTH(DATE($B$2,$E$2,1),0)),EOMONTH(DATE($B$2,$E$2,1),0),DATE($B$2,$E$2,R38))) -> 45622
P39: Greenlight | R39: 28 | S39: -6 | T39: =IF(ISBLANK(R39),"-",IF(R39>DAY(EOMONTH(DATE($B$2,$E$2,1),0)),EOMONTH(DATE($B$2,$E$2,1),0),DATE($B$2,$E$2,R39))) -> 45624
A40: BAL: | B40: =N34+SUM(B35:B39) -> 2167.877 | D40: =B40+SUM(D35:D39) -> 2138.537 | F40: =D40+SUM(F35:F39) -> 4892.977 | H40: =F40+SUM(H35:H39) -> 4794.977 | J40: =H40+SUM(J35:J39) -> 4754.427 | L40: =J40+SUM(L35:L39) -> 4753.997 | N40: =L40+SUM(N35:N39) -> 4742.997 | P40: HOC | R40: 28 | S40: -7.55 | T40: =IF(ISBLANK(R40),"-",IF(R40>DAY(EOMONTH(DATE($B$2,$E$2,1),0)),EOMONTH(DATE($B$2,$E$2,1),0),DATE($B$2,$E$2,R40))) -> 45624
A41: =IF(M35="","",IF(MONTH(M35+1)<>MONTH(M35),"",M35+1)) | B41: =SUMIF($T$11:$T$127,A41,$S$11:$S$87) -> 0 | C41: =IF(A41="","",IF(MONTH(A41+1)<>MONTH(A41),"",A41+1)) | D41: =SUMIF($T$11:$T$127,C41,$S$11:$S$87) -> 0 | F41: NOTES | P41: Netflix | R41: 28 | S41: -24 | T41: =IF(ISBLANK(R41),"-",IF(R41>DAY(EOMONTH(DATE($B$2,$E$2,1),0)),EOMONTH(DATE($B$2,$E$2,1),0),DATE($B$2,$E$2,R41))) -> 45624
F42: Remember to make copies of the worksheet before entering daily expenses. | T42: =IF(ISBLANK(R42),"-",IF(R42>DAY(EOMONTH(DATE($B$2,$E$2,1),0)),EOMONTH(DATE($B$2,$E$2,1),0),DATE($B$2,$E$2,R42))) -> -
P43: Peacock | R43: 28 | S43: -3 | T43: =IF(ISBLANK(R43),"-",IF(R43>DAY(EOMONTH(DATE($B$2,$E$2,1),0)),EOMONTH(DATE($B$2,$E$2,1),0),DATE($B$2,$E$2,R43))) -> 45624
P44: Apple Music | R44: 30 | S44: -11 | T44: =IF(ISBLANK(R44),"-",IF(R44>DAY(EOMONTH(DATE($B$2,$E$2,1),0)),EOMONTH(DATE($B$2,$E$2,1),0),DATE($B$2,$E$2,R44))) -> 45626
P45: YMCA After School | R45: 27 | S45: -98 | T45: =IF(ISBLANK(R45),"-",IF(R45>DAY(EOMONTH(DATE($B$2,$E$2,1),0)),EOMONTH(DATE($B$2,$E$2,1),0),DATE($B$2,$E$2,R45))) -> 45623
A46: BAL: | B46: =N40+SUM(B41:B45) -> 4742.997 | D46: =B46+SUM(D41:D45) -> 4742.997

Sheet Dashboard
A2: BILL | B2: ✔ | C2: DAY | D2: AMOUNT | E2: DUE DATE
A3: Amazon Music | C3: 30 | D3: -18.35
A4: Amazon Prime | C4: 6 | D4: -16.19
A5: Apple | C5: 17 | D5: -9.99
A6: Apple Music | C6: 30 | D6: -11
A7: Cap One | C7: 4 | D7: -96
A8: Car Insurance | C8: 5 | D8: -183.53
A9: Check # 1 | C9: 12 | D9: 2004.44
A10: Check # 3 | C10: 27 | D10: 2004.44
A12: Disney/Hulu | C12: 23 | D12: -12 | G12: 1
A13: Dribble Up | C13: 26 | D13: -18.35
A14: Emergency Loan | C14: 9 | D14: -35
A15: Google | C15: 12 | D15: -102
A16: Greenlight | C16: 10 | D16: -5
A17: Greenlight | C17: 24 | D17: -6
A18: HOC | C18: 26 | D18: -7.55
A19: Kia Car Payment | C19: 5 | D19: -791.16
A20: Mortgage | C20: 3 | D20: -1560.81
A21: Netflix | C21: 9 | D21: -24
A22: Peacock | C22: 30 | D22: -3
A23: Pest Control | C23: 4 | D23: -33
A24: Tia Cap One | C24: 10 | D24: -80
... A38: YMCA After School | C38: 21 | D38: -98

Sheet Calculator
F1: © 2007-2019 Vertex42 LLC | I1: Strategies
A2: =HYPERLINK("https://www.vertex42.com/Calculators/debt-reduction-calculator.html","By Vertex42.com") -> By Vertex42.com | G2: =HYPERLINK("https://www.vertex42.com/Calculators/debt-reduction-calculator.html","HELP") -> HELP | I2: Snowball (Lowest Balance First)
I3: Avalanche (Highest Interest First)
B4: Balance Date: | C4: 45658 | I4: Stair-Stepper
I5: Order Entered In Table
B6: Creditor Information Table | I6: No Snowball
A7: Row | B7: Creditor | C7: Balance | D7: Interest | E7: Payment | F7: Custom | G7: Interest-only | I7: Custom - Highest First
A8: 1 | B8: Christmas Affirm | D8: 0 | G8: =ROUNDUP(OFFSET($C$7,ROW()-ROW($C$7),0,1,1)*OFFSET($D$7,ROW()-ROW($D$7),0,1,1)/12,2) -> 0 | I8: Custom - Lowest First
A9: =OFFSET(A9,-1,0,1,1)+1 -> 2 | B9: Christmas Affirm 1 | C9: 35.72 | D9: 0 | E9: 9.8 | G9: =ROUNDUP(OFFSET($C$7,ROW()-ROW($C$7),0,1,1)*OFFSET($D$7,ROW()-ROW($D$7),0,1,1)/12,2) -> 0
A10: =OFFSET(A10,-1,0,1,1)+1 -> 3 | B10: Christmas Affirm 2 | C10: 51.83 | D10: 0 | E10: 14.7 | G10: =ROUNDUP(OFFSET($C$7,ROW()-ROW($C$7),0,1,1)*OFFSET($D$7,ROW()-ROW($D$7),0,1,1)/12,2) -> 0
A11: =OFFSET(A11,-1,0,1,1)+1 -> 4 | B11: Christmas Affirm 3 | C11: 26.86 | D11: 0 | E11: 14.02 | G11: =ROUNDUP(OFFSET($C$7,ROW()-ROW($C$7),0,1,1)*OFFSET($D$7,ROW()-ROW($D$7),0,1,1)/12,2) -> 0
A12: =OFFSET(A12,-1,0,1,1)+1 -> 5 | B12: Christmas Affirm 4 | C12: 162.21 | D12: 0 | E12: 28.09 | G12: =ROUNDUP(OFFSET($C$7,ROW()-ROW($C$7),0,1,1)*OFFSET($D$7,ROW()-ROW($D$7),0,1,1)/12,2) -> 0
A13: =OFFSET(A13,-1,0,1,1)+1 -> 6 | B13: Christmas Affirm 5 | C13: 240.34 | D13: 0 | E13: 20.96 | G13: =ROUNDUP(OFFSET($C$7,ROW()-ROW($C$7),0,1,1)*OFFSET($D$7,ROW()-ROW($D$7),0,1,1)/12,2) -> 0
A14: =OFFSET(A14,-1,0,1,1)+1 -> 7 | B14: Tia Cap One | C14: 3200 | D14: 0.3174 | E14: 82 | G14: =ROUNDUP(OFFSET($C$7,ROW()-ROW($C$7),0,1,1)*OFFSET($D$7,ROW()-ROW($D$7),0,1,1)/12,2) -> 84.64
A15: =OFFSET(A15,-1,0,1,1)+1 -> 8 | B15: John Cap One | C15: 3800 | D15: 0.2974 | E15: 102 | G15: =ROUNDUP(OFFSET($C$7,ROW()-ROW($C$7),0,1,1)*OFFSET($D$7,ROW()-ROW($D$7),0,1,1)/12,2) -> 94.18
A16: =OFFSET(A16,-1,0,1,1)+1 -> 9 | B16: La'Kia | C16: 50000 | D16: 0.0928 | E16: 791.16 | G16: =ROUNDUP(OFFSET($C$7,ROW()-ROW($C$7),0,1,1)*OFFSET($D$7,ROW()-ROW($D$7),0,1,1)/12,2) -> 386.67
A17: =OFFSET(A17,-1,0,1,1)+1 -> 10 | B17: Tesla | C17: 38130 | D17: 0.11 | E17: 695.6 | G17: =ROUNDUP(OFFSET($C$7,ROW()-ROW($C$7),0,1,1)*OFFSET($D$7,ROW()-ROW($D$7),0,1,1)/12,2) -> 349.53 | J17: Black Tesla | M17: 695 | O17: 38130
A18: =OFFSET(A18,-1,0,1,1)+1 -> 11 | B18: Mortgage | C18: 181200 | D18: 0.0375 | E18: 1467.13 | G18: =ROUNDUP(OFFSET($C$7,ROW()-ROW($C$7),0,1,1)*OFFSET($D$7,ROW()-ROW($D$7),0,1,1)/12,2) -> 566.25
A19: =OFFSET(A19,-1,0,1,1)+1 -> 12 | B19: Upgrade Loan | C19: 15650.03 | D19: 0.18 | E19: 450.08 | G19: =ROUNDUP(OFFSET($C$7,ROW()-ROW($C$7),0,1,1)*OFFSET($D$7,ROW()-ROW($D$7),0,1,1)/12,2) -> 234.76
A20: =OFFSET(A20,-1,0,1,1)+1 -> 13 | B20: Emergency Loan | C20: 609.55 | D20: 0.2981 | E20: 35 | G20: =ROUNDUP(OFFSET($C$7,ROW()-ROW($C$7),0,1,1)*OFFSET($D$7,ROW()-ROW($D$7),0,1,1)/12,2) -> 15.15
A21: =OFFSET(A21,-1,0,1,1)+1 -> 14 | B21: James Braces | C21: 3100 | D21: 0.3 | E21: 206 | G21: =ROUNDUP(OFFSET($C$7,ROW()-ROW($C$7),0,1,1)*OFFSET($D$7,ROW()-ROW($D$7),0,1,1)/12,2) -> 77.5
A22: =OFFSET(A22,-1,0,1,1)+1 -> 15 | G22: =ROUNDUP(OFFSET($C$7,ROW()-ROW($C$7),0,1,1)*OFFSET($D$7,ROW()-ROW($D$7),0,1,1)/12,2) -> 0
A23: =OFFSET(A23,-1,0,1,1)+1 -> 16 | G23: =ROUNDUP(OFFSET($C$7,ROW()-ROW($C$7),0,1,1)*OFFSET($D$7,ROW()-ROW($D$7),0,1,1)/12,2) -> 0
A24: =OFFSET(A24,-1,0,1,1)+1 -> 17 | G24: =ROUNDUP(OFFSET($C$7,ROW()-ROW($C$7),0,1,1)*OFFSET($D$7,ROW()-ROW($D$7),0,1,1)/12,2) -> 0
A25: =OFFSET(A25,-1,0,1,1)+1 -> 18 | G25: =ROUNDUP(OFFSET($C$7,ROW()-ROW($C$7),0,1,1)*OFFSET($D$7,ROW()-ROW($D$7),0,1,1)/12,2) -> 0
A26: =OFFSET(A26,-1,0,1,1)+1 -> 19 | G26: =ROUNDUP(OFFSET($C$7,ROW()-ROW($C$7),0,1,1)*OFFSET($D$7,ROW()-ROW($D$7),0,1,1)/12,2) -> 0
A27: =OFFSET(A27,-1,0,1,1)+1 -> 20 | G27: =ROUNDUP(OFFSET($C$7,ROW()-ROW($C$7),0,1,1)*OFFSET($D$7,ROW()-ROW($D$7),0,1,1)/12,2) -> 0
A28: =OFFSET(A28,-1,0,1,1)+1 -> 21 | G28: =ROUNDUP(OFFSET($C$7,ROW()-ROW($C$7),0,1,1)*OFFSET($D$7,ROW()-ROW($D$7),0,1,1)/12,2) -> 0
A29: =OFFSET(A29,-1,0,1,1)+1 -> 22 | G29: =ROUNDUP(OFFSET($C$7,ROW()-ROW($C$7),0,1,1)*OFFSET($D$7,ROW()-ROW($D$7),0,1,1)/12,2) -> 0
A30: =OFFSET(A30,-1,0,1,1)+1 -> 23 | G30: =ROUNDUP(OFFSET($C$7,ROW()-ROW($C$7),0,1,1)*OFFSET($D$7,ROW()-ROW($D$7),0,1,1)/12,2) -> 0
A31: =OFFSET(A31,-1,0,1,1)+1 -> 24 | G31: =ROUNDUP(OFFSET($C$7,ROW()-ROW($C$7),0,1,1)*OFFSET($D$7,ROW()-ROW($D$7),0,1,1)/12,2) -> 0
A32: =OFFSET(A32,-1,0,1,1)+1 -> 25 | G32: =ROUNDUP(OFFSET($C$7,ROW()-ROW($C$7),0,1,1)*OFFSET($D$7,ROW()-ROW($D$7),0,1,1)/12,2) -> 0
A33: =OFFSET(A33,-1,0,1,1)+1 -> 26 | G33: =ROUNDUP(OFFSET($C$7,ROW()-ROW($C$7),0,1,1)*OFFSET($D$7,ROW()-ROW($D$7),0,1,1)/12,2) -> 0
... A46: =OFFSET(A46,-1,0,1,1)+1 -> 39 | G46: =ROUNDUP(OFFSET($C$7,ROW()-ROW($C$7),0,1,1)*OFFSET($D$7,ROW()-ROW($D$7),0,1,1)/12,2) -> 0
B47: Total: | C47: =SUM(C8:C30) -> 296206.54 | D47: Total: | E47: =SUM(E8:E30) -> 3916.54
A49: Monthly Payment | C49: 3862 | D49: =IF(NOT(Calculator!snowball),"Not Applicable (No Snowball)",IF(C49<=E47,"Too Low"," . ")) -> Too Low
A50: Initial Snowball
B52: Strategy: | C52: Snowball (Lowest Balance First) | F52: =MATCH(C52,I2:I8,0) -> 1
F53: =if(Calculator!strategy=5,false,true) -> TRUE
B54: Results are only estimates
B55: Creditors in | C55: Original | D55: Total Interest | E55: Years to | F55: Month Paid
B56: Chosen Order | C56: Balance | D56: Paid | E56: Pay Off | F56: Off
B57: {=TRANSPOSE(PaymentSchedule!$E$7:$AG$7)} -> Christmas Affirm 3 | C57: {=TRANSPOSE(PaymentSchedule!$E$8:$AH$8)} -> 26.86 | D57: {=TRANSPOSE(PaymentSchedule!$E$13:$AH$13)} -> 0 | E57: {=TRANSPOSE(PaymentSchedule!$E$11:$AH$11)/12} -> 0.16666667 | F57: {=TRANSPOSE(PaymentSchedule!$E$12:$AH$12)} -> 45689 | G57: {=TRANSPOSE(PaymentSchedule!E14:N14)} -> .
B58: Christmas Affirm 1 | C58: 35.72 | D58: 0 | E58: 0.25 | F58: 45717 | G58: .
B59: Christmas Affirm 2 | C59: 51.83 | D59: 0 | E59: 0.25 | F59: 45717 | G59: .
B60: Christmas Affirm 4 | C60: 162.21 | D60: 0 | E60: 0.33333333 | F60: 45748 | G60: .
B61: Christmas Affirm 5 | C61: 240.34 | D61: 0 | E61: 0.41666667 | F61: 45778 | G61: .
B62: Emergency Loan | C62: 609.55 | D62: 152.09 | E62: 1.25 | F62: 46082 | G62: .
B63: James Braces | C63: 3100 | D63: 1248.19 | E63: 2.1666667 | F63: 46419 | G63: .
B64: Tia Cap One | C64: 3200 | D64: 2409.27 | E64: 2.3333333 | F64: 46478 | G64: .
B65: John Cap One | C65: 3800 | D65: 2356.8 | E65: 2.75 | F65: 46631 | G65: .
B66: Upgrade Loan | C66: 15650.03 | D66: 6159.42 | E66: 3.4166667 | F66: 46874 | G66: .
B67: Tesla | C67: 38130 | D67: 16719.58 | E67: 5.1666667 | F67: 47515
B68: La'Kia | C68: 50000 | D68: 17759.83 | E68: 5.8333333 | F68: 47757
B69: Mortgage | C69: 181200 | D69: 34604.94 | E69: 7.9166667 | F69: 48519
C70: 0 | D70: 0 | E70: 0
C71: 0 | D71: 0 | E71: 0
C72: 0 | D72: 0 | E72: 0
C73: 0 | D73: 0 | E73: 0
C74: 0 | D74: 0 | E74: 0
C75: 0 | D75: 0 | E75: 0
C76: 0 | D76: 0 | E76: 0
C77: 0 | D77: 0 | E77: 0
C78: 0 | D78: 0 | E78: 0
C79: 0 | D79: 0 | E79: 0
C80: 0 | D80: 0 | E80: 0
C81: 0 | D81: 0 | E81: 0
... C85: 0 | D85: 0 | E85: 0
E86: 0
C92: Total Interest Paid: | D92: =PaymentSchedule!E16 -> 81410.12 | E92: (Lower is Better)
A94: =HYPERLINK("https://www.vertex42.com/Calculators/debt-reduction-calculator.html","Debt Reduction Calculator by Vertex42.com") -> Debt Reduction Calculator by Vertex42.com
B97: [42]

Sheet PaymentSchedule
A1: Debt Snowball Payment Schedule | L1: © 2007-2019 Vertex42 LLC
A2: Results are only estimates. Only edit the yellow cells. | I2: =HYPERLINK("https://www.vertex42.com/Calculators/debt-reduction-calculator.html","https://www.vertex42.com/Calculators/debt-reduction-calculator.html") -> https://www.vertex42.com/Calculators/debt-reduction-calculator.html
A4: Strategy: | E4: {=INDEX(Calculator!I2:I8,Calculator!strategy)} -> Snowball (Lowest Balance First)
A5: Monthly Payment: | E5: =IF(NOT(Calculator!snowball),"Variable",Calculator!C49) -> 3862
AK6: row | AL6: col
A7: Creditor: | E7: {=IF(ISERROR(Order!B73),"",IF(ISBLANK(INDEX(Calculator!$B$8:$B$46,Order!B73))," - ",INDEX(Calculator!$B$8:$B$46,Order!B73)))} -> Christmas Affirm 3 | F7: {=IF(ISERROR(Order!C73),"",IF(ISBLANK(INDEX(Calculator!$B$8:$B$46,Order!C73))," - ",INDEX(Calculator!$B$8:$B$46,Order!C73)))} -> Christmas Affirm 1 | G7: {=IF(ISERROR(Order!D73),"",IF(ISBLANK(INDEX(Calculator!$B$8:$B$46,Order!D73))," - ",INDEX(Calculator!$B$8:$B$46,Order!D73)))} -> Christmas Affirm 2 | H7: {=IF(ISERROR(Order!E73),"",IF(ISBLANK(INDEX(Calculator!$B$8:$B$46,Order!E73))," - ",INDEX(Calculator!$B$8:$B$46,Order!E73)))} -> Christmas Affirm 4 | I7: {=IF(ISERROR(Order!F73),"",IF(ISBLANK(INDEX(Calculator!$B$8:$B$46,Order!F73))," - ",INDEX(Calculator!$B$8:$B$46,Order!F73)))} -> Christmas Affirm 5 | J7: {=IF(ISERROR(Order!G73),"",IF(ISBLANK(INDEX(Calculator!$B$8:$B$46,Order!G73))," - ",INDEX(Calculator!$B$8:$B$46,Order!G73)))} -> Emergency Loan | K7: {=IF(ISERROR(Order!H73),"",IF(ISBLANK(INDEX(Calculator!$B$8:$B$46,Order!H73))," - ",INDEX(Calculator!$B$8:$B$46,Order!H73)))} -> James Braces | L7: {=IF(ISERROR(Order!I73),"",IF(ISBLANK(INDEX(Calculator!$B$8:$B$46,Order!I73))," - ",INDEX(Calculator!$B$8:$B$46,Order!I73)))} -> Tia Cap One | ... AH7: {=IF(ISERROR(Order!AE73),"",IF(ISBLANK(INDEX(Calculator!$B$8:$B$46,Order!AE73))," - ",INDEX(Calculator!$B$8:$B$46,Order!AE73)))} | AK7: =MATCH(B21,$B$21:$B356,0) -> 1 | AL7: =MATCH('Jan 2025'!P28,$E19:$AG19,0) -> 8
A8: Balance: | E8: {=IF(ISERROR(Order!B73),0,INDEX(Calculator!$C$8:$C$46,Order!B73))} -> 26.86 | F8: {=IF(ISERROR(Order!C73),0,INDEX(Calculator!$C$8:$C$46,Order!C73))} -> 35.72 | G8: {=IF(ISERROR(Order!D73),0,INDEX(Calculator!$C$8:$C$46,Order!D73))} -> 51.83 | H8: {=IF(ISERROR(Order!E73),0,INDEX(Calculator!$C$8:$C$46,Order!E73))} -> 162.21 | I8: {=IF(ISERROR(Order!F73),0,INDEX(Calculator!$C$8:$C$46,Order!F73))} -> 240.34 | J8: {=IF(ISERROR(Order!G73),0,INDEX(Calculator!$C$8:$C$46,Order!G73))} -> 609.55 | K8: {=IF(ISERROR(Order!H73),0,INDEX(Calculator!$C$8:$C$46,Order!H73))} -> 3100 | L8: {=IF(ISERROR(Order!I73),0,INDEX(Calculator!$C$8:$C$46,Order!I73))} -> 3200 | ... AG8: {=IF(ISERROR(Order!AD73),0,INDEX(Calculator!$C$8:$C$46,Order!AD73))} -> 0 | AQ8: 204
A9: Rate: | E9: {=IF(ISERROR(Order!B73),0,INDEX(Calculator!$D$8:$D$46,Order!B73))} -> 0 | F9: {=IF(ISERROR(Order!C73),0,INDEX(Calculator!$D$8:$D$46,Order!C73))} -> 0 | G9: {=IF(ISERROR(Order!D73),0,INDEX(Calculator!$D$8:$D$46,Order!D73))} -> 0 | H9: {=IF(ISERROR(Order!E73),0,INDEX(Calculator!$D$8:$D$46,Order!E73))} -> 0 | I9: {=IF(ISERROR(Order!F73),0,INDEX(Calculator!$D$8:$D$46,Order!F73))} -> 0 | J9: {=IF(ISERROR(Order!G73),0,INDEX(Calculator!$D$8:$D$46,Order!G73))} -> 0.2981 | K9: {=IF(ISERROR(Order!H73),0,INDEX(Calculator!$D$8:$D$46,Order!H73))} -> 0.3 | L9: {=IF(ISERROR(Order!I73),0,INDEX(Calculator!$D$8:$D$46,Order!I73))} -> 0.3174 | ... AG9: {=IF(ISERROR(Order!AD73),0,INDEX(Calculator!$D$8:$D$46,Order!AD73))} -> 0 | AQ9: 176.71
A10: Base Payment: | E10: {=IF(ISERROR(Order!B73),0,INDEX(Calculator!$E$8:$E$46,Order!B73))} -> 14.02 | F10: {=IF(ISERROR(Order!C73),0,INDEX(Calculator!$E$8:$E$46,Order!C73))} -> 9.8 | G10: {=IF(ISERROR(Order!D73),0,INDEX(Calculator!$E$8:$E$46,Order!D73))} -> 14.7 | H10: {=IF(ISERROR(Order!E73),0,INDEX(Calculator!$E$8:$E$46,Order!E73))} -> 28.09 | I10: {=IF(ISERROR(Order!F73),0,INDEX(Calculator!$E$8:$E$46,Order!F73))} -> 20.96 | J10: {=IF(ISERROR(Order!G73),0,INDEX(Calculator!$E$8:$E$46,Order!G73))} -> 35 | K10: {=IF(ISERROR(Order!H73),0,INDEX(Calculator!$E$8:$E$46,Order!H73))} -> 206 | L10: {=IF(ISERROR(Order!I73),0,INDEX(Calculator!$E$8:$E$46,Order!I73))} -> 82 | ... AG10: {=IF(ISERROR(Order!AD73),0,INDEX(Calculator!$E$8:$E$46,Order!AD73))} -> 0
A11: Months to Pay Off: | E11: {=IF(E8>0,1+MAX((ROW(E21:E354)-ROW(E$21))*(E21:E354>0)),0)} -> 2 | F11: {=IF(F8>0,1+MAX((ROW(F21:F354)-ROW(F$21))*(F21:F354>0)),0)} -> 3 | G11: {=IF(G8>0,1+MAX((ROW(G21:G354)-ROW(G$21))*(G21:G354>0)),0)} -> 3 | H11: {=IF(H8>0,1+MAX((ROW(H21:H354)-ROW(H$21))*(H21:H354>0)),0)} -> 4 | I11: {=IF(I8>0,1+MAX((ROW(I21:I354)-ROW(I$21))*(I21:I354>0)),0)} -> 5 | J11: {=IF(J8>0,1+MAX((ROW(J21:J354)-ROW(J$21))*(J21:J354>0)),0)} -> 15 | K11: {=IF(K8>0,1+MAX((ROW(K21:K354)-ROW(K$21))*(K21:K354>0)),0)} -> 26 | L11: {=IF(L8>0,1+MAX((ROW(L21:L354)-ROW(L$21))*(L21:L354>0)),0)} -> 28 | ... AG11: {=IF(AG8>0,1+MAX((ROW(AG21:AG354)-ROW(AG$21))*(AG21:AG354>0)),0)} -> 0 | AK11: {=-INDEX($E$21:$AG356,MATCH(B21,$B$21:$B356,0),MATCH('Jan 2025'!P28,$E19:$AG19,0))} -> -82
A12: Month Paid Off: | E12: =IF(E8>0,INDEX($B$21:$B$354,E11),"") -> 45689 | F12: =IF(F8>0,INDEX($B$21:$B$354,F11),"") -> 45717 | G12: =IF(G8>0,INDEX($B$21:$B$354,G11),"") -> 45717 | H12: =IF(H8>0,INDEX($B$21:$B$354,H11),"") -> 45748 | I12: =IF(I8>0,INDEX($B$21:$B$354,I11),"") -> 45778 | J12: =IF(J8>0,INDEX($B$21:$B$354,J11),"") -> 46082 | K12: =IF(K8>0,INDEX($B$21:$B$354,K11),"") -> 46419 | L12: =IF(L8>0,INDEX($B$21:$B$354,L11),"") -> 46478 | ... AG12: =IF(AG8>0,INDEX($B$21:$B$354,AG11),"")
A13: Total Interest: | E13: =IF(E320=0,SUM(BN21:BN354),NA()) -> 0 | F13: =IF(F320=0,SUM(BO21:BO354),NA()) -> 0 | G13: =IF(G320=0,SUM(BP21:BP354),NA()) -> 0 | H13: =IF(H320=0,SUM(BQ21:BQ354),NA()) -> 0 | I13: =IF(I320=0,SUM(BR21:BR354),NA()) -> 0 | J13: =IF(J320=0,SUM(BS21:BS354),NA()) -> 152.09 | K13: =IF(K320=0,SUM(BT21:BT354),NA()) -> 1248.19 | L13: =IF(L320=0,SUM(BU21:BU354),NA()) -> 2409.27 | ... AG13: =IF(AG320=0,SUM(CP21:CP354),NA()) -> 0
A14: Error Code: | E14: =IF(E320>0,">"&$A$320&" Payments"," . ") -> . | F14: =IF(F320>0,">"&$A$320&" Payments"," . ") -> . | G14: =IF(G320>0,">"&$A$320&" Payments"," . ") -> . | H14: =IF(H320>0,">"&$A$320&" Payments"," . ") -> . | I14: =IF(I320>0,">"&$A$320&" Payments"," . ") -> . | J14: =IF(J320>0,">"&$A$320&" Payments"," . ") -> . | K14: =IF(K320>0,">"&$A$320&" Payments"," . ") -> . | L14: =IF(L320>0,">"&$A$320&" Payments"," . ") -> . | ... AG14: =IF(AG320>0,">"&$A$320&" Payments"," . ") -> .
A16: Total Interest: | E16: =SUM(E13:AG13) -> 81410.12
E18: Monthly Payments | AI18: Balance AFTER Payment | BN18: Interest | CT18: Payment Before Snowball
A19: No. | B19: Month | C19: Snowball | D19: Additional | E19: =E7 -> Christmas Affirm 3 | F19: =F7 -> Christmas Affirm 1 | G19: =G7 -> Christmas Affirm 2 | H19: =H7 -> Christmas Affirm 4 | I19: =I7 -> Christmas Affirm 5 | J19: =J7 -> Emergency Loan | K19: =K7 -> James Braces | L19: =L7 -> Tia Cap One | ... AG19: =AG7 | AH19: Total Balance | AI19: =E19 -> Christmas Affirm 3 | AJ19: =F19 -> Christmas Affirm 1 | AK19: =G19 -> Christmas Affirm 2 | AL19: =H19 -> Christmas Affirm 4 | AM19: =I19 -> Christmas Affirm 5 | AN19: =J19 -> Emergency Loan | AO19: =K19 -> James Braces | AP19: =L19 -> Tia Cap One | ... BK19: =AG19 | BL19: Total Balance | BN19: =E19 -> Christmas Affirm 3 | BO19: =F19 -> Christmas Affirm 1 | BP19: =G19 -> Christmas Affirm 2 | BQ19: =H19 -> Christmas Affirm 4 | BR19: =I19 -> Christmas Affirm 5 | BS19: =J19 -> Emergency Loan | BT19: =K19 -> James Braces | BU19: =L19 -> Tia Cap One | ... CP19: =AG19 | CR19: TOTAL | CT19: =E19 -> Christmas Affirm 3 | CU19: =F19 -> Christmas Affirm 1 | CV19: =G19 -> Christmas Affirm 2 | CW19: =H19 -> Christmas Affirm 4 | CX19: =I19 -> Christmas Affirm 5 | CY19: =J19 -> Emergency Loan | CZ19: =K19 -> James Braces | DA19: =L19 -> Tia Cap One | ... DV19: =AG19 | DY19: TOTAL | EA19: Extra Payment
AH20: =SUM(AI20:BK20) -> 296206.54 | AI20: =E8 -> 26.86 | AJ20: =F8 -> 35.72 | AK20: =G8 -> 51.83 | AL20: =H8 -> 162.21 | AM20: =I8 -> 240.34 | AN20: =J8 -> 609.55 | AO20: =K8 -> 3100 | AP20: =L8 -> 3200 | ... BK20: =AG8 -> 0 | BL20: =SUM(AI20:BK20) -> 296206.54 | EA20: =E7 -> Christmas Affirm 3 | EB20: =F7 -> Christmas Affirm 1 | EC20: =G7 -> Christmas Affirm 2 | ED20: =H7 -> Christmas Affirm 4 | EE20: =I7 -> Christmas Affirm 5 | EF20: =J7 -> Emergency Loan | EG20: =K7 -> James Braces | EH20: =L7 -> Tia Cap One | ... FE20: =AI7
A21: =IF(SUM(AI20:BK20)<=0,"",A20+1) -> 1 | B21: 45658 | C21: =IF(A21="","",IF(Calculator!snowball,IF(($E$5-DY21)<0,0,$E$5-DY21),0)+D21) -> 0 | E21: =CT21+EA22 -> 14.02 | F21: =CU21+EB22 -> 9.8 | G21: =CV21+EC22 -> 14.7 | H21: =CW21+ED22 -> 28.09 | I21: =CX21+EE22 -> 20.96 | J21: =CY21+EF22 -> 35 | L21: =DA21+EH22 -> 82 | M21: =DB21+EI22 -> 102 | N21: =DC21+EJ22 -> 450.08 | P21: =DE21+EL22 -> 791.16 | Q21: 1560.81 | R21: =DG21+EN22 -> 0 | S21: =DH21+EO22 -> 0 | T21: =DI21+EP22 -> 0 | U21: =DJ21+EQ22 -> 0 | V21: =DK21+ER22 -> 0 | W21: =DL21+ES22 -> 0 | X21: =DM21+ET22 -> 0 | Y21: =DN21+EU22 -> 0 | ... AG21: =DV21+FC22 -> 0 | AH21: =SUM(AI21:BK21) -> 294689.86 | AI21: =IF(E$8=0,0,ROUND(AI20-(E21-BN21),2)) -> 12.84 | AJ21: =IF(F$8=0,0,ROUND(AJ20-(F21-BO21),2)) -> 25.92 | AK21: =IF(G$8=0,0,ROUND(AK20-(G21-BP21),2)) -> 37.13 | AL21: =IF(H$8=0,0,ROUND(AL20-(H21-BQ21),2)) -> 134.12 | AM21: =IF(I$8=0,0,ROUND(AM20-(I21-BR21),2)) -> 219.38 | AN21: =IF(J$8=0,0,ROUND(AN20-(J21-BS21),2)) -> 589.69 | AO21: =IF(K$8=0,0,ROUND(AO20-(K21-BT21),2)) -> 3177.5 | AP21: =IF(L$8=0,0,ROUND(AP20-(L21-BU21),2)) -> 3202.64 | ... AS21: =IF(O$8=0,0,ROUND(AS20-(O21-BX21),2)) -> 38479.53 | AT21: =IF(P$8=0,0,ROUND(AT20-(P21-BX21),2)) -> 49558.37 | AU21: =IF(Q$8=0,0,ROUND(AU20-(Q21-BY21),2)) -> 180025.86 | AV21: =IF(R$8=0,0,ROUND(AV20-(R21-BZ21),2)) -> 0 | AW21: =IF(S$8=0,0,ROUND(AW20-(S21-CA21),2)) -> 0 | AX21: =IF(T$8=0,0,ROUND(AX20-(T21-CB21),2)) -> 0 | AY21: =IF(U$8=0,0,ROUND(AY20-(U21-CC21),2)) -> 0 | AZ21: =IF(V$8=0,0,ROUND(AZ20-(V21-CD21),2)) -> 0 | BA21: =IF(W$8=0,0,ROUND(BA20-(W21-CE21),2)) -> 0 | ... BK21: =IF(AG$8=0,0,ROUND(BK20-(AG21-CO21),2)) -> 0 | BL21: =SUM(AI21:BK21) -> 294689.86 | BN21: =ROUND(AI20*E$9/12,2) -> 0 | BO21: =ROUND(AJ20*F$9/12,2) -> 0 | BP21: =ROUND(AK20*G$9/12,2) -> 0 | BQ21: =ROUND(AL20*H$9/12,2) -> 0 | BR21: =ROUND(AM20*I$9/12,2) -> 0 | BS21: =ROUND(AN20*J$9/12,2) -> 15.14 | BT21: =ROUND(AO20*K$9/12,2) -> 77.5 | BU21: =ROUND(AP20*L$9/12,2) -> 84.64 | ... CP21: =ROUND(BK20*AG$9/12,2) -> 0 | CR21: =SUM(BN21:CP21) -> 1808.66 | CT21: =IF(AI20>0,IF((AI20+BN21)<E$10,AI20+BN21,E$10),0) -> 14.02 | CU21: =IF(AJ20>0,IF((AJ20+BO21)<F$10,AJ20+BO21,F$10),0) -> 9.8 | CV21: =IF(AK20>0,IF((AK20+BP21)<G$10,AK20+BP21,G$10),0) -> 14.7 | CW21: =IF(AL20>0,IF((AL20+BQ21)<H$10,AL20+BQ21,H$10),0) -> 28.09 | CX21: =IF(AM20>0,IF((AM20+BR21)<I$10,AM20+BR21,I$10),0) -> 20.96 | CY21: =IF(AN20>0,IF((AN20+BS21)<J$10,AN20+BS21,J$10),0) -> 35 | CZ21: =IF(AO20>0,IF((AO20+BT21)<K$10,AO20+BT21,K$10),0) -> 206 | DA21: =IF(AP20>0,IF((AP20+BU21)<L$10,AP20+BU21,L$10),0) -> 82 | ... DX21: =IF(BM20>0,IF((BM20+CR21)<AI$10,BM20+CR21,AI$10),0) -> 0 | DY21: =SUM(CT21:DX21) -> 3916.54
A22: =IF(SUM(AI21:BK21)<=0,"",A21+1) -> 2 | B22: 45689 | C22: 0 | E22: =CT22+EA23 -> 12.84 | F22: =CU22+EB23 -> 9.8 | G22: =CV22+EC23 -> 14.7 | H22: =CW22+ED23 -> 28.09 | I22: =CX22+EE23 -> 20.96 | J22: =CY22+EF23 -> 35 | L22: =DA22+EH23 -> 82 | M22: =DB22+EI23 -> 102 | N22: =DC22+EJ23 -> 450.08 | P22: =DE22+EL23 -> 791.16 | Q22: 1560.81 | R22: =DG22+EN23 -> 0 | S22: =DH22+EO23 -> 0 | T22: =DI22+EP23 -> 0 | U22: =DJ22+EQ23 -> 0 | V22: =DK22+ER23 -> 0 | W22: =DL22+ES23 -> 0 | X22: =DM22+ET23 -> 0 | Y22: =DN22+EU23 -> 0 | ... AG22: =DV22+FC23 -> 0 | AH22: =SUM(AI22:BK22) -> 293175.43 | AI22: =IF(E$8=0,0,ROUND(AI21-(E22-BN22),2)) -> 0 | AJ22: =IF(F$8=0,0,ROUND(AJ21-(F22-BO22),2)) -> 16.12 | AK22: =IF(G$8=0,0,ROUND(AK21-(G22-BP22),2)) -> 22.43 | AL22: =IF(H$8=0,0,ROUND(AL21-(H22-BQ22),2)) -> 106.03 | AM22: =IF(I$8=0,0,ROUND(AM21-(I22-BR22),2)) -> 198.42 | AN22: =IF(J$8=0,0,ROUND(AN21-(J22-BS22),2)) -> 569.34 | AO22: =IF(K$8=0,0,ROUND(AO21-(K22-BT22),2)) -> 3256.94 | AP22: =IF(L$8=0,0,ROUND(AP21-(L22-BU22),2)) -> 3205.35 | ... AS22: =IF(O$8=0,0,ROUND(AS21-(O22-BX22),2)) -> 38832.26 | AT22: =IF(P$8=0,0,ROUND(AT21-(P22-BX22),2)) -> 49119.94 | AU22: =IF(Q$8=0,0,ROUND(AU21-(Q22-BY22),2)) -> 178848.3 | AV22: =IF(R$8=0,0,ROUND(AV21-(R22-BZ22),2)) -> 0 | AW22: =IF(S$8=0,0,ROUND(AW21-(S22-CA22),2)) -> 0 | AX22: =IF(T$8=0,0,ROUND(AX21-(T22-CB22),2)) -> 0 | AY22: =IF(U$8=0,0,ROUND(AY21-(U22-CC22),2)) -> 0 | AZ22: =IF(V$8=0,0,ROUND(AZ21-(V22-CD22),2)) -> 0 | BA22: =IF(W$8=0,0,ROUND(BA21-(W22-CE22),2)) -> 0 | ... BK22: =IF(AG$8=0,0,ROUND(BK21-(AG22-CO22),2)) -> 0 | BL22: =SUM(AI22:BK22) -> 293175.43 | BN22: =ROUND(AI21*E$9/12,2) -> 0 | BO22: =ROUND(AJ21*F$9/12,2) -> 0 | BP22: =ROUND(AK21*G$9/12,2) -> 0 | BQ22: =ROUND(AL21*H$9/12,2) -> 0 | BR22: =ROUND(AM21*I$9/12,2) -> 0 | BS22: =ROUND(AN21*J$9/12,2) -> 14.65 | BT22: =ROUND(AO21*K$9/12,2) -> 79.44 | BU22: =ROUND(AP21*L$9/12,2) -> 84.71 | ... CP22: =ROUND(BK21*AG$9/12,2) -> 0 | CR22: =SUM(BN22:CP22) -> 1802.86 | CT22: =IF(AI21>0,IF((AI21+BN22)<E$10,AI21+BN22,E$10),0) -> 12.84 | CU22: =IF(AJ21>0,IF((AJ21+BO22)<F$10,AJ21+BO22,F$10),0) -> 9.8 | CV22: =IF(AK21>0,IF((AK21+BP22)<G$10,AK21+BP22,G$10),0) -> 14.7 | CW22: =IF(AL21>0,IF((AL21+BQ22)<H$10,AL21+BQ22,H$10),0) -> 28.09 | CX22: =IF(AM21>0,IF((AM21+BR22)<I$10,AM21+BR22,I$10),0) -> 20.96 | CY22: =IF(AN21>0,IF((AN21+BS22)<J$10,AN21+BS22,J$10),0) -> 35 | CZ22: =IF(AO21>0,IF((AO21+BT22)<K$10,AO21+BT22,K$10),0) -> 206 | DA22: =IF(AP21>0,IF((AP21+BU22)<L$10,AP21+BU22,L$10),0) -> 82 | ... DX22: =IF(BM21>0,IF((BM21+CR22)<AI$10,BM21+CR22,AI$10),0) -> 0 | DY22: =SUM(CT22:DX22) -> 3915.36 | EA22: =IF(AI20<=0,0,IF(CT21+$C21>AI20+BN21,AI20+BN21-CT21,$C21)) -> 0 | EB22: =IF(AJ20<=0,0,IF($C21<=SUM($EA22:EA22),0,IF(CU21+$C21-SUM($EA22:EA22)>AJ20+BO21,AJ20+BO21-CU21,$C21-SUM($EA22:EA22)))) -> 0 | EC22: =IF(AK20<=0,0,IF($C21<=SUM($EA22:EB22),0,IF(CV21+$C21-SUM($EA22:EB22)>AK20+BP21,AK20+BP21-CV21,$C21-SUM($EA22:EB22)))) -> 0 | ED22: =IF(AL20<=0,0,IF($C21<=SUM($EA22:EC22),0,IF(CW21+$C21-SUM($EA22:EC22)>AL20+BQ21,AL20+BQ21-CW21,$C21-SUM($EA22:EC22)))) -> 0 | EE22: =IF(AM20<=0,0,IF($C21<=SUM($EA22:ED22),0,IF(CX21+$C21-SUM($EA22:ED22)>AM20+BR21,AM20+BR21-CX21,$C21-SUM($EA22:ED22)))) -> 0 | EF22: =IF(AN20<=0,0,IF($C21<=SUM($EA22:EE22),0,IF(CY21+$C21-SUM($EA22:EE22)>AN20+BS21,AN20+BS21-CY21,$C21-SUM($EA22:EE22)))) -> 0 | EG22: =IF(AO20<=0,0,IF($C21<=SUM($EA22:EF22),0,IF(CZ21+$C21-SUM($EA22:EF22)>AO20+BT21,AO20+BT21-CZ21,$C21-SUM($EA22:EF22)))) -> 0 | EH22: =IF(AP20<=0,0,IF($C21<=SUM($EA22:EG22),0,IF(DA21+$C21-SUM($EA22:EG22)>AP20+BU21,AP20+BU21-DA21,$C21-SUM($EA22:EG22)))) -> 0 | EI22: =IF(AQ20<=0,0,IF($C21<=SUM($EA22:EH22),0,IF(DB21+$C21-SUM($EA22:EH22)>AQ20+BV21,AQ20+BV21-DB21,$C21-SUM($EA22:EH22)))) -> 0 | ... FC22: =IF(BK20<=0,0,IF($C21<=SUM($EA22:FB22),0,IF(DV21+$C21-SUM($EA22:FB22)>BK20+CP21,BK20+CP21-DV21,$C21-SUM($EA22:FB22)))) -> 0
A23: =IF(SUM(AI22:BK22)<=0,"",A22+1) -> 3 | B23: 45717 | C23: =IF(A23="","",IF(Calculator!snowball,IF(($E$5-DY23)<0,0,$E$5-DY23),0)+D23) -> 0 | E23: =CT23+EA24 -> 0 | F23: 16.12 | G23: 22.43 | H23: =CW23+ED24 -> 28.09 | I23: =CX23+EE24 -> 20.96 | J23: =CY23+EF24 -> 35 | K23: 600 | L23: =DA23+EH24 -> 82 | M23: =DB23+EI24 -> 102 | N23: =DC23+EJ24 -> 450.08 | P23: =DE23+EL24 -> 791.16 | Q23: 1487.37 | R23: =DG23+EN24 -> 0 | S23: =DH23+EO24 -> 0 | T23: =DI23+EP24 -> 0 | U23: =DJ23+EQ24 -> 0 | V23: =DK23+ER24 -> 0 | W23: =DL23+ES24 -> 0 | X23: =DM23+ET24 -> 0 | Y23: =DN23+EU24 -> 0 | ... AG23: =DV23+FC24 -> 0 | AH23: =SUM(AI23:BK23) -> 291134.36 | AI23: =IF(E$8=0,0,ROUND(AI22-(E23-BN23),2)) -> 0 | AJ23: 0 | AK23: 0 | AL23: =IF(H$8=0,0,ROUND(AL22-(H23-BQ23),2)) -> 77.94 | AM23: =IF(I$8=0,0,ROUND(AM22-(I23-BR23),2)) -> 177.46 | AN23: =IF(J$8=0,0,ROUND(AN22-(J23-BS23),2)) -> 548.48 | AO23: =IF(K$8=0,0,ROUND(AO22-(K23-BT23),2)) -> 2738.36 | AP23: =IF(L$8=0,0,ROUND(AP22-(L23-BU23),2)) -> 3208.13 | AQ23: =IF(M$8=0,0,ROUND(AQ22-(M23-BV23),2)) -> 3775.94 | AR23: =IF(N$8=0,0,ROUND(AR22-(N23-BW23),2)) -> 14994.3 | AS23: =IF(O$8=0,0,ROUND(AS22-(O23-BX23),2)) -> 39188.22 | AT23: =IF(P$8=0,0,ROUND(AT22-(P23-BX23),2)) -> 48684.74 | AU23: =IF(Q$8=0,0,ROUND(AU22-(Q23-BY23),2)) -> 177740.79 | AV23: =IF(R$8=0,0,ROUND(AV22-(R23-BZ23),2)) -> 0 | AW23: =IF(S$8=0,0,ROUND(AW22-(S23-CA23),2)) -> 0 | AX23: =IF(T$8=0,0,ROUND(AX22-(T23-CB23),2)) -> 0 | AY23: =IF(U$8=0,0,ROUND(AY22-(U23-CC23),2)) -> 0 | AZ23: =IF(V$8=0,0,ROUND(AZ22-(V23-CD23),2)) -> 0 | BA23: =IF(W$8=0,0,ROUND(BA22-(W23-CE23),2)) -> 0 | ... BK23: =IF(AG$8=0,0,ROUND(BK22-(AG23-CO23),2)) -> 0 | BL23: =SUM(AI23:BK23) -> 291134.36 | BN23: =ROUND(AI22*E$9/12,2) -> 0 | BO23: =ROUND(AJ22*F$9/12,2) -> 0 | BP23: =ROUND(AK22*G$9/12,2) -> 0 | BQ23: =ROUND(AL22*H$9/12,2) -> 0 | BR23: =ROUND(AM22*I$9/12,2) -> 0 | BS23: =ROUND(AN22*J$9/12,2) -> 14.14 | BT23: =ROUND(AO22*K$9/12,2) -> 81.42 | BU23: =ROUND(AP22*L$9/12,2) -> 84.78 | ... CP23: =ROUND(BK22*AG$9/12,2) -> 0 | CR23: =SUM(BN23:CP23) -> 1797.08 | CT23: =IF(AI22>0,IF((AI22+BN23)<E$10,AI22+BN23,E$10),0) -> 0 | CU23: =IF(AJ22>0,IF((AJ22+BO23)<F$10,AJ22+BO23,F$10),0) -> 9.8 | CV23: =IF(AK22>0,IF((AK22+BP23)<G$10,AK22+BP23,G$10),0) -> 14.7 | CW23: =IF(AL22>0,IF((AL22+BQ23)<H$10,AL22+BQ23,H$10),0) -> 28.09 | CX23: =IF(AM22>0,IF((AM22+BR23)<I$10,AM22+BR23,I$10),0) -> 20.96 | CY23: =IF(AN22>0,IF((AN22+BS23)<J$10,AN22+BS23,J$10),0) -> 35 | CZ23: =IF(AO22>0,IF((AO22+BT23)<K$10,AO22+BT23,K$10),0) -> 206 | DA23: =IF(AP22>0,IF((AP22+BU23)<L$10,AP22+BU23,L$10),0) -> 82 | ... DX23: =IF(BM22>0,IF((BM22+CR23)<AI$10,BM22+CR23,AI$10),0) -> 0 | DY23: =SUM(CT23:DX23) -> 3902.52 | EA23: =IF(AI21<=0,0,IF(CT22+$C22>AI21+BN22,AI21+BN22-CT22,$C22)) -> 0 | EB23: =IF(AJ21<=0,0,IF($C22<=SUM($EA23:EA23),0,IF(CU22+$C22-SUM($EA23:EA23)>AJ21+BO22,AJ21+BO22-CU22,$C22-SUM($EA23:EA23)))) -> 0 | EC23: =IF(AK21<=0,0,IF($C22<=SUM($EA23:EB23),0,IF(CV22+$C22-SUM($EA23:EB23)>AK21+BP22,AK21+BP22-CV22,$C22-SUM($EA23:EB23)))) -> 0 | ED23: =IF(AL21<=0,0,IF($C22<=SUM($EA23:EC23),0,IF(CW22+$C22-SUM($EA23:EC23)>AL21+BQ22,AL21+BQ22-CW22,$C22-SUM($EA23:EC23)))) -> 0 | EE23: =IF(AM21<=0,0,IF($C22<=SUM($EA23:ED23),0,IF(CX22+$C22-SUM($EA23:ED23)>AM21+BR22,AM21+BR22-CX22,$C22-SUM($EA23:ED23)))) -> 0 | EF23: =IF(AN21<=0,0,IF($C22<=SUM($EA23:EE23),0,IF(CY22+$C22-SUM($EA23:EE23)>AN21+BS22,AN21+BS22-CY22,$C22-SUM($EA23:EE23)))) -> 0 | EG23: =IF(AO21<=0,0,IF($C22<=SUM($EA23:EF23),0,IF(CZ22+$C22-SUM($EA23:EF23)>AO21+BT22,AO21+BT22-CZ22,$C22-SUM($EA23:EF23)))) -> 0 | EH23: =IF(AP21<=0,0,IF($C22<=SUM($EA23:EG23),0,IF(DA22+$C22-SUM($EA23:EG23)>AP21+BU22,AP21+BU22-DA22,$C22-SUM($EA23:EG23)))) -> 0 | EI23: =IF(AQ21<=0,0,IF($C22<=SUM($EA23:EH23),0,IF(DB22+$C22-SUM($EA23:EH23)>AQ21+BV22,AQ21+BV22-DB22,$C22-SUM($EA23:EH23)))) -> 0 | ... FC23: =IF(BK21<=0,0,IF($C22<=SUM($EA23:FB23),0,IF(DV22+$C22-SUM($EA23:FB23)>BK21+CP22,BK21+CP22-DV22,$C22-SUM($EA23:FB23)))) -> 0
A24: =IF(SUM(AI23:BK23)<=0,"",A23+1) -> 4 | B24: 45748 | C24: =IF(A24="","",IF(Calculator!snowball,IF(($E$5-DY24)<0,0,$E$5-DY24),0)+D24) -> 0 | E24: =CT24+EA25 -> 0 | F24: =CU24+EB25 -> 0 | G24: =CV24+EC25 -> 0 | H24: 78.85 | I24: =CX24+EE25 -> 20.96 | J24: 35 | K24: =CZ24+EG25 -> 206 | L24: 83 | M24: 109 | N24: =DC24+EJ25 -> 450.08 | P24: =DE24+EL25 -> 791.16 | Q24: 1487.37 | R24: =DG24+EN25 -> 0 | S24: =DH24+EO25 -> 0 | T24: =DI24+EP25 -> 0 | U24: =DJ24+EQ25 -> 0 | V24: =DK24+ER25 -> 0 | W24: =DL24+ES25 -> 0 | X24: =DM24+ET25 -> 0 | Y24: =DN24+EU25 -> 0 | ... AG24: =DV24+FC25 -> 0 | AH24: =SUM(AI24:BK24) -> 289454.25 | AI24: =IF(E$8=0,0,ROUND(AI23-(E24-BN24),2)) -> 0 | AJ24: =IF(F$8=0,0,ROUND(AJ23-(F24-BO24),2)) -> 0 | AK24: =IF(G$8=0,0,ROUND(AK23-(G24-BP24),2)) -> 0 | AL24: 0 | AM24: =IF(I$8=0,0,ROUND(AM23-(I24-BR24),2)) -> 156.5 | AN24: =IF(J$8=0,0,ROUND(AN23-(J24-BS24),2)) -> 527.11 | AO24: =IF(K$8=0,0,ROUND(AO23-(K24-BT24),2)) -> 2600.82 | AP24: =IF(L$8=0,0,ROUND(AP23-(L24-BU24),2)) -> 3209.99 | AQ24: =IF(M$8=0,0,ROUND(AQ23-(M24-BV24),2)) -> 3760.52 | AR24: =IF(N$8=0,0,ROUND(AR23-(N24-BW24),2)) -> 14769.13 | AS24: =IF(O$8=0,0,ROUND(AS23-(O24-BX24),2)) -> 39547.45 | AT24: =IF(P$8=0,0,ROUND(AT23-(P24-BX24),2)) -> 48252.81 | AU24: =IF(Q$8=0,0,ROUND(AU23-(Q24-BY24),2)) -> 176629.92 | AV24: =IF(R$8=0,0,ROUND(AV23-(R24-BZ24),2)) -> 0 | AW24: =IF(S$8=0,0,ROUND(AW23-(S24-CA24),2)) -> 0 | AX24: =IF(T$8=0,0,ROUND(AX23-(T24-CB24),2)) -> 0 | AY24: =IF(U$8=0,0,ROUND(AY23-(U24-CC24),2)) -> 0 | AZ24: =IF(V$8=0,0,ROUND(AZ23-(V24-CD24),2)) -> 0 | BA24: =IF(W$8=0,0,ROUND(BA23-(W24-CE24),2)) -> 0 | ... BK24: =IF(AG$8=0,0,ROUND(BK23-(AG24-CO24),2)) -> 0 | BL24: =SUM(AI24:BK24) -> 289454.25 | BN24: =ROUND(AI23*E$9/12,2) -> 0 | BO24: =ROUND(AJ23*F$9/12,2) -> 0 | BP24: =ROUND(AK23*G$9/12,2) -> 0 | BQ24: =ROUND(AL23*H$9/12,2) -> 0 | BR24: =ROUND(AM23*I$9/12,2) -> 0 | BS24: =ROUND(AN23*J$9/12,2) -> 13.63 | BT24: =ROUND(AO23*K$9/12,2) -> 68.46 | BU24: =ROUND(AP23*L$9/12,2) -> 84.86 | ... CP24: =ROUND(BK23*AG$9/12,2) -> 0 | CR24: =SUM(BN24:CP24) -> 1776.61 | CT24: =IF(AI23>0,IF((AI23+BN24)<E$10,AI23+BN24,E$10),0) -> 0 | CU24: =IF(AJ23>0,IF((AJ23+BO24)<F$10,AJ23+BO24,F$10),0) -> 0 | CV24: =IF(AK23>0,IF((AK23+BP24)<G$10,AK23+BP24,G$10),0) -> 0 | CW24: =IF(AL23>0,IF((AL23+BQ24)<H$10,AL23+BQ24,H$10),0) -> 28.09 | CX24: =IF(AM23>0,IF((AM23+BR24)<I$10,AM23+BR24,I$10),0) -> 20.96 | CY24: =IF(AN23>0,IF((AN23+BS24)<J$10,AN23+BS24,J$10),0) -> 35 | CZ24: =IF(AO23>0,IF((AO23+BT24)<K$10,AO23+BT24,K$10),0) -> 206 | DA24: =IF(AP23>0,IF((AP23+BU24)<L$10,AP23+BU24,L$10),0) -> 82 | ... DX24: =IF(BM23>0,IF((BM23+CR24)<AI$10,BM23+CR24,AI$10),0) -> 0 | DY24: =SUM(CT24:DX24) -> 3878.02 | EA24: =IF(AI22<=0,0,IF(CT23+$C23>AI22+BN23,AI22+BN23-CT23,$C23)) -> 0 | EB24: =IF(AJ22<=0,0,IF($C23<=SUM($EA24:EA24),0,IF(CU23+$C23-SUM($EA24:EA24)>AJ22+BO23,AJ22+BO23-CU23,$C23-SUM($EA24:EA24)))) -> 0 | EC24: =IF(AK22<=0,0,IF($C23<=SUM($EA24:EB24),0,IF(CV23+$C23-SUM($EA24:EB24)>AK22+BP23,AK22+BP23-CV23,$C23-SUM($EA24:EB24)))) -> 0 | ED24: =IF(AL22<=0,0,IF($C23<=SUM($EA24:EC24),0,IF(CW23+$C23-SUM($EA24:EC24)>AL22+BQ23,AL22+BQ23-CW23,$C23-SUM($EA24:EC24)))) -> 0 | EE24: =IF(AM22<=0,0,IF($C23<=SUM($EA24:ED24),0,IF(CX23+$C23-SUM($EA24:ED24)>AM22+BR23,AM22+BR23-CX23,$C23-SUM($EA24:ED24)))) -> 0 | EF24: =IF(AN22<=0,0,IF($C23<=SUM($EA24:EE24),0,IF(CY23+$C23-SUM($EA24:EE24)>AN22+BS23,AN22+BS23-CY23,$C23-SUM($EA24:EE24)))) -> 0 | EG24: =IF(AO22<=0,0,IF($C23<=SUM($EA24:EF24),0,IF(CZ23+$C23-SUM($EA24:EF24)>AO22+BT23,AO22+BT23-CZ23,$C23-SUM($EA24:EF24)))) -> 0 | EH24: =IF(AP22<=0,0,IF($C23<=SUM($EA24:EG24),0,IF(DA23+$C23-SUM($EA24:EG24)>AP22+BU23,AP22+BU23-DA23,$C23-SUM($EA24:EG24)))) -> 0 | EI24: =IF(AQ22<=0,0,IF($C23<=SUM($EA24:EH24),0,IF(DB23+$C23-SUM($EA24:EH24)>AQ22+BV23,AQ22+BV23-DB23,$C23-SUM($EA24:EH24)))) -> 0 | ... FC24: =IF(BK22<=0,0,IF($C23<=SUM($EA24:FB24),0,IF(DV23+$C23-SUM($EA24:FB24)>BK22+CP23,BK22+CP23-DV23,$C23-SUM($EA24:FB24)))) -> 0
A25: =IF(SUM(AI24:BK24)<=0,"",A24+1) -> 5 | B25: 45778 | C25: =IF(A25="","",IF(Calculator!snowball,IF(($E$5-DY25)<0,0,$E$5-DY25),0)+D25) -> 12.07 | E25: =CT25+EA26 -> 0 | F25: =CU25+EB26 -> 0 | G25: =CV25+EC26 -> 0 | H25: =CW25+ED26 -> 0 | I25: 156.5 | J25: =CY25+EF26 -> 35 | K25: =CZ25+EG26 -> 206 | L25: 83 | M25: 126 | N25: =DC25+EJ26 -> 450.08 | P25: =DE25+EL26 -> 791.16 | Q25: 1487.37 | R25: =DG25+EN26 -> 0 | S25: =DH25+EO26 -> 0 | T25: =DI25+EP26 -> 0 | U25: =DJ25+EQ26 -> 0 | V25: =DK25+ER26 -> 0 | W25: =DL25+ES26 -> 0 | X25: =DM25+ET26 -> 0 | Y25: =DN25+EU26 -> 0 | ... AG25: =DV25+FC26 -> 0 | AH25: =SUM(AI25:BK25) -> 287695.09 | AI25: =IF(E$8=0,0,ROUND(AI24-(E25-BN25),2)) -> 0 | AJ25: =IF(F$8=0,0,ROUND(AJ24-(F25-BO25),2)) -> 0 | AK25: =IF(G$8=0,0,ROUND(AK24-(G25-BP25),2)) -> 0 | AL25: =IF(H$8=0,0,ROUND(AL24-(H25-BQ25),2)) -> 0 | AM25: 0 | AN25: =IF(J$8=0,0,ROUND(AN24-(J25-BS25),2)) -> 505.2 | AO25: =IF(K$8=0,0,ROUND(AO24-(K25-BT25),2)) -> 2459.84 | AP25: =IF(L$8=0,0,ROUND(AP24-(L25-BU25),2)) -> 3211.89 | AQ25: =IF(M$8=0,0,ROUND(AQ24-(M25-BV25),2)) -> 3727.72 | AR25: =IF(N$8=0,0,ROUND(AR24-(N25-BW25),2)) -> 14540.59 | AS25: =IF(O$8=0,0,ROUND(AS24-(O25-BX25),2)) -> 39909.97 | AT25: =IF(P$8=0,0,ROUND(AT24-(P25-BX25),2)) -> 47824.17 | AU25: =IF(Q$8=0,0,ROUND(AU24-(Q25-BY25),2)) -> 175515.71 | AV25: =IF(R$8=0,0,ROUND(AV24-(R25-BZ25),2)) -> 0 | AW25: =IF(S$8=0,0,ROUND(AW24-(S25-CA25),2)) -> 0 | AX25: =IF(T$8=0,0,ROUND(AX24-(T25-CB25),2)) -> 0 | AY25: =IF(U$8=0,0,ROUND(AY24-(U25-CC25),2)) -> 0 | AZ25: =IF(V$8=0,0,ROUND(AZ24-(V25-CD25),2)) -> 0 | BA25: =IF(W$8=0,0,ROUND(BA24-(W25-CE25),2)) -> 0 | ... BK25: =IF(AG$8=0,0,ROUND(BK24-(AG25-CO25),2)) -> 0 | BL25: =SUM(AI25:BK25) -> 287695.09 | BN25: =ROUND(AI24*E$9/12,2) -> 0 | BO25: =ROUND(AJ24*F$9/12,2) -> 0 | BP25: =ROUND(AK24*G$9/12,2) -> 0 | BQ25: =ROUND(AL24*H$9/12,2) -> 0 | BR25: =ROUND(AM24*I$9/12,2) -> 0 | BS25: =ROUND(AN24*J$9/12,2) -> 13.09 | BT25: =ROUND(AO24*K$9/12,2) -> 65.02 | BU25: =ROUND(AP24*L$9/12,2) -> 84.9 | ... CP25: =ROUND(BK24*AG$9/12,2) -> 0 | CR25: =SUM(BN25:CP25) -> 1765.4 | CT25: =IF(AI24>0,IF((AI24+BN25)<E$10,AI24+BN25,E$10),0) -> 0 | CU25: =IF(AJ24>0,IF((AJ24+BO25)<F$10,AJ24+BO25,F$10),0) -> 0 | CV25: =IF(AK24>0,IF((AK24+BP25)<G$10,AK24+BP25,G$10),0) -> 0 | CW25: =IF(AL24>0,IF((AL24+BQ25)<H$10,AL24+BQ25,H$10),0) -> 0 | CX25: =IF(AM24>0,IF((AM24+BR25)<I$10,AM24+BR25,I$10),0) -> 20.96 | CY25: =IF(AN24>0,IF((AN24+BS25)<J$10,AN24+BS25,J$10),0) -> 35 | CZ25: =IF(AO24>0,IF((AO24+BT25)<K$10,AO24+BT25,K$10),0) -> 206 | DA25: =IF(AP24>0,IF((AP24+BU25)<L$10,AP24+BU25,L$10),0) -> 82 | ... DX25: =IF(BM24>0,IF((BM24+CR25)<AI$10,BM24+CR25,AI$10),0) -> 0 | DY25: =SUM(CT25:DX25) -> 3849.93 | EA25: =IF(AI23<=0,0,IF(CT24+$C24>AI23+BN24,AI23+BN24-CT24,$C24)) -> 0 | EB25: =IF(AJ23<=0,0,IF($C24<=SUM($EA25:EA25),0,IF(CU24+$C24-SUM($EA25:EA25)>AJ23+BO24,AJ23+BO24-CU24,$C24-SUM($EA25:EA25)))) -> 0 | EC25: =IF(AK23<=0,0,IF($C24<=SUM($EA25:EB25),0,IF(CV24+$C24-SUM($EA25:EB25)>AK23+BP24,AK23+BP24-CV24,$C24-SUM($EA25:EB25)))) -> 0 | ED25: =IF(AL23<=0,0,IF($C24<=SUM($EA25:EC25),0,IF(CW24+$C24-SUM($EA25:EC25)>AL23+BQ24,AL23+BQ24-CW24,$C24-SUM($EA25:EC25)))) -> 0 | EE25: =IF(AM23<=0,0,IF($C24<=SUM($EA25:ED25),0,IF(CX24+$C24-SUM($EA25:ED25)>AM23+BR24,AM23+BR24-CX24,$C24-SUM($EA25:ED25)))) -> 0 | EF25: =IF(AN23<=0,0,IF($C24<=SUM($EA25:EE25),0,IF(CY24+$C24-SUM($EA25:EE25)>AN23+BS24,AN23+BS24-CY24,$C24-SUM($EA25:EE25)))) -> 0 | EG25: =IF(AO23<=0,0,IF($C24<=SUM($EA25:EF25),0,IF(CZ24+$C24-SUM($EA25:EF25)>AO23+BT24,AO23+BT24-CZ24,$C24-SUM($EA25:EF25)))) -> 0 | EH25: =IF(AP23<=0,0,IF($C24<=SUM($EA25:EG25),0,IF(DA24+$C24-SUM($EA25:EG25)>AP23+BU24,AP23+BU24-DA24,$C24-SUM($EA25:EG25)))) -> 0 | EI25: =IF(AQ23<=0,0,IF($C24<=SUM($EA25:EH25),0,IF(DB24+$C24-SUM($EA25:EH25)>AQ23+BV24,AQ23+BV24-DB24,$C24-SUM($EA25:EH25)))) -> 0 | ... FC25: =IF(BK23<=0,0,IF($C24<=SUM($EA25:FB25),0,IF(DV24+$C24-SUM($EA25:FB25)>BK23+CP24,BK23+CP24-DV24,$C24-SUM($EA25:FB25)))) -> 0
A26: =IF(SUM(AI25:BK25)<=0,"",A25+1) -> 6 | B26: 45809 | C26: =IF(A26="","",IF(Calculator!snowball,IF(($E$5-DY26)<0,0,$E$5-DY26),0)+D26) -> 33.03 | E26: =CT26+EA27 -> 0 | F26: =CU26+EB27 -> 0 | G26: =CV26+EC27 -> 0 | H26: =CW26+ED27 -> 0 | I26: =CX26+EE27 -> 0 | J26: 35 | K26: 73 | L26: 80 | M26: 133 | N26: =DC26+EJ27 -> 450.08 | P26: =DE26+EL27 -> 791.16 | Q26: 1487.37 | R26: =DG26+EN27 -> 0 | S26: =DH26+EO27 -> 0 | T26: =DI26+EP27 -> 0 | U26: =DJ26+EQ27 -> 0 | V26: =DK26+ER27 -> 0 | W26: =DL26+ES27 -> 0 | X26: =DM26+ET27 -> 0 | Y26: =DN26+EU27 -> 0 | ... AG26: =DV26+FC27 -> 0 | AH26: =SUM(AI26:BK26) -> 286216.5 | AI26: =IF(E$8=0,0,ROUND(AI25-(E26-BN26),2)) -> 0 | AJ26: =IF(F$8=0,0,ROUND(AJ25-(F26-BO26),2)) -> 0 | AK26: =IF(G$8=0,0,ROUND(AK25-(G26-BP26),2)) -> 0 | AL26: =IF(H$8=0,0,ROUND(AL25-(H26-BQ26),2)) -> 0 | AM26: =IF(I$8=0,0,ROUND(AM25-(I26-BR26),2)) -> 0 | AN26: =IF(J$8=0,0,ROUND(AN25-(J26-BS26),2)) -> 482.75 | AO26: =IF(K$8=0,0,ROUND(AO25-(K26-BT26),2)) -> 2448.34 | AP26: =IF(L$8=0,0,ROUND(AP25-(L26-BU26),2)) -> 3216.84 | ... AS26: =IF(O$8=0,0,ROUND(AS25-(O26-BX26),2)) -> 40275.81 | AT26: =IF(P$8=0,0,ROUND(AT25-(P26-BX26),2)) -> 47398.85 | AU26: =IF(Q$8=0,0,ROUND(AU25-(Q26-BY26),2)) -> 174398.18 | AV26: =IF(R$8=0,0,ROUND(AV25-(R26-BZ26),2)) -> 0 | AW26: =IF(S$8=0,0,ROUND(AW25-(S26-CA26),2)) -> 0 | AX26: =IF(T$8=0,0,ROUND(AX25-(T26-CB26),2)) -> 0 | AY26: =IF(U$8=0,0,ROUND(AY25-(U26-CC26),2)) -> 0 | AZ26: =IF(V$8=0,0,ROUND(AZ25-(V26-CD26),2)) -> 0 | BA26: =IF(W$8=0,0,ROUND(BA25-(W26-CE26),2)) -> 0 | ... BK26: =IF(AG$8=0,0,ROUND(BK25-(AG26-CO26),2)) -> 0 | BL26: =SUM(AI26:BK26) -> 286216.5 | BN26: =ROUND(AI25*E$9/12,2) -> 0 | BO26: =ROUND(AJ25*F$9/12,2) -> 0 | BP26: =ROUND(AK25*G$9/12,2) -> 0 | BQ26: =ROUND(AL25*H$9/12,2) -> 0 | BR26: =ROUND(AM25*I$9/12,2) -> 0 | BS26: =ROUND(AN25*J$9/12,2) -> 12.55 | BT26: =ROUND(AO25*K$9/12,2) -> 61.5 | BU26: =ROUND(AP25*L$9/12,2) -> 84.95 | ... CP26: =ROUND(BK25*AG$9/12,2) -> 0 | CR26: =SUM(BN26:CP26) -> 1753.67 | CT26: =IF(AI25>0,IF((AI25+BN26)<E$10,AI25+BN26,E$10),0) -> 0 | CU26: =IF(AJ25>0,IF((AJ25+BO26)<F$10,AJ25+BO26,F$10),0) -> 0 | CV26: =IF(AK25>0,IF((AK25+BP26)<G$10,AK25+BP26,G$10),0) -> 0 | CW26: =IF(AL25>0,IF((AL25+BQ26)<H$10,AL25+BQ26,H$10),0) -> 0 | CX26: =IF(AM25>0,IF((AM25+BR26)<I$10,AM25+BR26,I$10),0) -> 0 | CY26: =IF(AN25>0,IF((AN25+BS26)<J$10,AN25+BS26,J$10),0) -> 35 | CZ26: =IF(AO25>0,IF((AO25+BT26)<K$10,AO25+BT26,K$10),0) -> 206 | DA26: =IF(AP25>0,IF((AP25+BU26)<L$10,AP25+BU26,L$10),0) -> 82 | ... DX26: =IF(BM25>0,IF((BM25+CR26)<AI$10,BM25+CR26,AI$10),0) -> 0 | DY26: =SUM(CT26:DX26) -> 3828.97 | EA26: =IF(AI24<=0,0,IF(CT25+$C25>AI24+BN25,AI24+BN25-CT25,$C25)) -> 0 | EB26: =IF(AJ24<=0,0,IF($C25<=SUM($EA26:EA26),0,IF(CU25+$C25-SUM($EA26:EA26)>AJ24+BO25,AJ24+BO25-CU25,$C25-SUM($EA26:EA26)))) -> 0 | EC26: =IF(AK24<=0,0,IF($C25<=SUM($EA26:EB26),0,IF(CV25+$C25-SUM($EA26:EB26)>AK24+BP25,AK24+BP25-CV25,$C25-SUM($EA26:EB26)))) -> 0 | ED26: =IF(AL24<=0,0,IF($C25<=SUM($EA26:EC26),0,IF(CW25+$C25-SUM($EA26:EC26)>AL24+BQ25,AL24+BQ25-CW25,$C25-SUM($EA26:EC26)))) -> 0 | EE26: =IF(AM24<=0,0,IF($C25<=SUM($EA26:ED26),0,IF(CX25+$C25-SUM($EA26:ED26)>AM24+BR25,AM24+BR25-CX25,$C25-SUM($EA26:ED26)))) -> 12.07 | EF26: =IF(AN24<=0,0,IF($C25<=SUM($EA26:EE26),0,IF(CY25+$C25-SUM($EA26:EE26)>AN24+BS25,AN24+BS25-CY25,$C25-SUM($EA26:EE26)))) -> 0 | EG26: =IF(AO24<=0,0,IF($C25<=SUM($EA26:EF26),0,IF(CZ25+$C25-SUM($EA26:EF26)>AO24+BT25,AO24+BT25-CZ25,$C25-SUM($EA26:EF26)))) -> 0 | EH26: =IF(AP24<=0,0,IF($C25<=SUM($EA26:EG26),0,IF(DA25+$C25-SUM($EA26:EG26)>AP24+BU25,AP24+BU25-DA25,$C25-SUM($EA26:EG26)))) -> 0 | EI26: =IF(AQ24<=0,0,IF($C25<=SUM($EA26:EH26),0,IF(DB25+$C25-SUM($EA26:EH26)>AQ24+BV25,AQ24+BV25-DB25,$C25-SUM($EA26:EH26)))) -> 0 | ... FC26: =IF(BK24<=0,0,IF($C25<=SUM($EA26:FB26),0,IF(DV25+$C25-SUM($EA26:FB26)>BK24+CP25,BK24+CP25-DV25,$C25-SUM($EA26:FB26)))) -> 0
A27: =IF(SUM(AI26:BK26)<=0,"",A26+1) -> 7 | B27: 45839 | C27: =IF(A27="","",IF(Calculator!snowball,IF(($E$5-DY27)<0,0,$E$5-DY27),0)+D27) -> 33.03 | E27: =CT27+EA28 -> 0 | F27: =CU27+EB28 -> 0 | G27: =CV27+EC28 -> 0 | H27: =CW27+ED28 -> 0 | I27: =CX27+EE28 -> 0 | J27: 35 | K27: 100 | L27: 77 | M27: 129 | N27: =DC27+EJ28 -> 450.08 | P27: =DE27+EL28 -> 791.16 | Q27: 1487.37 | R27: =DG27+EN28 -> 0 | S27: =DH27+EO28 -> 0 | T27: =DI27+EP28 -> 0 | U27: =DJ27+EQ28 -> 0 | V27: =DK27+ER28 -> 0 | W27: =DL27+ES28 -> 0 | X27: =DM27+ET28 -> 0 | Y27: =DN27+EU28 -> 0 | ... AG27: =DV27+FC28 -> 0 | AH27: =SUM(AI27:BK27) -> 284716.12 | AI27: =IF(E$8=0,0,ROUND(AI26-(E27-BN27),2)) -> 0 | AJ27: =IF(F$8=0,0,ROUND(AJ26-(F27-BO27),2)) -> 0 | AK27: =IF(G$8=0,0,ROUND(AK26-(G27-BP27),2)) -> 0 | AL27: =IF(H$8=0,0,ROUND(AL26-(H27-BQ27),2)) -> 0 | AM27: =IF(I$8=0,0,ROUND(AM26-(I27-BR27),2)) -> 0 | AN27: =IF(J$8=0,0,ROUND(AN26-(J27-BS27),2)) -> 459.74 | AO27: =IF(K$8=0,0,ROUND(AO26-(K27-BT27),2)) -> 2409.55 | AP27: =IF(L$8=0,0,ROUND(AP26-(L27-BU27),2)) -> 3224.93 | ... AS27: =IF(O$8=0,0,ROUND(AS26-(O27-BX27),2)) -> 40645 | AT27: =IF(P$8=0,0,ROUND(AT26-(P27-BX27),2)) -> 46976.88 | AU27: =IF(Q$8=0,0,ROUND(AU26-(Q27-BY27),2)) -> 173277.36 | AV27: =IF(R$8=0,0,ROUND(AV26-(R27-BZ27),2)) -> 0 | AW27: =IF(S$8=0,0,ROUND(AW26-(S27-CA27),2)) -> 0 | AX27: =IF(T$8=0,0,ROUND(AX26-(T27-CB27),2)) -> 0 | AY27: =IF(U$8=0,0,ROUND(AY26-(U27-CC27),2)) -> 0 | AZ27: =IF(V$8=0,0,ROUND(AZ26-(V27-CD27),2)) -> 0 | BA27: =IF(W$8=0,0,ROUND(BA26-(W27-CE27),2)) -> 0 | ... BK27: =IF(AG$8=0,0,ROUND(BK26-(AG27-CO27),2)) -> 0 | BL27: =SUM(AI27:BK27) -> 284716.12 | BN27: =ROUND(AI26*E$9/12,2) -> 0 | BO27: =ROUND(AJ26*F$9/12,2) -> 0 | BP27: =ROUND(AK26*G$9/12,2) -> 0 | BQ27: =ROUND(AL26*H$9/12,2) -> 0 | BR27: =ROUND(AM26*I$9/12,2) -> 0 | BS27: =ROUND(AN26*J$9/12,2) -> 11.99 | BT27: =ROUND(AO26*K$9/12,2) -> 61.21 | BU27: =ROUND(AP26*L$9/12,2) -> 85.09 | ... CP27: =ROUND(BK26*AG$9/12,2) -> 0 | CR27: =SUM(BN27:CP27) -> 1745.03 | CT27: =IF(AI26>0,IF((AI26+BN27)<E$10,AI26+BN27,E$10),0) -> 0 | CU27: =IF(AJ26>0,IF((AJ26+BO27)<F$10,AJ26+BO27,F$10),0) -> 0 | CV27: =IF(AK26>0,IF((AK26+BP27)<G$10,AK26+BP27,G$10),0) -> 0 | CW27: =IF(AL26>0,IF((AL26+BQ27)<H$10,AL26+BQ27,H$10),0) -> 0 | CX27: =IF(AM26>0,IF((AM26+BR27)<I$10,AM26+BR27,I$10),0) -> 0 | CY27: =IF(AN26>0,IF((AN26+BS27)<J$10,AN26+BS27,J$10),0) -> 35 | CZ27: =IF(AO26>0,IF((AO26+BT27)<K$10,AO26+BT27,K$10),0) -> 206 | DA27: =IF(AP26>0,IF((AP26+BU27)<L$10,AP26+BU27,L$10),0) -> 82 | ... DX27: =IF(BM26>0,IF((BM26+CR27)<AI$10,BM26+CR27,AI$10),0) -> 0 | DY27: =SUM(CT27:DX27) -> 3828.97 | EA27: =IF(AI25<=0,0,IF(CT26+$C26>AI25+BN26,AI25+BN26-CT26,$C26)) -> 0 | EB27: =IF(AJ25<=0,0,IF($C26<=SUM($EA27:EA27),0,IF(CU26+$C26-SUM($EA27:EA27)>AJ25+BO26,AJ25+BO26-CU26,$C26-SUM($EA27:EA27)))) -> 0 | EC27: =IF(AK25<=0,0,IF($C26<=SUM($EA27:EB27),0,IF(CV26+$C26-SUM($EA27:EB27)>AK25+BP26,AK25+BP26-CV26,$C26-SUM($EA27:EB27)))) -> 0 | ED27: =IF(AL25<=0,0,IF($C26<=SUM($EA27:EC27),0,IF(CW26+$C26-SUM($EA27:EC27)>AL25+BQ26,AL25+BQ26-CW26,$C26-SUM($EA27:EC27)))) -> 0 | EE27: =IF(AM25<=0,0,IF($C26<=SUM($EA27:ED27),0,IF(CX26+$C26-SUM($EA27:ED27)>AM25+BR26,AM25+BR26-CX26,$C26-SUM($EA27:ED27)))) -> 0 | EF27: =IF(AN25<=0,0,IF($C26<=SUM($EA27:EE27),0,IF(CY26+$C26-SUM($EA27:EE27)>AN25+BS26,AN25+BS26-CY26,$C26-SUM($EA27:EE27)))) -> 33.03 | EG27: =IF(AO25<=0,0,IF($C26<=SUM($EA27:EF27),0,IF(CZ26+$C26-SUM($EA27:EF27)>AO25+BT26,AO25+BT26-CZ26,$C26-SUM($EA27:EF27)))) -> 0 | EH27: =IF(AP25<=0,0,IF($C26<=SUM($EA27:EG27),0,IF(DA26+$C26-SUM($EA27:EG27)>AP25+BU26,AP25+BU26-DA26,$C26-SUM($EA27:EG27)))) -> 0 | EI27: =IF(AQ25<=0,0,IF($C26<=SUM($EA27:EH27),0,IF(DB26+$C26-SUM($EA27:EH27)>AQ25+BV26,AQ25+BV26-DB26,$C26-SUM($EA27:EH27)))) -> 0 | ... FC27: =IF(BK25<=0,0,IF($C26<=SUM($EA27:FB27),0,IF(DV26+$C26-SUM($EA27:FB27)>BK25+CP26,BK25+CP26-DV26,$C26-SUM($EA27:FB27)))) -> 0
A28: =IF(SUM(AI27:BK27)<=0,"",A27+1) -> 8 | B28: 45870 | C28: =IF(A28="","",IF(Calculator!snowball,IF(($E$5-DY28)<0,0,$E$5-DY28),0)+D28) -> 33.03 | E28: =CT28+EA29 -> 0 | F28: =CU28+EB29 -> 0 | G28: =CV28+EC29 -> 0 | H28: =CW28+ED29 -> 0 | I28: =CX28+EE29 -> 0 | J28: 35 | K28: 98 | L28: 80 | M28: 131 | N28: =DC28+EJ29 -> 450.08 | P28: =DE28+EL29 -> 791.16 | Q28: 1487.37 | R28: =DG28+EN29 -> 0 | S28: =DH28+EO29 -> 0 | T28: =DI28+EP29 -> 0 | U28: =DJ28+EQ29 -> 0 | V28: =DK28+ER29 -> 0 | W28: =DL28+ES29 -> 0 | X28: =DM28+ET29 -> 0 | Y28: =DN28+EU29 -> 0 | ... AG28: =DV28+FC29 -> 0 | AH28: =SUM(AI28:BK28) -> 283210.47 | AI28: =IF(E$8=0,0,ROUND(AI27-(E28-BN28),2)) -> 0 | AJ28: =IF(F$8=0,0,ROUND(AJ27-(F28-BO28),2)) -> 0 | AK28: =IF(G$8=0,0,ROUND(AK27-(G28-BP28),2)) -> 0 | AL28: =IF(H$8=0,0,ROUND(AL27-(H28-BQ28),2)) -> 0 | AM28: =IF(I$8=0,0,ROUND(AM27-(I28-BR28),2)) -> 0 | AN28: =IF(J$8=0,0,ROUND(AN27-(J28-BS28),2)) -> 436.16 | AO28: =IF(K$8=0,0,ROUND(AO27-(K28-BT28),2)) -> 2371.79 | AP28: =IF(L$8=0,0,ROUND(AP27-(L28-BU28),2)) -> 3230.23 | ... AS28: =IF(O$8=0,0,ROUND(AS27-(O28-BX28),2)) -> 41017.58 | AT28: =IF(P$8=0,0,ROUND(AT27-(P28-BX28),2)) -> 46558.3 | AU28: =IF(Q$8=0,0,ROUND(AU27-(Q28-BY28),2)) -> 172153.28 | AV28: =IF(R$8=0,0,ROUND(AV27-(R28-BZ28),2)) -> 0 | AW28: =IF(S$8=0,0,ROUND(AW27-(S28-CA28),2)) -> 0 | AX28: =IF(T$8=0,0,ROUND(AX27-(T28-CB28),2)) -> 0 | AY28: =IF(U$8=0,0,ROUND(AY27-(U28-CC28),2)) -> 0 | AZ28: =IF(V$8=0,0,ROUND(AZ27-(V28-CD28),2)) -> 0 | BA28: =IF(W$8=0,0,ROUND(BA27-(W28-CE28),2)) -> 0 | ... BK28: =IF(AG$8=0,0,ROUND(BK27-(AG28-CO28),2)) -> 0 | BL28: =SUM(AI28:BK28) -> 283210.47 | BN28: =ROUND(AI27*E$9/12,2) -> 0 | BO28: =ROUND(AJ27*F$9/12,2) -> 0 | BP28: =ROUND(AK27*G$9/12,2) -> 0 | BQ28: =ROUND(AL27*H$9/12,2) -> 0 | BR28: =ROUND(AM27*I$9/12,2) -> 0 | BS28: =ROUND(AN27*J$9/12,2) -> 11.42 | BT28: =ROUND(AO27*K$9/12,2) -> 60.24 | BU28: =ROUND(AP27*L$9/12,2) -> 85.3 | ... CP28: =ROUND(BK27*AG$9/12,2) -> 0 | CR28: =SUM(BN28:CP28) -> 1735.87 | CT28: =IF(AI27>0,IF((AI27+BN28)<E$10,AI27+BN28,E$10),0) -> 0 | CU28: =IF(AJ27>0,IF((AJ27+BO28)<F$10,AJ27+BO28,F$10),0) -> 0 | CV28: =IF(AK27>0,IF((AK27+BP28)<G$10,AK27+BP28,G$10),0) -> 0 | CW28: =IF(AL27>0,IF((AL27+BQ28)<H$10,AL27+BQ28,H$10),0) -> 0 | CX28: =IF(AM27>0,IF((AM27+BR28)<I$10,AM27+BR28,I$10),0) -> 0 | CY28: =IF(AN27>0,IF((AN27+BS28)<J$10,AN27+BS28,J$10),0) -> 35 | CZ28: =IF(AO27>0,IF((AO27+BT28)<K$10,AO27+BT28,K$10),0) -> 206 | DA28: =IF(AP27>0,IF((AP27+BU28)<L$10,AP27+BU28,L$10),0) -> 82 | ... DX28: =IF(BM27>0,IF((BM27+CR28)<AI$10,BM27+CR28,AI$10),0) -> 0 | DY28: =SUM(CT28:DX28) -> 3828.97 | EA28: =IF(AI26<=0,0,IF(CT27+$C27>AI26+BN27,AI26+BN27-CT27,$C27)) -> 0 | EB28: =IF(AJ26<=0,0,IF($C27<=SUM($EA28:EA28),0,IF(CU27+$C27-SUM($EA28:EA28)>AJ26+BO27,AJ26+BO27-CU27,$C27-SUM($EA28:EA28)))) -> 0 | EC28: =IF(AK26<=0,0,IF($C27<=SUM($EA28:EB28),0,IF(CV27+$C27-SUM($EA28:EB28)>AK26+BP27,AK26+BP27-CV27,$C27-SUM($EA28:EB28)))) -> 0 | ED28: =IF(AL26<=0,0,IF($C27<=SUM($EA28:EC28),0,IF(CW27+$C27-SUM($EA28:EC28)>AL26+BQ27,AL26+BQ27-CW27,$C27-SUM($EA28:EC28)))) -> 0 | EE28: =IF(AM26<=0,0,IF($C27<=SUM($EA28:ED28),0,IF(CX27+$C27-SUM($EA28:ED28)>AM26+BR27,AM26+BR27-CX27,$C27-SUM($EA28:ED28)))) -> 0 | EF28: =IF(AN26<=0,0,IF($C27<=SUM($EA28:EE28),0,IF(CY27+$C27-SUM($EA28:EE28)>AN26+BS27,AN26+BS27-CY27,$C27-SUM($EA28:EE28)))) -> 33.03 | EG28: =IF(AO26<=0,0,IF($C27<=SUM($EA28:EF28),0,IF(CZ27+$C27-SUM($EA28:EF28)>AO26+BT27,AO26+BT27-CZ27,$C27-SUM($EA28:EF28)))) -> 0 | EH28: =IF(AP26<=0,0,IF($C27<=SUM($EA28:EG28),0,IF(DA27+$C27-SUM($EA28:EG28)>AP26+BU27,AP26+BU27-DA27,$C27-SUM($EA28:EG28)))) -> 0 | EI28: =IF(AQ26<=0,0,IF($C27<=SUM($EA28:EH28),0,IF(DB27+$C27-SUM($EA28:EH28)>AQ26+BV27,AQ26+BV27-DB27,$C27-SUM($EA28:EH28)))) -> 0 | ... FC28: =IF(BK26<=0,0,IF($C27<=SUM($EA28:FB28),0,IF(DV27+$C27-SUM($EA28:FB28)>BK26+CP27,BK26+CP27-DV27,$C27-SUM($EA28:FB28)))) -> 0
A29: =IF(SUM(AI28:BK28)<=0,"",A28+1) -> 9 | B29: 45901 | C29: =IF(A29="","",IF(Calculator!snowball,IF(($E$5-DY29)<0,0,$E$5-DY29),0)+D29) -> 33.03 | E29: =CT29+EA30 -> 0 | F29: =CU29+EB30 -> 0 | G29: =CV29+EC30 -> 0 | H29: =CW29+ED30 -> 0 | I29: =CX29+EE30 -> 0 | J29: 35 | K29: 206 | L29: 80 | M29: 130 | N29: =DC29+EJ30 -> 450.08 | P29: =DE29+EL30 -> 791.16 | Q29: 1461.99 | R29: =DG29+EN30 -> 0 | S29: =DH29+EO30 -> 0 | T29: =DI29+EP30 -> 0 | U29: =DJ29+EQ30 -> 0 | V29: =DK29+ER30 -> 0 | W29: =DL29+ES30 -> 0 | X29: =DM29+ET30 -> 0 | Y29: =DN29+EU30 -> 0 | ... AG29: =DV29+FC30 -> 0 | AH29: =SUM(AI29:BK29) -> 281620.78 | AI29: =IF(E$8=0,0,ROUND(AI28-(E29-BN29),2)) -> 0 | AJ29: =IF(F$8=0,0,ROUND(AJ28-(F29-BO29),2)) -> 0 | AK29: =IF(G$8=0,0,ROUND(AK28-(G29-BP29),2)) -> 0 | AL29: =IF(H$8=0,0,ROUND(AL28-(H29-BQ29),2)) -> 0 | AM29: =IF(I$8=0,0,ROUND(AM28-(I29-BR29),2)) -> 0 | AN29: =IF(J$8=0,0,ROUND(AN28-(J29-BS29),2)) -> 411.99 | AO29: =IF(K$8=0,0,ROUND(AO28-(K29-BT29),2)) -> 2225.08 | AP29: =IF(L$8=0,0,ROUND(AP28-(L29-BU29),2)) -> 3235.67 | ... AS29: =IF(O$8=0,0,ROUND(AS28-(O29-BX29),2)) -> 41393.57 | AT29: =IF(P$8=0,0,ROUND(AT28-(P29-BX29),2)) -> 46143.13 | AU29: =IF(Q$8=0,0,ROUND(AU28-(Q29-BY29),2)) -> 171051.34 | AV29: =IF(R$8=0,0,ROUND(AV28-(R29-BZ29),2)) -> 0 | AW29: =IF(S$8=0,0,ROUND(AW28-(S29-CA29),2)) -> 0 | AX29: =IF(T$8=0,0,ROUND(AX28-(T29-CB29),2)) -> 0 | AY29: =IF(U$8=0,0,ROUND(AY28-(U29-CC29),2)) -> 0 | AZ29: =IF(V$8=0,0,ROUND(AZ28-(V29-CD29),2)) -> 0 | BA29: =IF(W$8=0,0,ROUND(BA28-(W29-CE29),2)) -> 0 | ... BK29: =IF(AG$8=0,0,ROUND(BK28-(AG29-CO29),2)) -> 0 | BL29: =SUM(AI29:BK29) -> 281620.78 | BN29: =ROUND(AI28*E$9/12,2) -> 0 | BO29: =ROUND(AJ28*F$9/12,2) -> 0 | BP29: =ROUND(AK28*G$9/12,2) -> 0 | BQ29: =ROUND(AL28*H$9/12,2) -> 0 | BR29: =ROUND(AM28*I$9/12,2) -> 0 | BS29: =ROUND(AN28*J$9/12,2) -> 10.83 | BT29: =ROUND(AO28*K$9/12,2) -> 59.29 | BU29: =ROUND(AP28*L$9/12,2) -> 85.44 | ... CP29: =ROUND(BK28*AG$9/12,2) -> 0 | CR29: =SUM(BN29:CP29) -> 1726.53 | CT29: =IF(AI28>0,IF((AI28+BN29)<E$10,AI28+BN29,E$10),0) -> 0 | CU29: =IF(AJ28>0,IF((AJ28+BO29)<F$10,AJ28+BO29,F$10),0) -> 0 | CV29: =IF(AK28>0,IF((AK28+BP29)<G$10,AK28+BP29,G$10),0) -> 0 | CW29: =IF(AL28>0,IF((AL28+BQ29)<H$10,AL28+BQ29,H$10),0) -> 0 | CX29: =IF(AM28>0,IF((AM28+BR29)<I$10,AM28+BR29,I$10),0) -> 0 | CY29: =IF(AN28>0,IF((AN28+BS29)<J$10,AN28+BS29,J$10),0) -> 35 | CZ29: =IF(AO28>0,IF((AO28+BT29)<K$10,AO28+BT29,K$10),0) -> 206 | DA29: =IF(AP28>0,IF((AP28+BU29)<L$10,AP28+BU29,L$10),0) -> 82 | ... DX29: =IF(BM28>0,IF((BM28+CR29)<AI$10,BM28+CR29,AI$10),0) -> 0 | DY29: =SUM(CT29:DX29) -> 3828.97 | EA29: =IF(AI27<=0,0,IF(CT28+$C28>AI27+BN28,AI27+BN28-CT28,$C28)) -> 0 | EB29: =IF(AJ27<=0,0,IF($C28<=SUM($EA29:EA29),0,IF(CU28+$C28-SUM($EA29:EA29)>AJ27+BO28,AJ27+BO28-CU28,$C28-SUM($EA29:EA29)))) -> 0 | EC29: =IF(AK27<=0,0,IF($C28<=SUM($EA29:EB29),0,IF(CV28+$C28-SUM($EA29:EB29)>AK27+BP28,AK27+BP28-CV28,$C28-SUM($EA29:EB29)))) -> 0 | ED29: =IF(AL27<=0,0,IF($C28<=SUM($EA29:EC29),0,IF(CW28+$C28-SUM($EA29:EC29)>AL27+BQ28,AL27+BQ28-CW28,$C28-SUM($EA29:EC29)))) -> 0 | EE29: =IF(AM27<=0,0,IF($C28<=SUM($EA29:ED29),0,IF(CX28+$C28-SUM($EA29:ED29)>AM27+BR28,AM27+BR28-CX28,$C28-SUM($EA29:ED29)))) -> 0 | EF29: =IF(AN27<=0,0,IF($C28<=SUM($EA29:EE29),0,IF(CY28+$C28-SUM($EA29:EE29)>AN27+BS28,AN27+BS28-CY28,$C28-SUM($EA29:EE29)))) -> 33.03 | EG29: =IF(AO27<=0,0,IF($C28<=SUM($EA29:EF29),0,IF(CZ28+$C28-SUM($EA29:EF29)>AO27+BT28,AO27+BT28-CZ28,$C28-SUM($EA29:EF29)))) -> 0 | EH29: =IF(AP27<=0,0,IF($C28<=SUM($EA29:EG29),0,IF(DA28+$C28-SUM($EA29:EG29)>AP27+BU28,AP27+BU28-DA28,$C28-SUM($EA29:EG29)))) -> 0 | EI29: =IF(AQ27<=0,0,IF($C28<=SUM($EA29:EH29),0,IF(DB28+$C28-SUM($EA29:EH29)>AQ27+BV28,AQ27+BV28-DB28,$C28-SUM($EA29:EH29)))) -> 0 | ... FC29: =IF(BK27<=0,0,IF($C28<=SUM($EA29:FB29),0,IF(DV28+$C28-SUM($EA29:FB29)>BK27+CP28,BK27+CP28-DV28,$C28-SUM($EA29:FB29)))) -> 0
A30: =IF(SUM(AI29:BK29)<=0,"",A29+1) -> 10 | B30: 45931 | C30: =IF(A30="","",IF(Calculator!snowball,IF(($E$5-DY30)<0,0,$E$5-DY30),0)+D30) -> 43.03 | D30: 10 | E30: =CT30+EA31 -> 0 | F30: =CU30+EB31 -> 0 | G30: =CV30+EC31 -> 0 | H30: =CW30+ED31 -> 0 | I30: =CX30+EE31 -> 0 | J30: =CY30+EF31 -> 78.03 | K30: 126 | L30: 80 | M30: 137 | N30: =DC30+EJ31 -> 450.08 | O30: =DD30+EK31 -> 695.6 | P30: =DE30+EL31 -> 791.16 | Q30: 1461.99 | R30: =DG30+EN31 -> 0 | S30: =DH30+EO31 -> 0 | T30: =DI30+EP31 -> 0 | U30: =DJ30+EQ31 -> 0 | V30: =DK30+ER31 -> 0 | W30: =DL30+ES31 -> 0 | X30: =DM30+ET31 -> 0 | Y30: =DN30+EU31 -> 0 | ... AG30: =DV30+FC31 -> 0 | AH30: =SUM(AI30:BK30) -> 279360.39 | AI30: =IF(E$8=0,0,ROUND(AI29-(E30-BN30),2)) -> 0 | AJ30: =IF(F$8=0,0,ROUND(AJ29-(F30-BO30),2)) -> 0 | AK30: =IF(G$8=0,0,ROUND(AK29-(G30-BP30),2)) -> 0 | AL30: =IF(H$8=0,0,ROUND(AL29-(H30-BQ30),2)) -> 0 | AM30: =IF(I$8=0,0,ROUND(AM29-(I30-BR30),2)) -> 0 | AN30: =IF(J$8=0,0,ROUND(AN29-(J30-BS30),2)) -> 344.19 | AO30: =IF(K$8=0,0,ROUND(AO29-(K30-BT30),2)) -> 2154.71 | AP30: =IF(L$8=0,0,ROUND(AP29-(L30-BU30),2)) -> 3241.25 | ... AS30: =IF(O$8=0,0,ROUND(AS29-(O30-BX30),2)) -> 41077.41 | AT30: =IF(P$8=0,0,ROUND(AT29-(P30-BX30),2)) -> 45731.41 | AU30: =IF(Q$8=0,0,ROUND(AU29-(Q30-BY30),2)) -> 169946.19 | AV30: =IF(R$8=0,0,ROUND(AV29-(R30-BZ30),2)) -> 0 | AW30: =IF(S$8=0,0,ROUND(AW29-(S30-CA30),2)) -> 0 | AX30: =IF(T$8=0,0,ROUND(AX29-(T30-CB30),2)) -> 0 | AY30: =IF(U$8=0,0,ROUND(AY29-(U30-CC30),2)) -> 0 | AZ30: =IF(V$8=0,0,ROUND(AZ29-(V30-CD30),2)) -> 0 | BA30: =IF(W$8=0,0,ROUND(BA29-(W30-CE30),2)) -> 0 | ... BK30: =IF(AG$8=0,0,ROUND(BK29-(AG30-CO30),2)) -> 0 | BL30: =SUM(AI30:BK30) -> 279360.39 | BN30: =ROUND(AI29*E$9/12,2) -> 0 | BO30: =ROUND(AJ29*F$9/12,2) -> 0 | BP30: =ROUND(AK29*G$9/12,2) -> 0 | BQ30: =ROUND(AL29*H$9/12,2) -> 0 | BR30: =ROUND(AM29*I$9/12,2) -> 0 | BS30: =ROUND(AN29*J$9/12,2) -> 10.23 | BT30: =ROUND(AO29*K$9/12,2) -> 55.63 | BU30: =ROUND(AP29*L$9/12,2) -> 85.58 | ... CP30: =ROUND(BK29*AG$9/12,2) -> 0 | CR30: =SUM(BN30:CP30) -> 1714.57 | CT30: =IF(AI29>0,IF((AI29+BN30)<E$10,AI29+BN30,E$10),0) -> 0 | CU30: =IF(AJ29>0,IF((AJ29+BO30)<F$10,AJ29+BO30,F$10),0) -> 0 | CV30: =IF(AK29>0,IF((AK29+BP30)<G$10,AK29+BP30,G$10),0) -> 0 | CW30: =IF(AL29>0,IF((AL29+BQ30)<H$10,AL29+BQ30,H$10),0) -> 0 | CX30: =IF(AM29>0,IF((AM29+BR30)<I$10,AM29+BR30,I$10),0) -> 0 | CY30: =IF(AN29>0,IF((AN29+BS30)<J$10,AN29+BS30,J$10),0) -> 35 | CZ30: =IF(AO29>0,IF((AO29+BT30)<K$10,AO29+BT30,K$10),0) -> 206 | DA30: =IF(AP29>0,IF((AP29+BU30)<L$10,AP29+BU30,L$10),0) -> 82 | ... DX30: =IF(BM29>0,IF((BM29+CR30)<AI$10,BM29+CR30,AI$10),0) -> 0 | DY30: =SUM(CT30:DX30) -> 3828.97 | EA30: =IF(AI28<=0,0,IF(CT29+$C29>AI28+BN29,AI28+BN29-CT29,$C29)) -> 0 | EB30: =IF(AJ28<=0,0,IF($C29<=SUM($EA30:EA30),0,IF(CU29+$C29-SUM($EA30:EA30)>AJ28+BO29,AJ28+BO29-CU29,$C29-SUM($EA30:EA30)))) -> 0 | EC30: =IF(AK28<=0,0,IF($C29<=SUM($EA30:EB30),0,IF(CV29+$C29-SUM($EA30:EB30)>AK28+BP29,AK28+BP29-CV29,$C29-SUM($EA30:EB30)))) -> 0 | ED30: =IF(AL28<=0,0,IF($C29<=SUM($EA30:EC30),0,IF(CW29+$C29-SUM($EA30:EC30)>AL28+BQ29,AL28+BQ29-CW29,$C29-SUM($EA30:EC30)))) -> 0 | EE30: =IF(AM28<=0,0,IF($C29<=SUM($EA30:ED30),0,IF(CX29+$C29-SUM($EA30:ED30)>AM28+BR29,AM28+BR29-CX29,$C29-SUM($EA30:ED30)))) -> 0 | EF30: =IF(AN28<=0,0,IF($C29<=SUM($EA30:EE30),0,IF(CY29+$C29-SUM($EA30:EE30)>AN28+BS29,AN28+BS29-CY29,$C29-SUM($EA30:EE30)))) -> 33.03 | EG30: =IF(AO28<=0,0,IF($C29<=SUM($EA30:EF30),0,IF(CZ29+$C29-SUM($EA30:EF30)>AO28+BT29,AO28+BT29-CZ29,$C29-SUM($EA30:EF30)))) -> 0 | EH30: =IF(AP28<=0,0,IF($C29<=SUM($EA30:EG30),0,IF(DA29+$C29-SUM($EA30:EG30)>AP28+BU29,AP28+BU29-DA29,$C29-SUM($EA30:EG30)))) -> 0 | EI30: =IF(AQ28<=0,0,IF($C29<=SUM($EA30:EH30),0,IF(DB29+$C29-SUM($EA30:EH30)>AQ28+BV29,AQ28+BV29-DB29,$C29-SUM($EA30:EH30)))) -> 0 | ... FC30: =IF(BK28<=0,0,IF($C29<=SUM($EA30:FB30),0,IF(DV29+$C29-SUM($EA30:FB30)>BK28+CP29,BK28+CP29-DV29,$C29-SUM($EA30:FB30)))) -> 0
A31: =IF(SUM(AI30:BK30)<=0,"",A30+1) -> 11 | B31: 45962 | C31: =IF(A31="","",IF(Calculator!snowball,IF(($E$5-DY31)<0,0,$E$5-DY31),0)+D31) -> 43.03 | D31: 10 | E31: =CT31+EA32 -> 0 | F31: =CU31+EB32 -> 0 | G31: =CV31+EC32 -> 0 | H31: =CW31+ED32 -> 0 | I31: =CX31+EE32 -> 0 | J31: =CY31+EF32 -> 78.03 | K31: 127 | L31: 83 | M31: 147 | N31: =DC31+EJ32 -> 450.08 | O31: =DD31+EK32 -> 695.6 | P31: =DE31+EL32 -> 791.16 | Q31: 1461.99 | R31: =DG31+EN32 -> 0 | S31: =DH31+EO32 -> 0 | T31: =DI31+EP32 -> 0 | U31: =DJ31+EQ32 -> 0 | V31: =DK31+ER32 -> 0 | W31: =DL31+ES32 -> 0 | X31: =DM31+ET32 -> 0 | Y31: =DN31+EU32 -> 0 | ... AG31: =DV31+FC32 -> 0 | AH31: =SUM(AI31:BK31) -> 277068.83 | AI31: =IF(E$8=0,0,ROUND(AI30-(E31-BN31),2)) -> 0 | AJ31: =IF(F$8=0,0,ROUND(AJ30-(F31-BO31),2)) -> 0 | AK31: =IF(G$8=0,0,ROUND(AK30-(G31-BP31),2)) -> 0 | AL31: =IF(H$8=0,0,ROUND(AL30-(H31-BQ31),2)) -> 0 | AM31: =IF(I$8=0,0,ROUND(AM30-(I31-BR31),2)) -> 0 | AN31: =IF(J$8=0,0,ROUND(AN30-(J31-BS31),2)) -> 274.71 | AO31: =IF(K$8=0,0,ROUND(AO30-(K31-BT31),2)) -> 2081.58 | AP31: =IF(L$8=0,0,ROUND(AP30-(L31-BU31),2)) -> 3243.98 | ... AS31: =IF(O$8=0,0,ROUND(AS30-(O31-BX31),2)) -> 40758.35 | AT31: =IF(P$8=0,0,ROUND(AT30-(P31-BX31),2)) -> 45316.79 | AU31: =IF(Q$8=0,0,ROUND(AU30-(Q31-BY31),2)) -> 168837.86 | AV31: =IF(R$8=0,0,ROUND(AV30-(R31-BZ31),2)) -> 0 | AW31: =IF(S$8=0,0,ROUND(AW30-(S31-CA31),2)) -> 0 | AX31: =IF(T$8=0,0,ROUND(AX30-(T31-CB31),2)) -> 0 | AY31: =IF(U$8=0,0,ROUND(AY30-(U31-CC31),2)) -> 0 | AZ31: =IF(V$8=0,0,ROUND(AZ30-(V31-CD31),2)) -> 0 | BA31: =IF(W$8=0,0,ROUND(BA30-(W31-CE31),2)) -> 0 | ... BK31: =IF(AG$8=0,0,ROUND(BK30-(AG31-CO31),2)) -> 0 | BL31: =SUM(AI31:BK31) -> 277068.83 | BN31: =ROUND(AI30*E$9/12,2) -> 0 | BO31: =ROUND(AJ30*F$9/12,2) -> 0 | BP31: =ROUND(AK30*G$9/12,2) -> 0 | BQ31: =ROUND(AL30*H$9/12,2) -> 0 | BR31: =ROUND(AM30*I$9/12,2) -> 0 | BS31: =ROUND(AN30*J$9/12,2) -> 8.55 | BT31: =ROUND(AO30*K$9/12,2) -> 53.87 | BU31: =ROUND(AP30*L$9/12,2) -> 85.73 | ... CP31: =ROUND(BK30*AG$9/12,2) -> 0 | CR31: =SUM(BN31:CP31) -> 1696.84 | CT31: =IF(AI30>0,IF((AI30+BN31)<E$10,AI30+BN31,E$10),0) -> 0 | CU31: =IF(AJ30>0,IF((AJ30+BO31)<F$10,AJ30+BO31,F$10),0) -> 0 | CV31: =IF(AK30>0,IF((AK30+BP31)<G$10,AK30+BP31,G$10),0) -> 0 | CW31: =IF(AL30>0,IF((AL30+BQ31)<H$10,AL30+BQ31,H$10),0) -> 0 | CX31: =IF(AM30>0,IF((AM30+BR31)<I$10,AM30+BR31,I$10),0) -> 0 | CY31: =IF(AN30>0,IF((AN30+BS31)<J$10,AN30+BS31,J$10),0) -> 35 | CZ31: =IF(AO30>0,IF((AO30+BT31)<K$10,AO30+BT31,K$10),0) -> 206 | DA31: =IF(AP30>0,IF((AP30+BU31)<L$10,AP30+BU31,L$10),0) -> 82 | ... DX31: =IF(BM30>0,IF((BM30+CR31)<AI$10,BM30+CR31,AI$10),0) -> 0 | DY31: =SUM(CT31:DX31) -> 3828.97 | EA31: =IF(AI29<=0,0,IF(CT30+$C30>AI29+BN30,AI29+BN30-CT30,$C30)) -> 0 | EB31: =IF(AJ29<=0,0,IF($C30<=SUM($EA31:EA31),0,IF(CU30+$C30-SUM($EA31:EA31)>AJ29+BO30,AJ29+BO30-CU30,$C30-SUM($EA31:EA31)))) -> 0 | EC31: =IF(AK29<=0,0,IF($C30<=SUM($EA31:EB31),0,IF(CV30+$C30-SUM($EA31:EB31)>AK29+BP30,AK29+BP30-CV30,$C30-SUM($EA31:EB31)))) -> 0 | ED31: =IF(AL29<=0,0,IF($C30<=SUM($EA31:EC31),0,IF(CW30+$C30-SUM($EA31:EC31)>AL29+BQ30,AL29+BQ30-CW30,$C30-SUM($EA31:EC31)))) -> 0 | EE31: =IF(AM29<=0,0,IF($C30<=SUM($EA31:ED31),0,IF(CX30+$C30-SUM($EA31:ED31)>AM29+BR30,AM29+BR30-CX30,$C30-SUM($EA31:ED31)))) -> 0 | EF31: =IF(AN29<=0,0,IF($C30<=SUM($EA31:EE31),0,IF(CY30+$C30-SUM($EA31:EE31)>AN29+BS30,AN29+BS30-CY30,$C30-SUM($EA31:EE31)))) -> 43.03 | EG31: =IF(AO29<=0,0,IF($C30<=SUM($EA31:EF31),0,IF(CZ30+$C30-SUM($EA31:EF31)>AO29+BT30,AO29+BT30-CZ30,$C30-SUM($EA31:EF31)))) -> 0 | EH31: =IF(AP29<=0,0,IF($C30<=SUM($EA31:EG31),0,IF(DA30+$C30-SUM($EA31:EG31)>AP29+BU30,AP29+BU30-DA30,$C30-SUM($EA31:EG31)))) -> 0 | EI31: =IF(AQ29<=0,0,IF($C30<=SUM($EA31:EH31),0,IF(DB30+$C30-SUM($EA31:EH31)>AQ29+BV30,AQ29+BV30-DB30,$C30-SUM($EA31:EH31)))) -> 0 | ... FC31: =IF(BK29<=0,0,IF($C30<=SUM($EA31:FB31),0,IF(DV30+$C30-SUM($EA31:FB31)>BK29+CP30,BK29+CP30-DV30,$C30-SUM($EA31:FB31)))) -> 0
A32: =IF(SUM(AI31:BK31)<=0,"",A31+1) -> 12 | B32: 45992 | C32: =IF(A32="","",IF(Calculator!snowball,IF(($E$5-DY32)<0,0,$E$5-DY32),0)+D32) -> 43.03 | D32: 10 | E32: =CT32+EA33 -> 0 | F32: =CU32+EB33 -> 0 | G32: =CV32+EC33 -> 0 | H32: =CW32+ED33 -> 0 | I32: =CX32+EE33 -> 0 | J32: 83 | K32: 122 | L32: 80 | M32: 150 | N32: =DC32+EJ33 -> 450.08 | O32: =DD32+EK33 -> 695.6 | P32: =DE32+EL33 -> 791.16 | Q32: 1461.99 | R32: =DG32+EN33 -> 0 | S32: =DH32+EO33 -> 0 | T32: =DI32+EP33 -> 0 | U32: =DJ32+EQ33 -> 0 | V32: =DK32+ER33 -> 0 | W32: =DL32+ES33 -> 0 | X32: =DM32+ET33 -> 0 | Y32: =DN32+EU33 -> 0 | ... AG32: =DV32+FC33 -> 0 | AH32: =SUM(AI32:BK32) -> 274759.53 | AI32: =IF(E$8=0,0,ROUND(AI31-(E32-BN32),2)) -> 0 | AJ32: =IF(F$8=0,0,ROUND(AJ31-(F32-BO32),2)) -> 0 | AK32: =IF(G$8=0,0,ROUND(AK31-(G32-BP32),2)) -> 0 | AL32: =IF(H$8=0,0,ROUND(AL31-(H32-BQ32),2)) -> 0 | AM32: =IF(I$8=0,0,ROUND(AM31-(I32-BR32),2)) -> 0 | AN32: =IF(J$8=0,0,ROUND(AN31-(J32-BS32),2)) -> 198.53 | AO32: =IF(K$8=0,0,ROUND(AO31-(K32-BT32),2)) -> 2011.62 | AP32: =IF(L$8=0,0,ROUND(AP31-(L32-BU32),2)) -> 3249.78 | ... AS32: =IF(O$8=0,0,ROUND(AS31-(O32-BX32),2)) -> 40436.37 | AT32: =IF(P$8=0,0,ROUND(AT31-(P32-BX32),2)) -> 44899.25 | AU32: =IF(Q$8=0,0,ROUND(AU31-(Q32-BY32),2)) -> 167726.32 | AV32: =IF(R$8=0,0,ROUND(AV31-(R32-BZ32),2)) -> 0 | AW32: =IF(S$8=0,0,ROUND(AW31-(S32-CA32),2)) -> 0 | AX32: =IF(T$8=0,0,ROUND(AX31-(T32-CB32),2)) -> 0 | AY32: =IF(U$8=0,0,ROUND(AY31-(U32-CC32),2)) -> 0 | AZ32: =IF(V$8=0,0,ROUND(AZ31-(V32-CD32),2)) -> 0 | BA32: =IF(W$8=0,0,ROUND(BA31-(W32-CE32),2)) -> 0 | ... BK32: =IF(AG$8=0,0,ROUND(BK31-(AG32-CO32),2)) -> 0 | BL32: =SUM(AI32:BK32) -> 274759.53 | BN32: =ROUND(AI31*E$9/12,2) -> 0 | BO32: =ROUND(AJ31*F$9/12,2) -> 0 | BP32: =ROUND(AK31*G$9/12,2) -> 0 | BQ32: =ROUND(AL31*H$9/12,2) -> 0 | BR32: =ROUND(AM31*I$9/12,2) -> 0 | BS32: =ROUND(AN31*J$9/12,2) -> 6.82 | BT32: =ROUND(AO31*K$9/12,2) -> 52.04 | BU32: =ROUND(AP31*L$9/12,2) -> 85.8 | ... CP32: =ROUND(BK31*AG$9/12,2) -> 0 | CR32: =SUM(BN32:CP32) -> 1678.53 | CT32: =IF(AI31>0,IF((AI31+BN32)<E$10,AI31+BN32,E$10),0) -> 0 | CU32: =IF(AJ31>0,IF((AJ31+BO32)<F$10,AJ31+BO32,F$10),0) -> 0 | CV32: =IF(AK31>0,IF((AK31+BP32)<G$10,AK31+BP32,G$10),0) -> 0 | CW32: =IF(AL31>0,IF((AL31+BQ32)<H$10,AL31+BQ32,H$10),0) -> 0 | CX32: =IF(AM31>0,IF((AM31+BR32)<I$10,AM31+BR32,I$10),0) -> 0 | CY32: =IF(AN31>0,IF((AN31+BS32)<J$10,AN31+BS32,J$10),0) -> 35 | CZ32: =IF(AO31>0,IF((AO31+BT32)<K$10,AO31+BT32,K$10),0) -> 206 | DA32: =IF(AP31>0,IF((AP31+BU32)<L$10,AP31+BU32,L$10),0) -> 82 | ... DX32: =IF(BM31>0,IF((BM31+CR32)<AI$10,BM31+CR32,AI$10),0) -> 0 | DY32: =SUM(CT32:DX32) -> 3828.97 | EA32: =IF(AI30<=0,0,IF(CT31+$C31>AI30+BN31,AI30+BN31-CT31,$C31)) -> 0 | EB32: =IF(AJ30<=0,0,IF($C31<=SUM($EA32:EA32),0,IF(CU31+$C31-SUM($EA32:EA32)>AJ30+BO31,AJ30+BO31-CU31,$C31-SUM($EA32:EA32)))) -> 0 | EC32: =IF(AK30<=0,0,IF($C31<=SUM($EA32:EB32),0,IF(CV31+$C31-SUM($EA32:EB32)>AK30+BP31,AK30+BP31-CV31,$C31-SUM($EA32:EB32)))) -> 0 | ED32: =IF(AL30<=0,0,IF($C31<=SUM($EA32:EC32),0,IF(CW31+$C31-SUM($EA32:EC32)>AL30+BQ31,AL30+BQ31-CW31,$C31-SUM($EA32:EC32)))) -> 0 | EE32: =IF(AM30<=0,0,IF($C31<=SUM($EA32:ED32),0,IF(CX31+$C31-SUM($EA32:ED32)>AM30+BR31,AM30+BR31-CX31,$C31-SUM($EA32:ED32)))) -> 0 | EF32: =IF(AN30<=0,0,IF($C31<=SUM($EA32:EE32),0,IF(CY31+$C31-SUM($EA32:EE32)>AN30+BS31,AN30+BS31-CY31,$C31-SUM($EA32:EE32)))) -> 43.03 | EG32: =IF(AO30<=0,0,IF($C31<=SUM($EA32:EF32),0,IF(CZ31+$C31-SUM($EA32:EF32)>AO30+BT31,AO30+BT31-CZ31,$C31-SUM($EA32:EF32)))) -> 0 | EH32: =IF(AP30<=0,0,IF($C31<=SUM($EA32:EG32),0,IF(DA31+$C31-SUM($EA32:EG32)>AP30+BU31,AP30+BU31-DA31,$C31-SUM($EA32:EG32)))) -> 0 | EI32: =IF(AQ30<=0,0,IF($C31<=SUM($EA32:EH32),0,IF(DB31+$C31-SUM($EA32:EH32)>AQ30+BV31,AQ30+BV31-DB31,$C31-SUM($EA32:EH32)))) -> 0 | ... FC32: =IF(BK30<=0,0,IF($C31<=SUM($EA32:FB32),0,IF(DV31+$C31-SUM($EA32:FB32)>BK30+CP31,BK30+CP31-DV31,$C31-SUM($EA32:FB32)))) -> 0
A33: =IF(SUM(AI32:BK32)<=0,"",A32+1) -> 13 | B33: 46023 | C33: =IF(A33="","",IF(Calculator!snowball,IF(($E$5-DY33)<0,0,$E$5-DY33),0)+D33) -> 43.03 | D33: 10 | E33: =CT33+EA34 -> 0 | F33: =CU33+EB34 -> 0 | G33: =CV33+EC34 -> 0 | H33: =CW33+ED34 -> 0 | I33: =CX33+EE34 -> 0 | J33: 83 | K33: 125 | L33: 81 | M33: 163 | N33: =DC33+EJ34 -> 450.08 | O33: =DD33+EK34 -> 695.6 | P33: =DE33+EL34 -> 791.16 | Q33: 1461.99 | R33: =DG33+EN34 -> 0 | S33: =DH33+EO34 -> 0 | T33: =DI33+EP34 -> 0 | U33: =DJ33+EQ34 -> 0 | V33: =DK33+ER34 -> 0 | W33: =DL33+ES34 -> 0 | X33: =DM33+ET34 -> 0 | Y33: =DN33+EU34 -> 0 | ... AG33: =DV33+FC34 -> 0 | AH33: =SUM(AI33:BK33) -> 272415.23 | AI33: =IF(E$8=0,0,ROUND(AI32-(E33-BN33),2)) -> 0 | AJ33: =IF(F$8=0,0,ROUND(AJ32-(F33-BO33),2)) -> 0 | AK33: =IF(G$8=0,0,ROUND(AK32-(G33-BP33),2)) -> 0 | AL33: =IF(H$8=0,0,ROUND(AL32-(H33-BQ33),2)) -> 0 | AM33: =IF(I$8=0,0,ROUND(AM32-(I33-BR33),2)) -> 0 | AN33: =IF(J$8=0,0,ROUND(AN32-(J33-BS33),2)) -> 120.46 | AO33: =IF(K$8=0,0,ROUND(AO32-(K33-BT33),2)) -> 1936.91 | AP33: =IF(L$8=0,0,ROUND(AP32-(L33-BU33),2)) -> 3254.74 | ... AS33: =IF(O$8=0,0,ROUND(AS32-(O33-BX33),2)) -> 40111.44 | AT33: =IF(P$8=0,0,ROUND(AT32-(P33-BX33),2)) -> 44478.76 | AU33: =IF(Q$8=0,0,ROUND(AU32-(Q33-BY33),2)) -> 166611.55 | AV33: =IF(R$8=0,0,ROUND(AV32-(R33-BZ33),2)) -> 0 | AW33: =IF(S$8=0,0,ROUND(AW32-(S33-CA33),2)) -> 0 | AX33: =IF(T$8=0,0,ROUND(AX32-(T33-CB33),2)) -> 0 | AY33: =IF(U$8=0,0,ROUND(AY32-(U33-CC33),2)) -> 0 | AZ33: =IF(V$8=0,0,ROUND(AZ32-(V33-CD33),2)) -> 0 | BA33: =IF(W$8=0,0,ROUND(BA32-(W33-CE33),2)) -> 0 | ... BK33: =IF(AG$8=0,0,ROUND(BK32-(AG33-CO33),2)) -> 0 | BL33: =SUM(AI33:BK33) -> 272415.23 | BN33: =ROUND(AI32*E$9/12,2) -> 0 | BO33: =ROUND(AJ32*F$9/12,2) -> 0 | BP33: =ROUND(AK32*G$9/12,2) -> 0 | BQ33: =ROUND(AL32*H$9/12,2) -> 0 | BR33: =ROUND(AM32*I$9/12,2) -> 0 | BS33: =ROUND(AN32*J$9/12,2) -> 4.93 | BT33: =ROUND(AO32*K$9/12,2) -> 50.29 | BU33: =ROUND(AP32*L$9/12,2) -> 85.96 | ... CP33: =ROUND(BK32*AG$9/12,2) -> 0 | CR33: =SUM(BN33:CP33) -> 1660 | CT33: =IF(AI32>0,IF((AI32+BN33)<E$10,AI32+BN33,E$10),0) -> 0 | CU33: =IF(AJ32>0,IF((AJ32+BO33)<F$10,AJ32+BO33,F$10),0) -> 0 | CV33: =IF(AK32>0,IF((AK32+BP33)<G$10,AK32+BP33,G$10),0) -> 0 | CW33: =IF(AL32>0,IF((AL32+BQ33)<H$10,AL32+BQ33,H$10),0) -> 0 | CX33: =IF(AM32>0,IF((AM32+BR33)<I$10,AM32+BR33,I$10),0) -> 0 | CY33: =IF(AN32>0,IF((AN32+BS33)<J$10,AN32+BS33,J$10),0) -> 35 | CZ33: =IF(AO32>0,IF((AO32+BT33)<K$10,AO32+BT33,K$10),0) -> 206 | DA33: =IF(AP32>0,IF((AP32+BU33)<L$10,AP32+BU33,L$10),0) -> 82 | ... DX33: =IF(BM32>0,IF((BM32+CR33)<AI$10,BM32+CR33,AI$10),0) -> 0 | DY33: =SUM(CT33:DX33) -> 3828.97 | EA33: =IF(AI31<=0,0,IF(CT32+$C32>AI31+BN32,AI31+BN32-CT32,$C32)) -> 0 | EB33: =IF(AJ31<=0,0,IF($C32<=SUM($EA33:EA33),0,IF(CU32+$C32-SUM($EA33:EA33)>AJ31+BO32,AJ31+BO32-CU32,$C32-SUM($EA33:EA33)))) -> 0 | EC33: =IF(AK31<=0,0,IF($C32<=SUM($EA33:EB33),0,IF(CV32+$C32-SUM($EA33:EB33)>AK31+BP32,AK31+BP32-CV32,$C32-SUM($EA33:EB33)))) -> 0 | ED33: =IF(AL31<=0,0,IF($C32<=SUM($EA33:EC33),0,IF(CW32+$C32-SUM($EA33:EC33)>AL31+BQ32,AL31+BQ32-CW32,$C32-SUM($EA33:EC33)))) -> 0 | EE33: =IF(AM31<=0,0,IF($C32<=SUM($EA33:ED33),0,IF(CX32+$C32-SUM($EA33:ED33)>AM31+BR32,AM31+BR32-CX32,$C32-SUM($EA33:ED33)))) -> 0 | EF33: =IF(AN31<=0,0,IF($C32<=SUM($EA33:EE33),0,IF(CY32+$C32-SUM($EA33:EE33)>AN31+BS32,AN31+BS32-CY32,$C32-SUM($EA33:EE33)))) -> 43.03 | EG33: =IF(AO31<=0,0,IF($C32<=SUM($EA33:EF33),0,IF(CZ32+$C32-SUM($EA33:EF33)>AO31+BT32,AO31+BT32-CZ32,$C32-SUM($EA33:EF33)))) -> 0 | EH33: =IF(AP31<=0,0,IF($C32<=SUM($EA33:EG33),0,IF(DA32+$C32-SUM($EA33:EG33)>AP31+BU32,AP31+BU32-DA32,$C32-SUM($EA33:EG33)))) -> 0 | EI33: =IF(AQ31<=0,0,IF($C32<=SUM($EA33:EH33),0,IF(DB32+$C32-SUM($EA33:EH33)>AQ31+BV32,AQ31+BV32-DB32,$C32-SUM($EA33:EH33)))) -> 0 | ... FC33: =IF(BK31<=0,0,IF($C32<=SUM($EA33:FB33),0,IF(DV32+$C32-SUM($EA33:FB33)>BK31+CP32,BK31+CP32-DV32,$C32-SUM($EA33:FB33)))) -> 0
A34: =IF(SUM(AI33:BK33)<=0,"",A33+1) -> 14 | B34: 46054 | C34: =IF(A34="","",IF(Calculator!snowball,IF(($E$5-DY34)<0,0,$E$5-DY34),0)+D34) -> 43.03 | D34: 10 | E34: =CT34+EA35 -> 0 | F34: =CU34+EB35 -> 0 | G34: =CV34+EC35 -> 0 | H34: =CW34+ED35 -> 0 | I34: =CX34+EE35 -> 0 | J34: =CY34+EF35 -> 78.03 | K34: 122 | L34: 80 | M34: 163 | N34: =DC34+EJ35 -> 450.08 | O34: =DD34+EK35 -> 695.6 | P34: =DE34+EL35 -> 791.16 | Q34: 1461.99 | R34: =DG34+EN35 -> 0 | S34: =DH34+EO35 -> 0 | T34: =DI34+EP35 -> 0 | U34: =DJ34+EQ35 -> 0 | V34: =DK34+ER35 -> 0 | W34: =DL34+ES35 -> 0 | X34: =DM34+ET35 -> 0 | Y34: =DN34+EU35 -> 0 | ... AG34: =DV34+FC35 -> 0 | AH34: =SUM(AI34:BK34) -> 270061.2 | AI34: =IF(E$8=0,0,ROUND(AI33-(E34-BN34),2)) -> 0 | AJ34: =IF(F$8=0,0,ROUND(AJ33-(F34-BO34),2)) -> 0 | AK34: =IF(G$8=0,0,ROUND(AK33-(G34-BP34),2)) -> 0 | AL34: =IF(H$8=0,0,ROUND(AL33-(H34-BQ34),2)) -> 0 | AM34: =IF(I$8=0,0,ROUND(AM33-(I34-BR34),2)) -> 0 | AN34: =IF(J$8=0,0,ROUND(AN33-(J34-BS34),2)) -> 45.42 | AO34: =IF(K$8=0,0,ROUND(AO33-(K34-BT34),2)) -> 1863.33 | AP34: =IF(L$8=0,0,ROUND(AP33-(L34-BU34),2)) -> 3260.83 | ... AS34: =IF(O$8=0,0,ROUND(AS33-(O34-BX34),2)) -> 39783.53 | AT34: =IF(P$8=0,0,ROUND(AT33-(P34-BX34),2)) -> 44055.29 | AU34: =IF(Q$8=0,0,ROUND(AU33-(Q34-BY34),2)) -> 165493.53 | AV34: =IF(R$8=0,0,ROUND(AV33-(R34-BZ34),2)) -> 0 | AW34: =IF(S$8=0,0,ROUND(AW33-(S34-CA34),2)) -> 0 | AX34: =IF(T$8=0,0,ROUND(AX33-(T34-CB34),2)) -> 0 | AY34: =IF(U$8=0,0,ROUND(AY33-(U34-CC34),2)) -> 0 | AZ34: =IF(V$8=0,0,ROUND(AZ33-(V34-CD34),2)) -> 0 | BA34: =IF(W$8=0,0,ROUND(BA33-(W34-CE34),2)) -> 0 | ... BK34: =IF(AG$8=0,0,ROUND(BK33-(AG34-CO34),2)) -> 0 | BL34: =SUM(AI34:BK34) -> 270061.2 | BN34: =ROUND(AI33*E$9/12,2) -> 0 | BO34: =ROUND(AJ33*F$9/12,2) -> 0 | BP34: =ROUND(AK33*G$9/12,2) -> 0 | BQ34: =ROUND(AL33*H$9/12,2) -> 0 | BR34: =ROUND(AM33*I$9/12,2) -> 0 | BS34: =ROUND(AN33*J$9/12,2) -> 2.99 | BT34: =ROUND(AO33*K$9/12,2) -> 48.42 | BU34: =ROUND(AP33*L$9/12,2) -> 86.09 | ... CP34: =ROUND(BK33*AG$9/12,2) -> 0 | CR34: =SUM(BN34:CP34) -> 1640.8 | CT34: =IF(AI33>0,IF((AI33+BN34)<E$10,AI33+BN34,E$10),0) -> 0 | CU34: =IF(AJ33>0,IF((AJ33+BO34)<F$10,AJ33+BO34,F$10),0) -> 0 | CV34: =IF(AK33>0,IF((AK33+BP34)<G$10,AK33+BP34,G$10),0) -> 0 | CW34: =IF(AL33>0,IF((AL33+BQ34)<H$10,AL33+BQ34,H$10),0) -> 0 | CX34: =IF(AM33>0,IF((AM33+BR34)<I$10,AM33+BR34,I$10),0) -> 0 | CY34: =IF(AN33>0,IF((AN33+BS34)<J$10,AN33+BS34,J$10),0) -> 35 | CZ34: =IF(AO33>0,IF((AO33+BT34)<K$10,AO33+BT34,K$10),0) -> 206 | DA34: =IF(AP33>0,IF((AP33+BU34)<L$10,AP33+BU34,L$10),0) -> 82 | ... DX34: =IF(BM33>0,IF((BM33+CR34)<AI$10,BM33+CR34,AI$10),0) -> 0 | DY34: =SUM(CT34:DX34) -> 3828.97 | EA34: =IF(AI32<=0,0,IF(CT33+$C33>AI32+BN33,AI32+BN33-CT33,$C33)) -> 0 | EB34: =IF(AJ32<=0,0,IF($C33<=SUM($EA34:EA34),0,IF(CU33+$C33-SUM($EA34:EA34)>AJ32+BO33,AJ32+BO33-CU33,$C33-SUM($EA34:EA34)))) -> 0 | EC34: =IF(AK32<=0,0,IF($C33<=SUM($EA34:EB34),0,IF(CV33+$C33-SUM($EA34:EB34)>AK32+BP33,AK32+BP33-CV33,$C33-SUM($EA34:EB34)))) -> 0 | ED34: =IF(AL32<=0,0,IF($C33<=SUM($EA34:EC34),0,IF(CW33+$C33-SUM($EA34:EC34)>AL32+BQ33,AL32+BQ33-CW33,$C33-SUM($EA34:EC34)))) -> 0 | EE34: =IF(AM32<=0,0,IF($C33<=SUM($EA34:ED34),0,IF(CX33+$C33-SUM($EA34:ED34)>AM32+BR33,AM32+BR33-CX33,$C33-SUM($EA34:ED34)))) -> 0 | EF34: =IF(AN32<=0,0,IF($C33<=SUM($EA34:EE34),0,IF(CY33+$C33-SUM($EA34:EE34)>AN32+BS33,AN32+BS33-CY33,$C33-SUM($EA34:EE34)))) -> 43.03 | EG34: =IF(AO32<=0,0,IF($C33<=SUM($EA34:EF34),0,IF(CZ33+$C33-SUM($EA34:EF34)>AO32+BT33,AO32+BT33-CZ33,$C33-SUM($EA34:EF34)))) -> 0 | EH34: =IF(AP32<=0,0,IF($C33<=SUM($EA34:EG34),0,IF(DA33+$C33-SUM($EA34:EG34)>AP32+BU33,AP32+BU33-DA33,$C33-SUM($EA34:EG34)))) -> 0 | EI34: =IF(AQ32<=0,0,IF($C33<=SUM($EA34:EH34),0,IF(DB33+$C33-SUM($EA34:EH34)>AQ32+BV33,AQ32+BV33-DB33,$C33-SUM($EA34:EH34)))) -> 0 | ... FC34: =IF(BK32<=0,0,IF($C33<=SUM($EA34:FB34),0,IF(DV33+$C33-SUM($EA34:FB34)>BK32+CP33,BK32+CP33-DV33,$C33-SUM($EA34:FB34)))) -> 0
A35: =IF(SUM(AI34:BK34)<=0,"",A34+1) -> 15 | B35: 46082 | C35: =IF(A35="","",IF(Calculator!snowball,IF(($E$5-DY35)<0,0,$E$5-DY35),0)+D35) -> 43.03 | D35: 10 | E35: =CT35+EA36 -> 0 | F35: =CU35+EB36 -> 0 | G35: =CV35+EC36 -> 0 | H35: =CW35+ED36 -> 0 | I35: =CX35+EE36 -> 0 | J35: =CY35+EF36 -> 46.55 | K35: 113 | L35: 73 | M35: 151 | N35: =DC35+EJ36 -> 450.08 | O35: =DD35+EK36 -> 695.6 | P35: =DE35+EL36 -> 791.16 | Q35: =DF35+EM36 -> 1467.13 | R35: =DG35+EN36 -> 0 | S35: =DH35+EO36 -> 0 | T35: =DI35+EP36 -> 0 | U35: =DJ35+EQ36 -> 0 | ... AG35: =DV35+FC36 -> 0 | AH35: =SUM(AI35:BK35) -> 267742.74 | AI35: =IF(E$8=0,0,ROUND(AI34-(E35-BN35),2)) -> 0 | AJ35: =IF(F$8=0,0,ROUND(AJ34-(F35-BO35),2)) -> 0 | AK35: =IF(G$8=0,0,ROUND(AK34-(G35-BP35),2)) -> 0 | AL35: =IF(H$8=0,0,ROUND(AL34-(H35-BQ35),2)) -> 0 | AM35: =IF(I$8=0,0,ROUND(AM34-(I35-BR35),2)) -> 0 | AN35: =IF(J$8=0,0,ROUND(AN34-(J35-BS35),2)) -> 0 | AO35: =IF(K$8=0,0,ROUND(AO34-(K35-BT35),2)) -> 1796.91 | AP35: =IF(L$8=0,0,ROUND(AP34-(L35-BU35),2)) -> 3274.08 | ... AS35: =IF(O$8=0,0,ROUND(AS34-(O35-BX35),2)) -> 39452.61 | AT35: =IF(P$8=0,0,ROUND(AT34-(P35-BX35),2)) -> 43628.81 | AU35: =IF(Q$8=0,0,ROUND(AU34-(Q35-BY35),2)) -> 164367.09 | AV35: =IF(R$8=0,0,ROUND(AV34-(R35-BZ35),2)) -> 0 | AW35: =IF(S$8=0,0,ROUND(AW34-(S35-CA35),2)) -> 0 | AX35: =IF(T$8=0,0,ROUND(AX34-(T35-CB35),2)) -> 0 | AY35: =IF(U$8=0,0,ROUND(AY34-(U35-CC35),2)) -> 0 | AZ35: =IF(V$8=0,0,ROUND(AZ34-(V35-CD35),2)) -> 0 | BA35: =IF(W$8=0,0,ROUND(BA34-(W35-CE35),2)) -> 0 | ... BK35: =IF(AG$8=0,0,ROUND(BK34-(AG35-CO35),2)) -> 0 | BL35: =SUM(AI35:BK35) -> 267742.74 | BN35: =ROUND(AI34*E$9/12,2) -> 0 | BO35: =ROUND(AJ34*F$9/12,2) -> 0 | BP35: =ROUND(AK34*G$9/12,2) -> 0 | BQ35: =ROUND(AL34*H$9/12,2) -> 0 | BR35: =ROUND(AM34*I$9/12,2) -> 0 | BS35: =ROUND(AN34*J$9/12,2) -> 1.13 | BT35: =ROUND(AO34*K$9/12,2) -> 46.58 | BU35: =ROUND(AP34*L$9/12,2) -> 86.25 | ... CP35: =ROUND(BK34*AG$9/12,2) -> 0 | CR35: =SUM(BN35:CP35) -> 1621.55 | CT35: =IF(AI34>0,IF((AI34+BN35)<E$10,AI34+BN35,E$10),0) -> 0 | CU35: =IF(AJ34>0,IF((AJ34+BO35)<F$10,AJ34+BO35,F$10),0) -> 0 | CV35: =IF(AK34>0,IF((AK34+BP35)<G$10,AK34+BP35,G$10),0) -> 0 | CW35: =IF(AL34>0,IF((AL34+BQ35)<H$10,AL34+BQ35,H$10),0) -> 0 | CX35: =IF(AM34>0,IF((AM34+BR35)<I$10,AM34+BR35,I$10),0) -> 0 | CY35: =IF(AN34>0,IF((AN34+BS35)<J$10,AN34+BS35,J$10),0) -> 35 | CZ35: =IF(AO34>0,IF((AO34+BT35)<K$10,AO34+BT35,K$10),0) -> 206 | DA35: =IF(AP34>0,IF((AP34+BU35)<L$10,AP34+BU35,L$10),0) -> 82 | ... DX35: =IF(BM34>0,IF((BM34+CR35)<AI$10,BM34+CR35,AI$10),0) -> 0 | DY35: =SUM(CT35:DX35) -> 3828.97 | EA35: =IF(AI33<=0,0,IF(CT34+$C34>AI33+BN34,AI33+BN34-CT34,$C34)) -> 0 | EB35: =IF(AJ33<=0,0,IF($C34<=SUM($EA35:EA35),0,IF(CU34+$C34-SUM($EA35:EA35)>AJ33+BO34,AJ33+BO34-CU34,$C34-SUM($EA35:EA35)))) -> 0 | EC35: =IF(AK33<=0,0,IF($C34<=SUM($EA35:EB35),0,IF(CV34+$C34-SUM($EA35:EB35)>AK33+BP34,AK33+BP34-CV34,$C34-SUM($EA35:EB35)))) -> 0 | ED35: =IF(AL33<=0,0,IF($C34<=SUM($EA35:EC35),0,IF(CW34+$C34-SUM($EA35:EC35)>AL33+BQ34,AL33+BQ34-CW34,$C34-SUM($EA35:EC35)))) -> 0 | EE35: =IF(AM33<=0,0,IF($C34<=SUM($EA35:ED35),0,IF(CX34+$C34-SUM($EA35:ED35)>AM33+BR34,AM33+BR34-CX34,$C34-SUM($EA35:ED35)))) -> 0 | EF35: =IF(AN33<=0,0,IF($C34<=SUM($EA35:EE35),0,IF(CY34+$C34-SUM($EA35:EE35)>AN33+BS34,AN33+BS34-CY34,$C34-SUM($EA35:EE35)))) -> 43.03 | EG35: =IF(AO33<=0,0,IF($C34<=SUM($EA35:EF35),0,IF(CZ34+$C34-SUM($EA35:EF35)>AO33+BT34,AO33+BT34-CZ34,$C34-SUM($EA35:EF35)))) -> 0 | EH35: =IF(AP33<=0,0,IF($C34<=SUM($EA35:EG35),0,IF(DA34+$C34-SUM($EA35:EG35)>AP33+BU34,AP33+BU34-DA34,$C34-SUM($EA35:EG35)))) -> 0 | EI35: =IF(AQ33<=0,0,IF($C34<=SUM($EA35:EH35),0,IF(DB34+$C34-SUM($EA35:EH35)>AQ33+BV34,AQ33+BV34-DB34,$C34-SUM($EA35:EH35)))) -> 0 | ... FC35: =IF(BK33<=0,0,IF($C34<=SUM($EA35:FB35),0,IF(DV34+$C34-SUM($EA35:FB35)>BK33+CP34,BK33+CP34-DV34,$C34-SUM($EA35:FB35)))) -> 0
A36: =IF(SUM(AI35:BK35)<=0,"",A35+1) -> 16 | B36: 46113 | C36: =IF(A36="","",IF(Calculator!snowball,IF(($E$5-DY36)<0,0,$E$5-DY36),0)+D36) -> 78.03 | D36: 10 | E36: =CT36+EA37 -> 0 | F36: =CU36+EB37 -> 0 | G36: =CV36+EC37 -> 0 | H36: =CW36+ED37 -> 0 | I36: =CX36+EE37 -> 0 | J36: =CY36+EF37 -> 0 | K36: 125 | L36: 80 | M36: 151 | N36: =DC36+EJ37 -> 450.08 | O36: =DD36+EK37 -> 695.6 | P36: =DE36+EL37 -> 791.16 | Q36: =DF36+EM37 -> 1467.13 | R36: =DG36+EN37 -> 0 | S36: =DH36+EO37 -> 0 | T36: =DI36+EP37 -> 0 | U36: =DJ36+EQ37 -> 0 | ... AG36: =DV36+FC37 -> 0 | AH36: =SUM(AI36:BK36) -> 265434.31 | AI36: =IF(E$8=0,0,ROUND(AI35-(E36-BN36),2)) -> 0 | AJ36: =IF(F$8=0,0,ROUND(AJ35-(F36-BO36),2)) -> 0 | AK36: =IF(G$8=0,0,ROUND(AK35-(G36-BP36),2)) -> 0 | AL36: =IF(H$8=0,0,ROUND(AL35-(H36-BQ36),2)) -> 0 | AM36: =IF(I$8=0,0,ROUND(AM35-(I36-BR36),2)) -> 0 | AN36: =IF(J$8=0,0,ROUND(AN35-(J36-BS36),2)) -> 0 | AO36: =IF(K$8=0,0,ROUND(AO35-(K36-BT36),2)) -> 1716.83 | AP36: =IF(L$8=0,0,ROUND(AP35-(L36-BU36),2)) -> 3280.68 | ... AS36: =IF(O$8=0,0,ROUND(AS35-(O36-BX36),2)) -> 39118.66 | AT36: =IF(P$8=0,0,ROUND(AT35-(P36-BX36),2)) -> 43199.3 | AU36: =IF(Q$8=0,0,ROUND(AU35-(Q36-BY36),2)) -> 163237.36 | AV36: =IF(R$8=0,0,ROUND(AV35-(R36-BZ36),2)) -> 0 | AW36: =IF(S$8=0,0,ROUND(AW35-(S36-CA36),2)) -> 0 | AX36: =IF(T$8=0,0,ROUND(AX35-(T36-CB36),2)) -> 0 | AY36: =IF(U$8=0,0,ROUND(AY35-(U36-CC36),2)) -> 0 | AZ36: =IF(V$8=0,0,ROUND(AZ35-(V36-CD36),2)) -> 0 | BA36: =IF(W$8=0,0,ROUND(BA35-(W36-CE36),2)) -> 0 | ... BK36: =IF(AG$8=0,0,ROUND(BK35-(AG36-CO36),2)) -> 0 | BL36: =SUM(AI36:BK36) -> 265434.31 | BN36: =ROUND(AI35*E$9/12,2) -> 0 | BO36: =ROUND(AJ35*F$9/12,2) -> 0 | BP36: =ROUND(AK35*G$9/12,2) -> 0 | BQ36: =ROUND(AL35*H$9/12,2) -> 0 | BR36: =ROUND(AM35*I$9/12,2) -> 0 | BS36: =ROUND(AN35*J$9/12,2) -> 0 | BT36: =ROUND(AO35*K$9/12,2) -> 44.92 | BU36: =ROUND(AP35*L$9/12,2) -> 86.6 | ... CP36: =ROUND(BK35*AG$9/12,2) -> 0 | CR36: =SUM(BN36:CP36) -> 1603.54 | CT36: =IF(AI35>0,IF((AI35+BN36)<E$10,AI35+BN36,E$10),0) -> 0 | CU36: =IF(AJ35>0,IF((AJ35+BO36)<F$10,AJ35+BO36,F$10),0) -> 0 | CV36: =IF(AK35>0,IF((AK35+BP36)<G$10,AK35+BP36,G$10),0) -> 0 | CW36: =IF(AL35>0,IF((AL35+BQ36)<H$10,AL35+BQ36,H$10),0) -> 0 | CX36: =IF(AM35>0,IF((AM35+BR36)<I$10,AM35+BR36,I$10),0) -> 0 | CY36: =IF(AN35>0,IF((AN35+BS36)<J$10,AN35+BS36,J$10),0) -> 0 | CZ36: =IF(AO35>0,IF((AO35+BT36)<K$10,AO35+BT36,K$10),0) -> 206 | DA36: =IF(AP35>0,IF((AP35+BU36)<L$10,AP35+BU36,L$10),0) -> 82 | ... DX36: =IF(BM35>0,IF((BM35+CR36)<AI$10,BM35+CR36,AI$10),0) -> 0 | DY36: =SUM(CT36:DX36) -> 3793.97 | EA36: =IF(AI34<=0,0,IF(CT35+$C35>AI34+BN35,AI34+BN35-CT35,$C35)) -> 0 | EB36: =IF(AJ34<=0,0,IF($C35<=SUM($EA36:EA36),0,IF(CU35+$C35-SUM($EA36:EA36)>AJ34+BO35,AJ34+BO35-CU35,$C35-SUM($EA36:EA36)))) -> 0 | EC36: =IF(AK34<=0,0,IF($C35<=SUM($EA36:EB36),0,IF(CV35+$C35-SUM($EA36:EB36)>AK34+BP35,AK34+BP35-CV35,$C35-SUM($EA36:EB36)))) -> 0 | ED36: =IF(AL34<=0,0,IF($C35<=SUM($EA36:EC36),0,IF(CW35+$C35-SUM($EA36:EC36)>AL34+BQ35,AL34+BQ35-CW35,$C35-SUM($EA36:EC36)))) -> 0 | EE36: =IF(AM34<=0,0,IF($C35<=SUM($EA36:ED36),0,IF(CX35+$C35-SUM($EA36:ED36)>AM34+BR35,AM34+BR35-CX35,$C35-SUM($EA36:ED36)))) -> 0 | EF36: =IF(AN34<=0,0,IF($C35<=SUM($EA36:EE36),0,IF(CY35+$C35-SUM($EA36:EE36)>AN34+BS35,AN34+BS35-CY35,$C35-SUM($EA36:EE36)))) -> 11.55 | EG36: =IF(AO34<=0,0,IF($C35<=SUM($EA36:EF36),0,IF(CZ35+$C35-SUM($EA36:EF36)>AO34+BT35,AO34+BT35-CZ35,$C35-SUM($EA36:EF36)))) -> 31.48 | EH36: =IF(AP34<=0,0,IF($C35<=SUM($EA36:EG36),0,IF(DA35+$C35-SUM($EA36:EG36)>AP34+BU35,AP34+BU35-DA35,$C35-SUM($EA36:EG36)))) -> 0 | EI36: =IF(AQ34<=0,0,IF($C35<=SUM($EA36:EH36),0,IF(DB35+$C35-SUM($EA36:EH36)>AQ34+BV35,AQ34+BV35-DB35,$C35-SUM($EA36:EH36)))) -> 0 | ... FC36: =IF(BK34<=0,0,IF($C35<=SUM($EA36:FB36),0,IF(DV35+$C35-SUM($EA36:FB36)>BK34+CP35,BK34+CP35-DV35,$C35-SUM($EA36:FB36)))) -> 0
A37: =IF(SUM(AI36:BK36)<=0,"",A36+1) -> 17 | B37: 46143 | C37: =IF(A37="","",IF(Calculator!snowball,IF(($E$5-DY37)<0,0,$E$5-DY37),0)+D37) -> 78.03 | D37: 10 | E37: =CT37+EA38 -> 0 | F37: =CU37+EB38 -> 0 | G37: =CV37+EC38 -> 0 | H37: =CW37+ED38 -> 0 | I37: =CX37+EE38 -> 0 | J37: =CY37+EF38 -> 0 | K37: 125 | L37: 80 | M37: 151 | N37: =DC37+EJ38 -> 450.08 | O37: =DD37+EK38 -> 695.6 | P37: =DE37+EL38 -> 791.16 | Q37: 1467.13 | R37: =DG37+EN38 -> 0 | S37: =DH37+EO38 -> 0 | T37: =DI37+EP38 -> 0 | U37: =DJ37+EQ38 -> 0 | V37: =DK37+ER38 -> 0 | W37: =DL37+ES38 -> 0 | X37: =DM37+ET38 -> 0 | Y37: =DN37+EU38 -> 0 | ... AG37: =DV37+FC38 -> 0 | AH37: =SUM(AI37:BK37) -> 263108.76 | AI37: =IF(E$8=0,0,ROUND(AI36-(E37-BN37),2)) -> 0 | AJ37: =IF(F$8=0,0,ROUND(AJ36-(F37-BO37),2)) -> 0 | AK37: =IF(G$8=0,0,ROUND(AK36-(G37-BP37),2)) -> 0 | AL37: =IF(H$8=0,0,ROUND(AL36-(H37-BQ37),2)) -> 0 | AM37: =IF(I$8=0,0,ROUND(AM36-(I37-BR37),2)) -> 0 | AN37: =IF(J$8=0,0,ROUND(AN36-(J37-BS37),2)) -> 0 | AO37: =IF(K$8=0,0,ROUND(AO36-(K37-BT37),2)) -> 1634.75 | AP37: =IF(L$8=0,0,ROUND(AP36-(L37-BU37),2)) -> 3287.45 | ... AS37: =IF(O$8=0,0,ROUND(AS36-(O37-BX37),2)) -> 38781.65 | AT37: =IF(P$8=0,0,ROUND(AT36-(P37-BX37),2)) -> 42766.73 | AU37: =IF(Q$8=0,0,ROUND(AU36-(Q37-BY37),2)) -> 162104.3 | AV37: =IF(R$8=0,0,ROUND(AV36-(R37-BZ37),2)) -> 0 | AW37: =IF(S$8=0,0,ROUND(AW36-(S37-CA37),2)) -> 0 | AX37: =IF(T$8=0,0,ROUND(AX36-(T37-CB37),2)) -> 0 | AY37: =IF(U$8=0,0,ROUND(AY36-(U37-CC37),2)) -> 0 | AZ37: =IF(V$8=0,0,ROUND(AZ36-(V37-CD37),2)) -> 0 | BA37: =IF(W$8=0,0,ROUND(BA36-(W37-CE37),2)) -> 0 | ... BK37: =IF(AG$8=0,0,ROUND(BK36-(AG37-CO37),2)) -> 0 | BL37: =SUM(AI37:BK37) -> 263108.76 | BN37: =ROUND(AI36*E$9/12,2) -> 0 | BO37: =ROUND(AJ36*F$9/12,2) -> 0 | BP37: =ROUND(AK36*G$9/12,2) -> 0 | BQ37: =ROUND(AL36*H$9/12,2) -> 0 | BR37: =ROUND(AM36*I$9/12,2) -> 0 | BS37: =ROUND(AN36*J$9/12,2) -> 0 | BT37: =ROUND(AO36*K$9/12,2) -> 42.92 | BU37: =ROUND(AP36*L$9/12,2) -> 86.77 | ... CP37: =ROUND(BK36*AG$9/12,2) -> 0 | CR37: =SUM(BN37:CP37) -> 1585.95 | CT37: =IF(AI36>0,IF((AI36+BN37)<E$10,AI36+BN37,E$10),0) -> 0 | CU37: =IF(AJ36>0,IF((AJ36+BO37)<F$10,AJ36+BO37,F$10),0) -> 0 | CV37: =IF(AK36>0,IF((AK36+BP37)<G$10,AK36+BP37,G$10),0) -> 0 | CW37: =IF(AL36>0,IF((AL36+BQ37)<H$10,AL36+BQ37,H$10),0) -> 0 | CX37: =IF(AM36>0,IF((AM36+BR37)<I$10,AM36+BR37,I$10),0) -> 0 | CY37: =IF(AN36>0,IF((AN36+BS37)<J$10,AN36+BS37,J$10),0) -> 0 | CZ37: =IF(AO36>0,IF((AO36+BT37)<K$10,AO36+BT37,K$10),0) -> 206 | DA37: =IF(AP36>0,IF((AP36+BU37)<L$10,AP36+BU37,L$10),0) -> 82 | ... DX37: =IF(BM36>0,IF((BM36+CR37)<AI$10,BM36+CR37,AI$10),0) -> 0 | DY37: =SUM(CT37:DX37) -> 3793.97 | EA37: =IF(AI35<=0,0,IF(CT36+$C36>AI35+BN36,AI35+BN36-CT36,$C36)) -> 0 | EB37: =IF(AJ35<=0,0,IF($C36<=SUM($EA37:EA37),0,IF(CU36+$C36-SUM($EA37:EA37)>AJ35+BO36,AJ35+BO36-CU36,$C36-SUM($EA37:EA37)))) -> 0 | EC37: =IF(AK35<=0,0,IF($C36<=SUM($EA37:EB37),0,IF(CV36+$C36-SUM($EA37:EB37)>AK35+BP36,AK35+BP36-CV36,$C36-SUM($EA37:EB37)))) -> 0 | ED37: =IF(AL35<=0,0,IF($C36<=SUM($EA37:EC37),0,IF(CW36+$C36-SUM($EA37:EC37)>AL35+BQ36,AL35+BQ36-CW36,$C36-SUM($EA37:EC37)))) -> 0 | EE37: =IF(AM35<=0,0,IF($C36<=SUM($EA37:ED37),0,IF(CX36+$C36-SUM($EA37:ED37)>AM35+BR36,AM35+BR36-CX36,$C36-SUM($EA37:ED37)))) -> 0 | EF37: =IF(AN35<=0,0,IF($C36<=SUM($EA37:EE37),0,IF(CY36+$C36-SUM($EA37:EE37)>AN35+BS36,AN35+BS36-CY36,$C36-SUM($EA37:EE37)))) -> 0 | EG37: =IF(AO35<=0,0,IF($C36<=SUM($EA37:EF37),0,IF(CZ36+$C36-SUM($EA37:EF37)>AO35+BT36,AO35+BT36-CZ36,$C36-SUM($EA37:EF37)))) -> 78.03 | EH37: =IF(AP35<=0,0,IF($C36<=SUM($EA37:EG37),0,IF(DA36+$C36-SUM($EA37:EG37)>AP35+BU36,AP35+BU36-DA36,$C36-SUM($EA37:EG37)))) -> 0 | EI37: =IF(AQ35<=0,0,IF($C36<=SUM($EA37:EH37),0,IF(DB36+$C36-SUM($EA37:EH37)>AQ35+BV36,AQ35+BV36-DB36,$C36-SUM($EA37:EH37)))) -> 0 | ... FC37: =IF(BK35<=0,0,IF($C36<=SUM($EA37:FB37),0,IF(DV36+$C36-SUM($EA37:FB37)>BK35+CP36,BK35+CP36-DV36,$C36-SUM($EA37:FB37)))) -> 0
A38: =IF(SUM(AI37:BK37)<=0,"",A37+1) -> 18 | B38: 46174 | C38: =IF(A38="","",IF(Calculator!snowball,IF(($E$5-DY38)<0,0,$E$5-DY38),0)+D38) -> 78.03 | D38: 10 | E38: =CT38+EA39 -> 0 | F38: =CU38+EB39 -> 0 | G38: =CV38+EC39 -> 0 | H38: =CW38+ED39 -> 0 | I38: =CX38+EE39 -> 0 | J38: =CY38+EF39 -> 0 | K38: 125 | L38: 80 | M38: 151 | N38: =DC38+EJ39 -> 450.08 | O38: =DD38+EK39 -> 695.6 | P38: =DE38+EL39 -> 791.16 | Q38: =DF38+EM39 -> 1467.13 | R38: =DG38+EN39 -> 0 | S38: =DH38+EO39 -> 0 | T38: =DI38+EP39 -> 0 | U38: =DJ38+EQ39 -> 0 | ... AG38: =DV38+FC39 -> 0 | AH38: =SUM(AI38:BK38) -> 260765.88 | AI38: =IF(E$8=0,0,ROUND(AI37-(E38-BN38),2)) -> 0 | AJ38: =IF(F$8=0,0,ROUND(AJ37-(F38-BO38),2)) -> 0 | AK38: =IF(G$8=0,0,ROUND(AK37-(G38-BP38),2)) -> 0 | AL38: =IF(H$8=0,0,ROUND(AL37-(H38-BQ38),2)) -> 0 | AM38: =IF(I$8=0,0,ROUND(AM37-(I38-BR38),2)) -> 0 | AN38: =IF(J$8=0,0,ROUND(AN37-(J38-BS38),2)) -> 0 | AO38: =IF(K$8=0,0,ROUND(AO37-(K38-BT38),2)) -> 1550.62 | AP38: =IF(L$8=0,0,ROUND(AP37-(L38-BU38),2)) -> 3294.4 | ... AS38: =IF(O$8=0,0,ROUND(AS37-(O38-BX38),2)) -> 38441.55 | AT38: =IF(P$8=0,0,ROUND(AT37-(P38-BX38),2)) -> 42331.07 | AU38: =IF(Q$8=0,0,ROUND(AU37-(Q38-BY38),2)) -> 160967.9 | AV38: =IF(R$8=0,0,ROUND(AV37-(R38-BZ38),2)) -> 0 | AW38: =IF(S$8=0,0,ROUND(AW37-(S38-CA38),2)) -> 0 | AX38: =IF(T$8=0,0,ROUND(AX37-(T38-CB38),2)) -> 0 | AY38: =IF(U$8=0,0,ROUND(AY37-(U38-CC38),2)) -> 0 | AZ38: =IF(V$8=0,0,ROUND(AZ37-(V38-CD38),2)) -> 0 | BA38: =IF(W$8=0,0,ROUND(BA37-(W38-CE38),2)) -> 0 | ... BK38: =IF(AG$8=0,0,ROUND(BK37-(AG38-CO38),2)) -> 0 | BL38: =SUM(AI38:BK38) -> 260765.88 | BN38: =ROUND(AI37*E$9/12,2) -> 0 | BO38: =ROUND(AJ37*F$9/12,2) -> 0 | BP38: =ROUND(AK37*G$9/12,2) -> 0 | BQ38: =ROUND(AL37*H$9/12,2) -> 0 | BR38: =ROUND(AM37*I$9/12,2) -> 0 | BS38: =ROUND(AN37*J$9/12,2) -> 0 | BT38: =ROUND(AO37*K$9/12,2) -> 40.87 | BU38: =ROUND(AP37*L$9/12,2) -> 86.95 | ... CP38: =ROUND(BK37*AG$9/12,2) -> 0 | CR38: =SUM(BN38:CP38) -> 1568.17 | CT38: =IF(AI37>0,IF((AI37+BN38)<E$10,AI37+BN38,E$10),0) -> 0 | CU38: =IF(AJ37>0,IF((AJ37+BO38)<F$10,AJ37+BO38,F$10),0) -> 0 | CV38: =IF(AK37>0,IF((AK37+BP38)<G$10,AK37+BP38,G$10),0) -> 0 | CW38: =IF(AL37>0,IF((AL37+BQ38)<H$10,AL37+BQ38,H$10),0) -> 0 | CX38: =IF(AM37>0,IF((AM37+BR38)<I$10,AM37+BR38,I$10),0) -> 0 | CY38: =IF(AN37>0,IF((AN37+BS38)<J$10,AN37+BS38,J$10),0) -> 0 | CZ38: =IF(AO37>0,IF((AO37+BT38)<K$10,AO37+BT38,K$10),0) -> 206 | DA38: =IF(AP37>0,IF((AP37+BU38)<L$10,AP37+BU38,L$10),0) -> 82 | ... DX38: =IF(BM37>0,IF((BM37+CR38)<AI$10,BM37+CR38,AI$10),0) -> 0 | DY38: =SUM(CT38:DX38) -> 3793.97 | EA38: =IF(AI36<=0,0,IF(CT37+$C37>AI36+BN37,AI36+BN37-CT37,$C37)) -> 0 | EB38: =IF(AJ36<=0,0,IF($C37<=SUM($EA38:EA38),0,IF(CU37+$C37-SUM($EA38:EA38)>AJ36+BO37,AJ36+BO37-CU37,$C37-SUM($EA38:EA38)))) -> 0 | EC38: =IF(AK36<=0,0,IF($C37<=SUM($EA38:EB38),0,IF(CV37+$C37-SUM($EA38:EB38)>AK36+BP37,AK36+BP37-CV37,$C37-SUM($EA38:EB38)))) -> 0 | ED38: =IF(AL36<=0,0,IF($C37<=SUM($EA38:EC38),0,IF(CW37+$C37-SUM($EA38:EC38)>AL36+BQ37,AL36+BQ37-CW37,$C37-SUM($EA38:EC38)))) -> 0 | EE38: =IF(AM36<=0,0,IF($C37<=SUM($EA38:ED38),0,IF(CX37+$C37-SUM($EA38:ED38)>AM36+BR37,AM36+BR37-CX37,$C37-SUM($EA38:ED38)))) -> 0 | EF38: =IF(AN36<=0,0,IF($C37<=SUM($EA38:EE38),0,IF(CY37+$C37-SUM($EA38:EE38)>AN36+BS37,AN36+BS37-CY37,$C37-SUM($EA38:EE38)))) -> 0 | EG38: =IF(AO36<=0,0,IF($C37<=SUM($EA38:EF38),0,IF(CZ37+$C37-SUM($EA38:EF38)>AO36+BT37,AO36+BT37-CZ37,$C37-SUM($EA38:EF38)))) -> 78.03 | EH38: =IF(AP36<=0,0,IF($C37<=SUM($EA38:EG38),0,IF(DA37+$C37-SUM($EA38:EG38)>AP36+BU37,AP36+BU37-DA37,$C37-SUM($EA38:EG38)))) -> 0 | EI38: =IF(AQ36<=0,0,IF($C37<=SUM($EA38:EH38),0,IF(DB37+$C37-SUM($EA38:EH38)>AQ36+BV37,AQ36+BV37-DB37,$C37-SUM($EA38:EH38)))) -> 0 | ... FC38: =IF(BK36<=0,0,IF($C37<=SUM($EA38:FB38),0,IF(DV37+$C37-SUM($EA38:FB38)>BK36+CP37,BK36+CP37-DV37,$C37-SUM($EA38:FB38)))) -> 0
A39: =IF(SUM(AI38:BK38)<=0,"",A38+1) -> 19 | B39: 46204 | C39: =IF(A39="","",IF(Calculator!snowball,IF(($E$5-DY39)<0,0,$E$5-DY39),0)+D39) -> 118.03 | D39: 50 | E39: =CT39+EA40 -> 0 | F39: =CU39+EB40 -> 0 | G39: =CV39+EC40 -> 0 | H39: =CW39+ED40 -> 0 | I39: =CX39+EE40 -> 0 | J39: =CY39+EF40 -> 0 | K39: 175 | L39: 80 | M39: 151 | N39: =DC39+EJ40 -> 450.08 | O39: =DD39+EK40 -> 695.6 | P39: =DE39+EL40 -> 791.16 | Q39: =DF39+EM40 -> 1467.13 | R39: =DG39+EN40 -> 0 | S39: =DH39+EO40 -> 0 | T39: =DI39+EP40 -> 0 | U39: =DJ39+EQ40 -> 0 | ... AG39: =DV39+FC40 -> 0 | AH39: =SUM(AI39:BK39) -> 258355.43 | AI39: =IF(E$8=0,0,ROUND(AI38-(E39-BN39),2)) -> 0 | AJ39: =IF(F$8=0,0,ROUND(AJ38-(F39-BO39),2)) -> 0 | AK39: =IF(G$8=0,0,ROUND(AK38-(G39-BP39),2)) -> 0 | AL39: =IF(H$8=0,0,ROUND(AL38-(H39-BQ39),2)) -> 0 | AM39: =IF(I$8=0,0,ROUND(AM38-(I39-BR39),2)) -> 0 | AN39: =IF(J$8=0,0,ROUND(AN38-(J39-BS39),2)) -> 0 | AO39: =IF(K$8=0,0,ROUND(AO38-(K39-BT39),2)) -> 1414.39 | AP39: =IF(L$8=0,0,ROUND(AP38-(L39-BU39),2)) -> 3301.54 | ... AS39: =IF(O$8=0,0,ROUND(AS38-(O39-BX39),2)) -> 38098.33 | AT39: =IF(P$8=0,0,ROUND(AT38-(P39-BX39),2)) -> 41892.29 | AU39: =IF(Q$8=0,0,ROUND(AU38-(Q39-BY39),2)) -> 159828.13 | AV39: =IF(R$8=0,0,ROUND(AV38-(R39-BZ39),2)) -> 0 | AW39: =IF(S$8=0,0,ROUND(AW38-(S39-CA39),2)) -> 0 | AX39: =IF(T$8=0,0,ROUND(AX38-(T39-CB39),2)) -> 0 | AY39: =IF(U$8=0,0,ROUND(AY38-(U39-CC39),2)) -> 0 | AZ39: =IF(V$8=0,0,ROUND(AZ38-(V39-CD39),2)) -> 0 | BA39: =IF(W$8=0,0,ROUND(BA38-(W39-CE39),2)) -> 0 | ... BK39: =IF(AG$8=0,0,ROUND(BK38-(AG39-CO39),2)) -> 0 | BL39: =SUM(AI39:BK39) -> 258355.43 | BN39: =ROUND(AI38*E$9/12,2) -> 0 | BO39: =ROUND(AJ38*F$9/12,2) -> 0 | BP39: =ROUND(AK38*G$9/12,2) -> 0 | BQ39: =ROUND(AL38*H$9/12,2) -> 0 | BR39: =ROUND(AM38*I$9/12,2) -> 0 | BS39: =ROUND(AN38*J$9/12,2) -> 0 | BT39: =ROUND(AO38*K$9/12,2) -> 38.77 | BU39: =ROUND(AP38*L$9/12,2) -> 87.14 | ... CP39: =ROUND(BK38*AG$9/12,2) -> 0 | CR39: =SUM(BN39:CP39) -> 1550.16 | CT39: =IF(AI38>0,IF((AI38+BN39)<E$10,AI38+BN39,E$10),0) -> 0 | CU39: =IF(AJ38>0,IF((AJ38+BO39)<F$10,AJ38+BO39,F$10),0) -> 0 | CV39: =IF(AK38>0,IF((AK38+BP39)<G$10,AK38+BP39,G$10),0) -> 0 | CW39: =IF(AL38>0,IF((AL38+BQ39)<H$10,AL38+BQ39,H$10),0) -> 0 | CX39: =IF(AM38>0,IF((AM38+BR39)<I$10,AM38+BR39,I$10),0) -> 0 | CY39: =IF(AN38>0,IF((AN38+BS39)<J$10,AN38+BS39,J$10),0) -> 0 | CZ39: =IF(AO38>0,IF((AO38+BT39)<K$10,AO38+BT39,K$10),0) -> 206 | DA39: =IF(AP38>0,IF((AP38+BU39)<L$10,AP38+BU39,L$10),0) -> 82 | ... DX39: =IF(BM38>0,IF((BM38+CR39)<AI$10,BM38+CR39,AI$10),0) -> 0 | DY39: =SUM(CT39:DX39) -> 3793.97 | EA39: =IF(AI37<=0,0,IF(CT38+$C38>AI37+BN38,AI37+BN38-CT38,$C38)) -> 0 | EB39: =IF(AJ37<=0,0,IF($C38<=SUM($EA39:EA39),0,IF(CU38+$C38-SUM($EA39:EA39)>AJ37+BO38,AJ37+BO38-CU38,$C38-SUM($EA39:EA39)))) -> 0 | EC39: =IF(AK37<=0,0,IF($C38<=SUM($EA39:EB39),0,IF(CV38+$C38-SUM($EA39:EB39)>AK37+BP38,AK37+BP38-CV38,$C38-SUM($EA39:EB39)))) -> 0 | ED39: =IF(AL37<=0,0,IF($C38<=SUM($EA39:EC39),0,IF(CW38+$C38-SUM($EA39:EC39)>AL37+BQ38,AL37+BQ38-CW38,$C38-SUM($EA39:EC39)))) -> 0 | EE39: =IF(AM37<=0,0,IF($C38<=SUM($EA39:ED39),0,IF(CX38+$C38-SUM($EA39:ED39)>AM37+BR38,AM37+BR38-CX38,$C38-SUM($EA39:ED39)))) -> 0 | EF39: =IF(AN37<=0,0,IF($C38<=SUM($EA39:EE39),0,IF(CY38+$C38-SUM($EA39:EE39)>AN37+BS38,AN37+BS38-CY38,$C38-SUM($EA39:EE39)))) -> 0 | EG39: =IF(AO37<=0,0,IF($C38<=SUM($EA39:EF39),0,IF(CZ38+$C38-SUM($EA39:EF39)>AO37+BT38,AO37+BT38-CZ38,$C38-SUM($EA39:EF39)))) -> 78.03 | EH39: =IF(AP37<=0,0,IF($C38<=SUM($EA39:EG39),0,IF(DA38+$C38-SUM($EA39:EG39)>AP37+BU38,AP37+BU38-DA38,$C38-SUM($EA39:EG39)))) -> 0 | EI39: =IF(AQ37<=0,0,IF($C38<=SUM($EA39:EH39),0,IF(DB38+$C38-SUM($EA39:EH39)>AQ37+BV38,AQ37+BV38-DB38,$C38-SUM($EA39:EH39)))) -> 0 | ... FC39: =IF(BK37<=0,0,IF($C38<=SUM($EA39:FB39),0,IF(DV38+$C38-SUM($EA39:FB39)>BK37+CP38,BK37+CP38-DV38,$C38-SUM($EA39:FB39)))) -> 0
A40: =IF(SUM(AI39:BK39)<=0,"",A39+1) -> 20 | B40: 46235 | C40: =IF(A40="","",IF(Calculator!snowball,IF(($E$5-DY40)<0,0,$E$5-DY40),0)+D40) -> 118.03 | D40: 50 | E40: =CT40+EA41 -> 0 | F40: =CU40+EB41 -> 0 | G40: =CV40+EC41 -> 0 | H40: =CW40+ED41 -> 0 | I40: =CX40+EE41 -> 0 | J40: =CY40+EF41 -> 0 | K40: 175 | L40: 80 | M40: 151 | N40: =DC40+EJ41 -> 450.08 | O40: =DD40+EK41 -> 695.6 | P40: =DE40+EL41 -> 791.16 | Q40: =DF40+EM41 -> 1467.13 | R40: =DG40+EN41 -> 0 | S40: =DH40+EO41 -> 0 | T40: =DI40+EP41 -> 0 | U40: =DJ40+EQ41 -> 0 | ... AG40: =DV40+FC41 -> 0 | AH40: =SUM(AI40:BK40) -> 255925.91 | AI40: =IF(E$8=0,0,ROUND(AI39-(E40-BN40),2)) -> 0 | AJ40: =IF(F$8=0,0,ROUND(AJ39-(F40-BO40),2)) -> 0 | AK40: =IF(G$8=0,0,ROUND(AK39-(G40-BP40),2)) -> 0 | AL40: =IF(H$8=0,0,ROUND(AL39-(H40-BQ40),2)) -> 0 | AM40: =IF(I$8=0,0,ROUND(AM39-(I40-BR40),2)) -> 0 | AN40: =IF(J$8=0,0,ROUND(AN39-(J40-BS40),2)) -> 0 | AO40: =IF(K$8=0,0,ROUND(AO39-(K40-BT40),2)) -> 1274.75 | AP40: =IF(L$8=0,0,ROUND(AP39-(L40-BU40),2)) -> 3308.87 | ... AS40: =IF(O$8=0,0,ROUND(AS39-(O40-BX40),2)) -> 37751.96 | AT40: =IF(P$8=0,0,ROUND(AT39-(P40-BX40),2)) -> 41450.36 | AU40: =IF(Q$8=0,0,ROUND(AU39-(Q40-BY40),2)) -> 158684.97 | AV40: =IF(R$8=0,0,ROUND(AV39-(R40-BZ40),2)) -> 0 | AW40: =IF(S$8=0,0,ROUND(AW39-(S40-CA40),2)) -> 0 | AX40: =IF(T$8=0,0,ROUND(AX39-(T40-CB40),2)) -> 0 | AY40: =IF(U$8=0,0,ROUND(AY39-(U40-CC40),2)) -> 0 | AZ40: =IF(V$8=0,0,ROUND(AZ39-(V40-CD40),2)) -> 0 | BA40: =IF(W$8=0,0,ROUND(BA39-(W40-CE40),2)) -> 0 | ... BK40: =IF(AG$8=0,0,ROUND(BK39-(AG40-CO40),2)) -> 0 | BL40: =SUM(AI40:BK40) -> 255925.91 | BN40: =ROUND(AI39*E$9/12,2) -> 0 | BO40: =ROUND(AJ39*F$9/12,2) -> 0 | BP40: =ROUND(AK39*G$9/12,2) -> 0 | BQ40: =ROUND(AL39*H$9/12,2) -> 0 | BR40: =ROUND(AM39*I$9/12,2) -> 0 | BS40: =ROUND(AN39*J$9/12,2) -> 0 | BT40: =ROUND(AO39*K$9/12,2) -> 35.36 | BU40: =ROUND(AP39*L$9/12,2) -> 87.33 | ... CP40: =ROUND(BK39*AG$9/12,2) -> 0 | CR40: =SUM(BN40:CP40) -> 1530.68 | CT40: =IF(AI39>0,IF((AI39+BN40)<E$10,AI39+BN40,E$10),0) -> 0 | CU40: =IF(AJ39>0,IF((AJ39+BO40)<F$10,AJ39+BO40,F$10),0) -> 0 | CV40: =IF(AK39>0,IF((AK39+BP40)<G$10,AK39+BP40,G$10),0) -> 0 | CW40: =IF(AL39>0,IF((AL39+BQ40)<H$10,AL39+BQ40,H$10),0) -> 0 | CX40: =IF(AM39>0,IF((AM39+BR40)<I$10,AM39+BR40,I$10),0) -> 0 | CY40: =IF(AN39>0,IF((AN39+BS40)<J$10,AN39+BS40,J$10),0) -> 0 | CZ40: =IF(AO39>0,IF((AO39+BT40)<K$10,AO39+BT40,K$10),0) -> 206 | DA40: =IF(AP39>0,IF((AP39+BU40)<L$10,AP39+BU40,L$10),0) -> 82 | ... DX40: =IF(BM39>0,IF((BM39+CR40)<AI$10,BM39+CR40,AI$10),0) -> 0 | DY40: =SUM(CT40:DX40) -> 3793.97 | EA40: =IF(AI38<=0,0,IF(CT39+$C39>AI38+BN39,AI38+BN39-CT39,$C39)) -> 0 | EB40: =IF(AJ38<=0,0,IF($C39<=SUM($EA40:EA40),0,IF(CU39+$C39-SUM($EA40:EA40)>AJ38+BO39,AJ38+BO39-CU39,$C39-SUM($EA40:EA40)))) -> 0 | EC40: =IF(AK38<=0,0,IF($C39<=SUM($EA40:EB40),0,IF(CV39+$C39-SUM($EA40:EB40)>AK38+BP39,AK38+BP39-CV39,$C39-SUM($EA40:EB40)))) -> 0 | ED40: =IF(AL38<=0,0,IF($C39<=SUM($EA40:EC40),0,IF(CW39+$C39-SUM($EA40:EC40)>AL38+BQ39,AL38+BQ39-CW39,$C39-SUM($EA40:EC40)))) -> 0 | EE40: =IF(AM38<=0,0,IF($C39<=SUM($EA40:ED40),0,IF(CX39+$C39-SUM($EA40:ED40)>AM38+BR39,AM38+BR39-CX39,$C39-SUM($EA40:ED40)))) -> 0 | EF40: =IF(AN38<=0,0,IF($C39<=SUM($EA40:EE40),0,IF(CY39+$C39-SUM($EA40:EE40)>AN38+BS39,AN38+BS39-CY39,$C39-SUM($EA40:EE40)))) -> 0 | EG40: =IF(AO38<=0,0,IF($C39<=SUM($EA40:EF40),0,IF(CZ39+$C39-SUM($EA40:EF40)>AO38+BT39,AO38+BT39-CZ39,$C39-SUM($EA40:EF40)))) -> 118.03 | EH40: =IF(AP38<=0,0,IF($C39<=SUM($EA40:EG40),0,IF(DA39+$C39-SUM($EA40:EG40)>AP38+BU39,AP38+BU39-DA39,$C39-SUM($EA40:EG40)))) -> 0 | EI40: =IF(AQ38<=0,0,IF($C39<=SUM($EA40:EH40),0,IF(DB39+$C39-SUM($EA40:EH40)>AQ38+BV39,AQ38+BV39-DB39,$C39-SUM($EA40:EH40)))) -> 0 | ... FC40: =IF(BK38<=0,0,IF($C39<=SUM($EA40:FB40),0,IF(DV39+$C39-SUM($EA40:FB40)>BK38+CP39,BK38+CP39-DV39,$C39-SUM($EA40:FB40)))) -> 0
A41: =IF(SUM(AI40:BK40)<=0,"",A40+1) -> 21 | B41: 46266 | C41: =IF(A41="","",IF(Calculator!snowball,IF(($E$5-DY41)<0,0,$E$5-DY41),0)+D41) -> 118.03 | D41: 50 | E41: =CT41+EA42 -> 0 | F41: =CU41+EB42 -> 0 | G41: =CV41+EC42 -> 0 | H41: =CW41+ED42 -> 0 | I41: =CX41+EE42 -> 0 | J41: =CY41+EF42 -> 0 | K41: 175 | L41: =DA41+EH42 -> 82 | M41: 151 | N41: =DC41+EJ42 -> 450.08 | O41: =DD41+EK42 -> 695.6 | P41: =DE41+EL42 -> 791.16 | Q41: =DF41+EM42 -> 1467.13 | R41: =DG41+EN42 -> 0 | S41: =DH41+EO42 -> 0 | T41: =DI41+EP42 -> 0 | U41: =DJ41+EQ42 -> 0 | ... AG41: =DV41+FC42 -> 0 | AH41: =SUM(AI41:BK41) -> 253475.06 | AI41: =IF(E$8=0,0,ROUND(AI40-(E41-BN41),2)) -> 0 | AJ41: =IF(F$8=0,0,ROUND(AJ40-(F41-BO41),2)) -> 0 | AK41: =IF(G$8=0,0,ROUND(AK40-(G41-BP41),2)) -> 0 | AL41: =IF(H$8=0,0,ROUND(AL40-(H41-BQ41),2)) -> 0 | AM41: =IF(I$8=0,0,ROUND(AM40-(I41-BR41),2)) -> 0 | AN41: =IF(J$8=0,0,ROUND(AN40-(J41-BS41),2)) -> 0 | AO41: =IF(K$8=0,0,ROUND(AO40-(K41-BT41),2)) -> 1131.62 | AP41: =IF(L$8=0,0,ROUND(AP40-(L41-BU41),2)) -> 3314.39 | ... AS41: =IF(O$8=0,0,ROUND(AS40-(O41-BX41),2)) -> 37402.42 | AT41: =IF(P$8=0,0,ROUND(AT40-(P41-BX41),2)) -> 41005.26 | AU41: =IF(Q$8=0,0,ROUND(AU40-(Q41-BY41),2)) -> 157538.39 | AV41: =IF(R$8=0,0,ROUND(AV40-(R41-BZ41),2)) -> 0 | AW41: =IF(S$8=0,0,ROUND(AW40-(S41-CA41),2)) -> 0 | AX41: =IF(T$8=0,0,ROUND(AX40-(T41-CB41),2)) -> 0 | AY41: =IF(U$8=0,0,ROUND(AY40-(U41-CC41),2)) -> 0 | AZ41: =IF(V$8=0,0,ROUND(AZ40-(V41-CD41),2)) -> 0 | BA41: =IF(W$8=0,0,ROUND(BA40-(W41-CE41),2)) -> 0 | ... BK41: =IF(AG$8=0,0,ROUND(BK40-(AG41-CO41),2)) -> 0 | BL41: =SUM(AI41:BK41) -> 253475.06 | BN41: =ROUND(AI40*E$9/12,2) -> 0 | BO41: =ROUND(AJ40*F$9/12,2) -> 0 | BP41: =ROUND(AK40*G$9/12,2) -> 0 | BQ41: =ROUND(AL40*H$9/12,2) -> 0 | BR41: =ROUND(AM40*I$9/12,2) -> 0 | BS41: =ROUND(AN40*J$9/12,2) -> 0 | BT41: =ROUND(AO40*K$9/12,2) -> 31.87 | BU41: =ROUND(AP40*L$9/12,2) -> 87.52 | ... CP41: =ROUND(BK40*AG$9/12,2) -> 0 | CR41: =SUM(BN41:CP41) -> 1510.95 | CT41: =IF(AI40>0,IF((AI40+BN41)<E$10,AI40+BN41,E$10),0) -> 0 | CU41: =IF(AJ40>0,IF((AJ40+BO41)<F$10,AJ40+BO41,F$10),0) -> 0 | CV41: =IF(AK40>0,IF((AK40+BP41)<G$10,AK40+BP41,G$10),0) -> 0 | CW41: =IF(AL40>0,IF((AL40+BQ41)<H$10,AL40+BQ41,H$10),0) -> 0 | CX41: =IF(AM40>0,IF((AM40+BR41)<I$10,AM40+BR41,I$10),0) -> 0 | CY41: =IF(AN40>0,IF((AN40+BS41)<J$10,AN40+BS41,J$10),0) -> 0 | CZ41: =IF(AO40>0,IF((AO40+BT41)<K$10,AO40+BT41,K$10),0) -> 206 | DA41: =IF(AP40>0,IF((AP40+BU41)<L$10,AP40+BU41,L$10),0) -> 82 | ... DX41: =IF(BM40>0,IF((BM40+CR41)<AI$10,BM40+CR41,AI$10),0) -> 0 | DY41: =SUM(CT41:DX41) -> 3793.97 | EA41: =IF(AI39<=0,0,IF(CT40+$C40>AI39+BN40,AI39+BN40-CT40,$C40)) -> 0 | EB41: =IF(AJ39<=0,0,IF($C40<=SUM($EA41:EA41),0,IF(CU40+$C40-SUM($EA41:EA41)>AJ39+BO40,AJ39+BO40-CU40,$C40-SUM($EA41:EA41)))) -> 0 | EC41: =IF(AK39<=0,0,IF($C40<=SUM($EA41:EB41),0,IF(CV40+$C40-SUM($EA41:EB41)>AK39+BP40,AK39+BP40-CV40,$C40-SUM($EA41:EB41)))) -> 0 | ED41: =IF(AL39<=0,0,IF($C40<=SUM($EA41:EC41),0,IF(CW40+$C40-SUM($EA41:EC41)>AL39+BQ40,AL39+BQ40-CW40,$C40-SUM($EA41:EC41)))) -> 0 | EE41: =IF(AM39<=0,0,IF($C40<=SUM($EA41:ED41),0,IF(CX40+$C40-SUM($EA41:ED41)>AM39+BR40,AM39+BR40-CX40,$C40-SUM($EA41:ED41)))) -> 0 | EF41: =IF(AN39<=0,0,IF($C40<=SUM($EA41:EE41),0,IF(CY40+$C40-SUM($EA41:EE41)>AN39+BS40,AN39+BS40-CY40,$C40-SUM($EA41:EE41)))) -> 0 | EG41: =IF(AO39<=0,0,IF($C40<=SUM($EA41:EF41),0,IF(CZ40+$C40-SUM($EA41:EF41)>AO39+BT40,AO39+BT40-CZ40,$C40-SUM($EA41:EF41)))) -> 118.03 | EH41: =IF(AP39<=0,0,IF($C40<=SUM($EA41:EG41),0,IF(DA40+$C40-SUM($EA41:EG41)>AP39+BU40,AP39+BU40-DA40,$C40-SUM($EA41:EG41)))) -> 0 | EI41: =IF(AQ39<=0,0,IF($C40<=SUM($EA41:EH41),0,IF(DB40+$C40-SUM($EA41:EH41)>AQ39+BV40,AQ39+BV40-DB40,$C40-SUM($EA41:EH41)))) -> 0 | ... FC41: =IF(BK39<=0,0,IF($C40<=SUM($EA41:FB41),0,IF(DV40+$C40-SUM($EA41:FB41)>BK39+CP40,BK39+CP40-DV40,$C40-SUM($EA41:FB41)))) -> 0
A42: =IF(SUM(AI41:BK41)<=0,"",A41+1) -> 22 | B42: 46296 | C42: =IF(A42="","",IF(Calculator!snowball,IF(($E$5-DY42)<0,0,$E$5-DY42),0)+D42) -> 118.03 | D42: 50 | E42: =CT42+EA43 -> 0 | F42: =CU42+EB43 -> 0 | G42: =CV42+EC43 -> 0 | H42: =CW42+ED43 -> 0 | I42: =CX42+EE43 -> 0 | J42: =CY42+EF43 -> 0 | K42: 175 | L42: =DA42+EH43 -> 82 | M42: 151 | N42: =DC42+EJ43 -> 450.08 | O42: =DD42+EK43 -> 695.6 | P42: =DE42+EL43 -> 791.16 | Q42: =DF42+EM43 -> 1467.13 | R42: =DG42+EN43 -> 0 | S42: =DH42+EO43 -> 0 | T42: =DI42+EP43 -> 0 | U42: =DJ42+EQ43 -> 0 | ... AG42: =DV42+FC43 -> 0 | AH42: =SUM(AI42:BK42) -> 251004.56 | AI42: =IF(E$8=0,0,ROUND(AI41-(E42-BN42),2)) -> 0 | AJ42: =IF(F$8=0,0,ROUND(AJ41-(F42-BO42),2)) -> 0 | AK42: =IF(G$8=0,0,ROUND(AK41-(G42-BP42),2)) -> 0 | AL42: =IF(H$8=0,0,ROUND(AL41-(H42-BQ42),2)) -> 0 | AM42: =IF(I$8=0,0,ROUND(AM41-(I42-BR42),2)) -> 0 | AN42: =IF(J$8=0,0,ROUND(AN41-(J42-BS42),2)) -> 0 | AO42: =IF(K$8=0,0,ROUND(AO41-(K42-BT42),2)) -> 984.91 | AP42: =IF(L$8=0,0,ROUND(AP41-(L42-BU42),2)) -> 3320.06 | ... AS42: =IF(O$8=0,0,ROUND(AS41-(O42-BX42),2)) -> 37049.68 | AT42: =IF(P$8=0,0,ROUND(AT41-(P42-BX42),2)) -> 40556.96 | AU42: =IF(Q$8=0,0,ROUND(AU41-(Q42-BY42),2)) -> 156388.37 | AV42: =IF(R$8=0,0,ROUND(AV41-(R42-BZ42),2)) -> 0 | AW42: =IF(S$8=0,0,ROUND(AW41-(S42-CA42),2)) -> 0 | AX42: =IF(T$8=0,0,ROUND(AX41-(T42-CB42),2)) -> 0 | AY42: =IF(U$8=0,0,ROUND(AY41-(U42-CC42),2)) -> 0 | AZ42: =IF(V$8=0,0,ROUND(AZ41-(V42-CD42),2)) -> 0 | BA42: =IF(W$8=0,0,ROUND(BA41-(W42-CE42),2)) -> 0 | ... BK42: =IF(AG$8=0,0,ROUND(BK41-(AG42-CO42),2)) -> 0 | BL42: =SUM(AI42:BK42) -> 251004.56 | BN42: =ROUND(AI41*E$9/12,2) -> 0 | BO42: =ROUND(AJ41*F$9/12,2) -> 0 | BP42: =ROUND(AK41*G$9/12,2) -> 0 | BQ42: =ROUND(AL41*H$9/12,2) -> 0 | BR42: =ROUND(AM41*I$9/12,2) -> 0 | BS42: =ROUND(AN41*J$9/12,2) -> 0 | BT42: =ROUND(AO41*K$9/12,2) -> 28.29 | BU42: =ROUND(AP41*L$9/12,2) -> 87.67 | ... CP42: =ROUND(BK41*AG$9/12,2) -> 0 | CR42: =SUM(BN42:CP42) -> 1490.92 | CT42: =IF(AI41>0,IF((AI41+BN42)<E$10,AI41+BN42,E$10),0) -> 0 | CU42: =IF(AJ41>0,IF((AJ41+BO42)<F$10,AJ41+BO42,F$10),0) -> 0 | CV42: =IF(AK41>0,IF((AK41+BP42)<G$10,AK41+BP42,G$10),0) -> 0 | CW42: =IF(AL41>0,IF((AL41+BQ42)<H$10,AL41+BQ42,H$10),0) -> 0 | CX42: =IF(AM41>0,IF((AM41+BR42)<I$10,AM41+BR42,I$10),0) -> 0 | CY42: =IF(AN41>0,IF((AN41+BS42)<J$10,AN41+BS42,J$10),0) -> 0 | CZ42: =IF(AO41>0,IF((AO41+BT42)<K$10,AO41+BT42,K$10),0) -> 206 | DA42: =IF(AP41>0,IF((AP41+BU42)<L$10,AP41+BU42,L$10),0) -> 82 | ... DX42: =IF(BM41>0,IF((BM41+CR42)<AI$10,BM41+CR42,AI$10),0) -> 0 | DY42: =SUM(CT42:DX42) -> 3793.97 | EA42: =IF(AI40<=0,0,IF(CT41+$C41>AI40+BN41,AI40+BN41-CT41,$C41)) -> 0 | EB42: =IF(AJ40<=0,0,IF($C41<=SUM($EA42:EA42),0,IF(CU41+$C41-SUM($EA42:EA42)>AJ40+BO41,AJ40+BO41-CU41,$C41-SUM($EA42:EA42)))) -> 0 | EC42: =IF(AK40<=0,0,IF($C41<=SUM($EA42:EB42),0,IF(CV41+$C41-SUM($EA42:EB42)>AK40+BP41,AK40+BP41-CV41,$C41-SUM($EA42:EB42)))) -> 0 | ED42: =IF(AL40<=0,0,IF($C41<=SUM($EA42:EC42),0,IF(CW41+$C41-SUM($EA42:EC42)>AL40+BQ41,AL40+BQ41-CW41,$C41-SUM($EA42:EC42)))) -> 0 | EE42: =IF(AM40<=0,0,IF($C41<=SUM($EA42:ED42),0,IF(CX41+$C41-SUM($EA42:ED42)>AM40+BR41,AM40+BR41-CX41,$C41-SUM($EA42:ED42)))) -> 0 | EF42: =IF(AN40<=0,0,IF($C41<=SUM($EA42:EE42),0,IF(CY41+$C41-SUM($EA42:EE42)>AN40+BS41,AN40+BS41-CY41,$C41-SUM($EA42:EE42)))) -> 0 | EG42: =IF(AO40<=0,0,IF($C41<=SUM($EA42:EF42),0,IF(CZ41+$C41-SUM($EA42:EF42)>AO40+BT41,AO40+BT41-CZ41,$C41-SUM($EA42:EF42)))) -> 118.03 | EH42: =IF(AP40<=0,0,IF($C41<=SUM($EA42:EG42),0,IF(DA41+$C41-SUM($EA42:EG42)>AP40+BU41,AP40+BU41-DA41,$C41-SUM($EA42:EG42)))) -> 0 | EI42: =IF(AQ40<=0,0,IF($C41<=SUM($EA42:EH42),0,IF(DB41+$C41-SUM($EA42:EH42)>AQ40+BV41,AQ40+BV41-DB41,$C41-SUM($EA42:EH42)))) -> 0 | ... FC42: =IF(BK40<=0,0,IF($C41<=SUM($EA42:FB42),0,IF(DV41+$C41-SUM($EA42:FB42)>BK40+CP41,BK40+CP41-DV41,$C41-SUM($EA42:FB42)))) -> 0
A43: =IF(SUM(AI42:BK42)<=0,"",A42+1) -> 23 | B43: 46327 | C43: =IF(A43="","",IF(Calculator!snowball,IF(($E$5-DY43)<0,0,$E$5-DY43),0)+D43) -> 118.03 | D43: 50 | E43: =CT43+EA44 -> 0 | F43: =CU43+EB44 -> 0 | G43: =CV43+EC44 -> 0 | H43: =CW43+ED44 -> 0 | I43: =CX43+EE44 -> 0 | J43: =CY43+EF44 -> 0 | K43: 175 | L43: =DA43+EH44 -> 82 | M43: 151 | N43: =DC43+EJ44 -> 450.08 | O43: =DD43+EK44 -> 695.6 | P43: =DE43+EL44 -> 791.16 | Q43: =DF43+EM44 -> 1467.13 | R43: =DG43+EN44 -> 0 | S43: =DH43+EO44 -> 0 | T43: =DI43+EP44 -> 0 | U43: =DJ43+EQ44 -> 0 | ... AG43: =DV43+FC44 -> 0 | AH43: =SUM(AI43:BK43) -> 248514.1 | AI43: =IF(E$8=0,0,ROUND(AI42-(E43-BN43),2)) -> 0 | AJ43: =IF(F$8=0,0,ROUND(AJ42-(F43-BO43),2)) -> 0 | AK43: =IF(G$8=0,0,ROUND(AK42-(G43-BP43),2)) -> 0 | AL43: =IF(H$8=0,0,ROUND(AL42-(H43-BQ43),2)) -> 0 | AM43: =IF(I$8=0,0,ROUND(AM42-(I43-BR43),2)) -> 0 | AN43: =IF(J$8=0,0,ROUND(AN42-(J43-BS43),2)) -> 0 | AO43: =IF(K$8=0,0,ROUND(AO42-(K43-BT43),2)) -> 834.53 | AP43: =IF(L$8=0,0,ROUND(AP42-(L43-BU43),2)) -> 3325.88 | ... AS43: =IF(O$8=0,0,ROUND(AS42-(O43-BX43),2)) -> 36693.7 | AT43: =IF(P$8=0,0,ROUND(AT42-(P43-BX43),2)) -> 40105.42 | AU43: =IF(Q$8=0,0,ROUND(AU42-(Q43-BY43),2)) -> 155234.88 | AV43: =IF(R$8=0,0,ROUND(AV42-(R43-BZ43),2)) -> 0 | AW43: =IF(S$8=0,0,ROUND(AW42-(S43-CA43),2)) -> 0 | AX43: =IF(T$8=0,0,ROUND(AX42-(T43-CB43),2)) -> 0 | AY43: =IF(U$8=0,0,ROUND(AY42-(U43-CC43),2)) -> 0 | AZ43: =IF(V$8=0,0,ROUND(AZ42-(V43-CD43),2)) -> 0 | BA43: =IF(W$8=0,0,ROUND(BA42-(W43-CE43),2)) -> 0 | ... BK43: =IF(AG$8=0,0,ROUND(BK42-(AG43-CO43),2)) -> 0 | BL43: =SUM(AI43:BK43) -> 248514.1 | BN43: =ROUND(AI42*E$9/12,2) -> 0 | BO43: =ROUND(AJ42*F$9/12,2) -> 0 | BP43: =ROUND(AK42*G$9/12,2) -> 0 | BQ43: =ROUND(AL42*H$9/12,2) -> 0 | BR43: =ROUND(AM42*I$9/12,2) -> 0 | BS43: =ROUND(AN42*J$9/12,2) -> 0 | BT43: =ROUND(AO42*K$9/12,2) -> 24.62 | BU43: =ROUND(AP42*L$9/12,2) -> 87.82 | ... CP43: =ROUND(BK42*AG$9/12,2) -> 0 | CR43: =SUM(BN43:CP43) -> 1470.6 | CT43: =IF(AI42>0,IF((AI42+BN43)<E$10,AI42+BN43,E$10),0) -> 0 | CU43: =IF(AJ42>0,IF((AJ42+BO43)<F$10,AJ42+BO43,F$10),0) -> 0 | CV43: =IF(AK42>0,IF((AK42+BP43)<G$10,AK42+BP43,G$10),0) -> 0 | CW43: =IF(AL42>0,IF((AL42+BQ43)<H$10,AL42+BQ43,H$10),0) -> 0 | CX43: =IF(AM42>0,IF((AM42+BR43)<I$10,AM42+BR43,I$10),0) -> 0 | CY43: =IF(AN42>0,IF((AN42+BS43)<J$10,AN42+BS43,J$10),0) -> 0 | CZ43: =IF(AO42>0,IF((AO42+BT43)<K$10,AO42+BT43,K$10),0) -> 206 | DA43: =IF(AP42>0,IF((AP42+BU43)<L$10,AP42+BU43,L$10),0) -> 82 | ... DX43: =IF(BM42>0,IF((BM42+CR43)<AI$10,BM42+CR43,AI$10),0) -> 0 | DY43: =SUM(CT43:DX43) -> 3793.97 | EA43: =IF(AI41<=0,0,IF(CT42+$C42>AI41+BN42,AI41+BN42-CT42,$C42)) -> 0 | EB43: =IF(AJ41<=0,0,IF($C42<=SUM($EA43:EA43),0,IF(CU42+$C42-SUM($EA43:EA43)>AJ41+BO42,AJ41+BO42-CU42,$C42-SUM($EA43:EA43)))) -> 0 | EC43: =IF(AK41<=0,0,IF($C42<=SUM($EA43:EB43),0,IF(CV42+$C42-SUM($EA43:EB43)>AK41+BP42,AK41+BP42-CV42,$C42-SUM($EA43:EB43)))) -> 0 | ED43: =IF(AL41<=0,0,IF($C42<=SUM($EA43:EC43),0,IF(CW42+$C42-SUM($EA43:EC43)>AL41+BQ42,AL41+BQ42-CW42,$C42-SUM($EA43:EC43)))) -> 0 | EE43: =IF(AM41<=0,0,IF($C42<=SUM($EA43:ED43),0,IF(CX42+$C42-SUM($EA43:ED43)>AM41+BR42,AM41+BR42-CX42,$C42-SUM($EA43:ED43)))) -> 0 | EF43: =IF(AN41<=0,0,IF($C42<=SUM($EA43:EE43),0,IF(CY42+$C42-SUM($EA43:EE43)>AN41+BS42,AN41+BS42-CY42,$C42-SUM($EA43:EE43)))) -> 0 | EG43: =IF(AO41<=0,0,IF($C42<=SUM($EA43:EF43),0,IF(CZ42+$C42-SUM($EA43:EF43)>AO41+BT42,AO41+BT42-CZ42,$C42-SUM($EA43:EF43)))) -> 118.03 | EH43: =IF(AP41<=0,0,IF($C42<=SUM($EA43:EG43),0,IF(DA42+$C42-SUM($EA43:EG43)>AP41+BU42,AP41+BU42-DA42,$C42-SUM($EA43:EG43)))) -> 0 | EI43: =IF(AQ41<=0,0,IF($C42<=SUM($EA43:EH43),0,IF(DB42+$C42-SUM($EA43:EH43)>AQ41+BV42,AQ41+BV42-DB42,$C42-SUM($EA43:EH43)))) -> 0 | ... FC43: =IF(BK41<=0,0,IF($C42<=SUM($EA43:FB43),0,IF(DV42+$C42-SUM($EA43:FB43)>BK41+CP42,BK41+CP42-DV42,$C42-SUM($EA43:FB43)))) -> 0
A44: =IF(SUM(AI43:BK43)<=0,"",A43+1) -> 24 | B44: 46357 | C44: =IF(A44="","",IF(Calculator!snowball,IF(($E$5-DY44)<0,0,$E$5-DY44),0)+D44) -> 118.03 | D44: 50 | E44: =CT44+EA45 -> 0 | F44: =CU44+EB45 -> 0 | G44: =CV44+EC45 -> 0 | H44: =CW44+ED45 -> 0 | I44: =CX44+EE45 -> 0 | J44: =CY44+EF45 -> 0 | K44: =CZ44+EG45 -> 324.03 | L44: =DA44+EH45 -> 82 | M44: 151 | N44: =DC44+EJ45 -> 450.08 | O44: =DD44+EK45 -> 695.6 | P44: =DE44+EL45 -> 791.16 | Q44: =DF44+EM45 -> 1467.13 | R44: =DG44+EN45 -> 0 | S44: =DH44+EO45 -> 0 | T44: =DI44+EP45 -> 0 | U44: =DJ44+EQ45 -> 0 | ... AG44: =DV44+FC45 -> 0 | AH44: =SUM(AI44:BK44) -> 245854.36 | AI44: =IF(E$8=0,0,ROUND(AI43-(E44-BN44),2)) -> 0 | AJ44: =IF(F$8=0,0,ROUND(AJ43-(F44-BO44),2)) -> 0 | AK44: =IF(G$8=0,0,ROUND(AK43-(G44-BP44),2)) -> 0 | AL44: =IF(H$8=0,0,ROUND(AL43-(H44-BQ44),2)) -> 0 | AM44: =IF(I$8=0,0,ROUND(AM43-(I44-BR44),2)) -> 0 | AN44: =IF(J$8=0,0,ROUND(AN43-(J44-BS44),2)) -> 0 | AO44: =IF(K$8=0,0,ROUND(AO43-(K44-BT44),2)) -> 531.36 | AP44: =IF(L$8=0,0,ROUND(AP43-(L44-BU44),2)) -> 3331.85 | ... AS44: =IF(O$8=0,0,ROUND(AS43-(O44-BX44),2)) -> 36334.46 | AT44: =IF(P$8=0,0,ROUND(AT43-(P44-BX44),2)) -> 39650.62 | AU44: =IF(Q$8=0,0,ROUND(AU43-(Q44-BY44),2)) -> 154077.9 | AV44: =IF(R$8=0,0,ROUND(AV43-(R44-BZ44),2)) -> 0 | AW44: =IF(S$8=0,0,ROUND(AW43-(S44-CA44),2)) -> 0 | AX44: =IF(T$8=0,0,ROUND(AX43-(T44-CB44),2)) -> 0 | AY44: =IF(U$8=0,0,ROUND(AY43-(U44-CC44),2)) -> 0 | AZ44: =IF(V$8=0,0,ROUND(AZ43-(V44-CD44),2)) -> 0 | BA44: =IF(W$8=0,0,ROUND(BA43-(W44-CE44),2)) -> 0 | ... BK44: =IF(AG$8=0,0,ROUND(BK43-(AG44-CO44),2)) -> 0 | BL44: =SUM(AI44:BK44) -> 245854.36 | BN44: =ROUND(AI43*E$9/12,2) -> 0 | BO44: =ROUND(AJ43*F$9/12,2) -> 0 | BP44: =ROUND(AK43*G$9/12,2) -> 0 | BQ44: =ROUND(AL43*H$9/12,2) -> 0 | BR44: =ROUND(AM43*I$9/12,2) -> 0 | BS44: =ROUND(AN43*J$9/12,2) -> 0 | BT44: =ROUND(AO43*K$9/12,2) -> 20.86 | BU44: =ROUND(AP43*L$9/12,2) -> 87.97 | ... CP44: =ROUND(BK43*AG$9/12,2) -> 0 | CR44: =SUM(BN44:CP44) -> 1450.01 | CT44: =IF(AI43>0,IF((AI43+BN44)<E$10,AI43+BN44,E$10),0) -> 0 | CU44: =IF(AJ43>0,IF((AJ43+BO44)<F$10,AJ43+BO44,F$10),0) -> 0 | CV44: =IF(AK43>0,IF((AK43+BP44)<G$10,AK43+BP44,G$10),0) -> 0 | CW44: =IF(AL43>0,IF((AL43+BQ44)<H$10,AL43+BQ44,H$10),0) -> 0 | CX44: =IF(AM43>0,IF((AM43+BR44)<I$10,AM43+BR44,I$10),0) -> 0 | CY44: =IF(AN43>0,IF((AN43+BS44)<J$10,AN43+BS44,J$10),0) -> 0 | CZ44: =IF(AO43>0,IF((AO43+BT44)<K$10,AO43+BT44,K$10),0) -> 206 | DA44: =IF(AP43>0,IF((AP43+BU44)<L$10,AP43+BU44,L$10),0) -> 82 | ... DX44: =IF(BM43>0,IF((BM43+CR44)<AI$10,BM43+CR44,AI$10),0) -> 0 | DY44: =SUM(CT44:DX44) -> 3793.97 | EA44: =IF(AI42<=0,0,IF(CT43+$C43>AI42+BN43,AI42+BN43-CT43,$C43)) -> 0 | EB44: =IF(AJ42<=0,0,IF($C43<=SUM($EA44:EA44),0,IF(CU43+$C43-SUM($EA44:EA44)>AJ42+BO43,AJ42+BO43-CU43,$C43-SUM($EA44:EA44)))) -> 0 | EC44: =IF(AK42<=0,0,IF($C43<=SUM($EA44:EB44),0,IF(CV43+$C43-SUM($EA44:EB44)>AK42+BP43,AK42+BP43-CV43,$C43-SUM($EA44:EB44)))) -> 0 | ED44: =IF(AL42<=0,0,IF($C43<=SUM($EA44:EC44),0,IF(CW43+$C43-SUM($EA44:EC44)>AL42+BQ43,AL42+BQ43-CW43,$C43-SUM($EA44:EC44)))) -> 0 | EE44: =IF(AM42<=0,0,IF($C43<=SUM($EA44:ED44),0,IF(CX43+$C43-SUM($EA44:ED44)>AM42+BR43,AM42+BR43-CX43,$C43-SUM($EA44:ED44)))) -> 0 | EF44: =IF(AN42<=0,0,IF($C43<=SUM($EA44:EE44),0,IF(CY43+$C43-SUM($EA44:EE44)>AN42+BS43,AN42+BS43-CY43,$C43-SUM($EA44:EE44)))) -> 0 | EG44: =IF(AO42<=0,0,IF($C43<=SUM($EA44:EF44),0,IF(CZ43+$C43-SUM($EA44:EF44)>AO42+BT43,AO42+BT43-CZ43,$C43-SUM($EA44:EF44)))) -> 118.03 | EH44: =IF(AP42<=0,0,IF($C43<=SUM($EA44:EG44),0,IF(DA43+$C43-SUM($EA44:EG44)>AP42+BU43,AP42+BU43-DA43,$C43-SUM($EA44:EG44)))) -> 0 | EI44: =IF(AQ42<=0,0,IF($C43<=SUM($EA44:EH44),0,IF(DB43+$C43-SUM($EA44:EH44)>AQ42+BV43,AQ42+BV43-DB43,$C43-SUM($EA44:EH44)))) -> 0 | ... FC44: =IF(BK42<=0,0,IF($C43<=SUM($EA44:FB44),0,IF(DV43+$C43-SUM($EA44:FB44)>BK42+CP43,BK42+CP43-DV43,$C43-SUM($EA44:FB44)))) -> 0
A45: =IF(SUM(AI44:BK44)<=0,"",A44+1) -> 25 | B45: 46388 | C45: =IF(A45="","",IF(Calculator!snowball,IF(($E$5-DY45)<0,0,$E$5-DY45),0)+D45) -> 118.03 | D45: 50 | E45: =CT45+EA46 -> 0 | F45: =CU45+EB46 -> 0 | G45: =CV45+EC46 -> 0 | H45: =CW45+ED46 -> 0 | I45: =CX45+EE46 -> 0 | J45: =CY45+EF46 -> 0 | K45: =CZ45+EG46 -> 324.03 | L45: =DA45+EH46 -> 82 | M45: 151 | N45: =DC45+EJ46 -> 450.08 | O45: =DD45+EK46 -> 695.6 | P45: =DE45+EL46 -> 791.16 | Q45: =DF45+EM46 -> 1467.13 | R45: =DG45+EN46 -> 0 | S45: =DH45+EO46 -> 0 | T45: =DI45+EP46 -> 0 | U45: =DJ45+EQ46 -> 0 | ... AG45: =DV45+FC46 -> 0 | AH45: =SUM(AI45:BK45) -> 243170.38 | AI45: =IF(E$8=0,0,ROUND(AI44-(E45-BN45),2)) -> 0 | AJ45: =IF(F$8=0,0,ROUND(AJ44-(F45-BO45),2)) -> 0 | AK45: =IF(G$8=0,0,ROUND(AK44-(G45-BP45),2)) -> 0 | AL45: =IF(H$8=0,0,ROUND(AL44-(H45-BQ45),2)) -> 0 | AM45: =IF(I$8=0,0,ROUND(AM44-(I45-BR45),2)) -> 0 | AN45: =IF(J$8=0,0,ROUND(AN44-(J45-BS45),2)) -> 0 | AO45: =IF(K$8=0,0,ROUND(AO44-(K45-BT45),2)) -> 220.61 | AP45: =IF(L$8=0,0,ROUND(AP44-(L45-BU45),2)) -> 3337.98 | ... AS45: =IF(O$8=0,0,ROUND(AS44-(O45-BX45),2)) -> 35971.93 | AT45: =IF(P$8=0,0,ROUND(AT44-(P45-BX45),2)) -> 39192.53 | AU45: =IF(Q$8=0,0,ROUND(AU44-(Q45-BY45),2)) -> 152917.4 | AV45: =IF(R$8=0,0,ROUND(AV44-(R45-BZ45),2)) -> 0 | AW45: =IF(S$8=0,0,ROUND(AW44-(S45-CA45),2)) -> 0 | AX45: =IF(T$8=0,0,ROUND(AX44-(T45-CB45),2)) -> 0 | AY45: =IF(U$8=0,0,ROUND(AY44-(U45-CC45),2)) -> 0 | AZ45: =IF(V$8=0,0,ROUND(AZ44-(V45-CD45),2)) -> 0 | BA45: =IF(W$8=0,0,ROUND(BA44-(W45-CE45),2)) -> 0 | ... BK45: =IF(AG$8=0,0,ROUND(BK44-(AG45-CO45),2)) -> 0 | BL45: =SUM(AI45:BK45) -> 243170.38 | BN45: =ROUND(AI44*E$9/12,2) -> 0 | BO45: =ROUND(AJ44*F$9/12,2) -> 0 | BP45: =ROUND(AK44*G$9/12,2) -> 0 | BQ45: =ROUND(AL44*H$9/12,2) -> 0 | BR45: =ROUND(AM44*I$9/12,2) -> 0 | BS45: =ROUND(AN44*J$9/12,2) -> 0 | BT45: =ROUND(AO44*K$9/12,2) -> 13.28 | BU45: =ROUND(AP44*L$9/12,2) -> 88.13 | ... CP45: =ROUND(BK44*AG$9/12,2) -> 0 | CR45: =SUM(BN45:CP45) -> 1425.44 | CT45: =IF(AI44>0,IF((AI44+BN45)<E$10,AI44+BN45,E$10),0) -> 0 | CU45: =IF(AJ44>0,IF((AJ44+BO45)<F$10,AJ44+BO45,F$10),0) -> 0 | CV45: =IF(AK44>0,IF((AK44+BP45)<G$10,AK44+BP45,G$10),0) -> 0 | CW45: =IF(AL44>0,IF((AL44+BQ45)<H$10,AL44+BQ45,H$10),0) -> 0 | CX45: =IF(AM44>0,IF((AM44+BR45)<I$10,AM44+BR45,I$10),0) -> 0 | CY45: =IF(AN44>0,IF((AN44+BS45)<J$10,AN44+BS45,J$10),0) -> 0 | CZ45: =IF(AO44>0,IF((AO44+BT45)<K$10,AO44+BT45,K$10),0) -> 206 | DA45: =IF(AP44>0,IF((AP44+BU45)<L$10,AP44+BU45,L$10),0) -> 82 | ... DX45: =IF(BM44>0,IF((BM44+CR45)<AI$10,BM44+CR45,AI$10),0) -> 0 | DY45: =SUM(CT45:DX45) -> 3793.97 | EA45: =IF(AI43<=0,0,IF(CT44+$C44>AI43+BN44,AI43+BN44-CT44,$C44)) -> 0 | EB45: =IF(AJ43<=0,0,IF($C44<=SUM($EA45:EA45),0,IF(CU44+$C44-SUM($EA45:EA45)>AJ43+BO44,AJ43+BO44-CU44,$C44-SUM($EA45:EA45)))) -> 0 | EC45: =IF(AK43<=0,0,IF($C44<=SUM($EA45:EB45),0,IF(CV44+$C44-SUM($EA45:EB45)>AK43+BP44,AK43+BP44-CV44,$C44-SUM($EA45:EB45)))) -> 0 | ED45: =IF(AL43<=0,0,IF($C44<=SUM($EA45:EC45),0,IF(CW44+$C44-SUM($EA45:EC45)>AL43+BQ44,AL43+BQ44-CW44,$C44-SUM($EA45:EC45)))) -> 0 | EE45: =IF(AM43<=0,0,IF($C44<=SUM($EA45:ED45),0,IF(CX44+$C44-SUM($EA45:ED45)>AM43+BR44,AM43+BR44-CX44,$C44-SUM($EA45:ED45)))) -> 0 | EF45: =IF(AN43<=0,0,IF($C44<=SUM($EA45:EE45),0,IF(CY44+$C44-SUM($EA45:EE45)>AN43+BS44,AN43+BS44-CY44,$C44-SUM($EA45:EE45)))) -> 0 | EG45: =IF(AO43<=0,0,IF($C44<=SUM($EA45:EF45),0,IF(CZ44+$C44-SUM($EA45:EF45)>AO43+BT44,AO43+BT44-CZ44,$C44-SUM($EA45:EF45)))) -> 118.03 | EH45: =IF(AP43<=0,0,IF($C44<=SUM($EA45:EG45),0,IF(DA44+$C44-SUM($EA45:EG45)>AP43+BU44,AP43+BU44-DA44,$C44-SUM($EA45:EG45)))) -> 0 | EI45: =IF(AQ43<=0,0,IF($C44<=SUM($EA45:EH45),0,IF(DB44+$C44-SUM($EA45:EH45)>AQ43+BV44,AQ43+BV44-DB44,$C44-SUM($EA45:EH45)))) -> 0 | ... FC45: =IF(BK43<=0,0,IF($C44<=SUM($EA45:FB45),0,IF(DV44+$C44-SUM($EA45:FB45)>BK43+CP44,BK43+CP44-DV44,$C44-SUM($EA45:FB45)))) -> 0
A46: =IF(SUM(AI45:BK45)<=0,"",A45+1) -> 26 | B46: 46419 | C46: =IF(A46="","",IF(Calculator!snowball,IF(($E$5-DY46)<0,0,$E$5-DY46),0)+D46) -> 68.03 | D46: 0 | E46: =CT46+EA47 -> 0 | F46: =CU46+EB47 -> 0 | G46: =CV46+EC47 -> 0 | H46: =CW46+ED47 -> 0 | I46: =CX46+EE47 -> 0 | J46: =CY46+EF47 -> 0 | K46: =CZ46+EG47 -> 226.13 | L46: =DA46+EH47 -> 129.9 | M46: 151 | N46: =DC46+EJ47 -> 450.08 | O46: =DD46+EK47 -> 695.6 | P46: =DE46+EL47 -> 791.16 | Q46: =DF46+EM47 -> 1467.13 | R46: =DG46+EN47 -> 0 | S46: =DH46+EO47 -> 0 | T46: =DI46+EP47 -> 0 | U46: =DJ46+EQ47 -> 0 | ... AG46: =DV46+FC47 -> 0 | AH46: =SUM(AI46:BK46) -> 240511.73 | AI46: =IF(E$8=0,0,ROUND(AI45-(E46-BN46),2)) -> 0 | AJ46: =IF(F$8=0,0,ROUND(AJ45-(F46-BO46),2)) -> 0 | AK46: =IF(G$8=0,0,ROUND(AK45-(G46-BP46),2)) -> 0 | AL46: =IF(H$8=0,0,ROUND(AL45-(H46-BQ46),2)) -> 0 | AM46: =IF(I$8=0,0,ROUND(AM45-(I46-BR46),2)) -> 0 | AN46: =IF(J$8=0,0,ROUND(AN45-(J46-BS46),2)) -> 0 | AO46: =IF(K$8=0,0,ROUND(AO45-(K46-BT46),2)) -> 0 | AP46: =IF(L$8=0,0,ROUND(AP45-(L46-BU46),2)) -> 3296.37 | ... AS46: =IF(O$8=0,0,ROUND(AS45-(O46-BX46),2)) -> 35606.07 | AT46: =IF(P$8=0,0,ROUND(AT45-(P46-BX46),2)) -> 38731.11 | AU46: =IF(Q$8=0,0,ROUND(AU45-(Q46-BY46),2)) -> 151753.36 | AV46: =IF(R$8=0,0,ROUND(AV45-(R46-BZ46),2)) -> 0 | AW46: =IF(S$8=0,0,ROUND(AW45-(S46-CA46),2)) -> 0 | AX46: =IF(T$8=0,0,ROUND(AX45-(T46-CB46),2)) -> 0 | AY46: =IF(U$8=0,0,ROUND(AY45-(U46-CC46),2)) -> 0 | AZ46: =IF(V$8=0,0,ROUND(AZ45-(V46-CD46),2)) -> 0 | BA46: =IF(W$8=0,0,ROUND(BA45-(W46-CE46),2)) -> 0 | ... BK46: =IF(AG$8=0,0,ROUND(BK45-(AG46-CO46),2)) -> 0 | BL46: =SUM(AI46:BK46) -> 240511.73 | BN46: =ROUND(AI45*E$9/12,2) -> 0 | BO46: =ROUND(AJ45*F$9/12,2) -> 0 | BP46: =ROUND(AK45*G$9/12,2) -> 0 | BQ46: =ROUND(AL45*H$9/12,2) -> 0 | BR46: =ROUND(AM45*I$9/12,2) -> 0 | BS46: =ROUND(AN45*J$9/12,2) -> 0 | BT46: =ROUND(AO45*K$9/12,2) -> 5.52 | BU46: =ROUND(AP45*L$9/12,2) -> 88.29 | ... CP46: =ROUND(BK45*AG$9/12,2) -> 0 | CR46: =SUM(BN46:CP46) -> 1400.48 | CT46: =IF(AI45>0,IF((AI45+BN46)<E$10,AI45+BN46,E$10),0) -> 0 | CU46: =IF(AJ45>0,IF((AJ45+BO46)<F$10,AJ45+BO46,F$10),0) -> 0 | CV46: =IF(AK45>0,IF((AK45+BP46)<G$10,AK45+BP46,G$10),0) -> 0 | CW46: =IF(AL45>0,IF((AL45+BQ46)<H$10,AL45+BQ46,H$10),0) -> 0 | CX46: =IF(AM45>0,IF((AM45+BR46)<I$10,AM45+BR46,I$10),0) -> 0 | CY46: =IF(AN45>0,IF((AN45+BS46)<J$10,AN45+BS46,J$10),0) -> 0 | CZ46: =IF(AO45>0,IF((AO45+BT46)<K$10,AO45+BT46,K$10),0) -> 206 | DA46: =IF(AP45>0,IF((AP45+BU46)<L$10,AP45+BU46,L$10),0) -> 82 | ... DX46: =IF(BM45>0,IF((BM45+CR46)<AI$10,BM45+CR46,AI$10),0) -> 0 | DY46: =SUM(CT46:DX46) -> 3793.97 | EA46: =IF(AI44<=0,0,IF(CT45+$C45>AI44+BN45,AI44+BN45-CT45,$C45)) -> 0 | EB46: =IF(AJ44<=0,0,IF($C45<=SUM($EA46:EA46),0,IF(CU45+$C45-SUM($EA46:EA46)>AJ44+BO45,AJ44+BO45-CU45,$C45-SUM($EA46:EA46)))) -> 0 | EC46: =IF(AK44<=0,0,IF($C45<=SUM($EA46:EB46),0,IF(CV45+$C45-SUM($EA46:EB46)>AK44+BP45,AK44+BP45-CV45,$C45-SUM($EA46:EB46)))) -> 0 | ED46: =IF(AL44<=0,0,IF($C45<=SUM($EA46:EC46),0,IF(CW45+$C45-SUM($EA46:EC46)>AL44+BQ45,AL44+BQ45-CW45,$C45-SUM($EA46:EC46)))) -> 0 | EE46: =IF(AM44<=0,0,IF($C45<=SUM($EA46:ED46),0,IF(CX45+$C45-SUM($EA46:ED46)>AM44+BR45,AM44+BR45-CX45,$C45-SUM($EA46:ED46)))) -> 0 | EF46: =IF(AN44<=0,0,IF($C45<=SUM($EA46:EE46),0,IF(CY45+$C45-SUM($EA46:EE46)>AN44+BS45,AN44+BS45-CY45,$C45-SUM($EA46:EE46)))) -> 0 | EG46: =IF(AO44<=0,0,IF($C45<=SUM($EA46:EF46),0,IF(CZ45+$C45-SUM($EA46:EF46)>AO44+BT45,AO44+BT45-CZ45,$C45-SUM($EA46:EF46)))) -> 118.03 | EH46: =IF(AP44<=0,0,IF($C45<=SUM($EA46:EG46),0,IF(DA45+$C45-SUM($EA46:EG46)>AP44+BU45,AP44+BU45-DA45,$C45-SUM($EA46:EG46)))) -> 0 | EI46: =IF(AQ44<=0,0,IF($C45<=SUM($EA46:EH46),0,IF(DB45+$C45-SUM($EA46:EH46)>AQ44+BV45,AQ44+BV45-DB45,$C45-SUM($EA46:EH46)))) -> 0 | ... FC46: =IF(BK44<=0,0,IF($C45<=SUM($EA46:FB46),0,IF(DV45+$C45-SUM($EA46:FB46)>BK44+CP45,BK44+CP45-DV45,$C45-SUM($EA46:FB46)))) -> 0
A47: =IF(SUM(AI46:BK46)<=0,"",A46+1) -> 27 | B47: 46447 | C47: =IF(A47="","",IF(Calculator!snowball,IF(($E$5-DY47)<0,0,$E$5-DY47),0)+D47) -> 284.03 | D47: 10 | E47: =CT47+EA48 -> 0 | F47: =CU47+EB48 -> 0 | G47: =CV47+EC48 -> 0 | H47: =CW47+ED48 -> 0 | I47: =CX47+EE48 -> 0 | J47: =CY47+EF48 -> 0 | K47: =CZ47+EG48 -> 0 | L47: =DA47+EH48 -> 366.03 | M47: 151 | N47: =DC47+EJ48 -> 450.08 | O47: =DD47+EK48 -> 695.6 | P47: =DE47+EL48 -> 791.16 | Q47: =DF47+EM48 -> 1467.13 | R47: =DG47+EN48 -> 0 | S47: =DH47+EO48 -> 0 | T47: =DI47+EP48 -> 0 | U47: =DJ47+EQ48 -> 0 | ... AG47: =DV47+FC48 -> 0 | AH47: =SUM(AI47:BK47) -> 237819.21 | AI47: =IF(E$8=0,0,ROUND(AI46-(E47-BN47),2)) -> 0 | AJ47: =IF(F$8=0,0,ROUND(AJ46-(F47-BO47),2)) -> 0 | AK47: =IF(G$8=0,0,ROUND(AK46-(G47-BP47),2)) -> 0 | AL47: =IF(H$8=0,0,ROUND(AL46-(H47-BQ47),2)) -> 0 | AM47: =IF(I$8=0,0,ROUND(AM46-(I47-BR47),2)) -> 0 | AN47: =IF(J$8=0,0,ROUND(AN46-(J47-BS47),2)) -> 0 | AO47: =IF(K$8=0,0,ROUND(AO46-(K47-BT47),2)) -> 0 | AP47: =IF(L$8=0,0,ROUND(AP46-(L47-BU47),2)) -> 3017.53 | ... AS47: =IF(O$8=0,0,ROUND(AS46-(O47-BX47),2)) -> 35236.86 | AT47: =IF(P$8=0,0,ROUND(AT46-(P47-BX47),2)) -> 38266.34 | AU47: =IF(Q$8=0,0,ROUND(AU46-(Q47-BY47),2)) -> 150585.75 | AV47: =IF(R$8=0,0,ROUND(AV46-(R47-BZ47),2)) -> 0 | AW47: =IF(S$8=0,0,ROUND(AW46-(S47-CA47),2)) -> 0 | AX47: =IF(T$8=0,0,ROUND(AX46-(T47-CB47),2)) -> 0 | AY47: =IF(U$8=0,0,ROUND(AY46-(U47-CC47),2)) -> 0 | AZ47: =IF(V$8=0,0,ROUND(AZ46-(V47-CD47),2)) -> 0 | BA47: =IF(W$8=0,0,ROUND(BA46-(W47-CE47),2)) -> 0 | ... BK47: =IF(AG$8=0,0,ROUND(BK46-(AG47-CO47),2)) -> 0 | BL47: =SUM(AI47:BK47) -> 237819.21 | BN47: =ROUND(AI46*E$9/12,2) -> 0 | BO47: =ROUND(AJ46*F$9/12,2) -> 0 | BP47: =ROUND(AK46*G$9/12,2) -> 0 | BQ47: =ROUND(AL46*H$9/12,2) -> 0 | BR47: =ROUND(AM46*I$9/12,2) -> 0 | BS47: =ROUND(AN46*J$9/12,2) -> 0 | BT47: =ROUND(AO46*K$9/12,2) -> 0 | BU47: =ROUND(AP46*L$9/12,2) -> 87.19 | ... CP47: =ROUND(BK46*AG$9/12,2) -> 0 | CR47: =SUM(BN47:CP47) -> 1376.32 | CT47: =IF(AI46>0,IF((AI46+BN47)<E$10,AI46+BN47,E$10),0) -> 0 | CU47: =IF(AJ46>0,IF((AJ46+BO47)<F$10,AJ46+BO47,F$10),0) -> 0 | CV47: =IF(AK46>0,IF((AK46+BP47)<G$10,AK46+BP47,G$10),0) -> 0 | CW47: =IF(AL46>0,IF((AL46+BQ47)<H$10,AL46+BQ47,H$10),0) -> 0 | CX47: =IF(AM46>0,IF((AM46+BR47)<I$10,AM46+BR47,I$10),0) -> 0 | CY47: =IF(AN46>0,IF((AN46+BS47)<J$10,AN46+BS47,J$10),0) -> 0 | CZ47: =IF(AO46>0,IF((AO46+BT47)<K$10,AO46+BT47,K$10),0) -> 0 | DA47: =IF(AP46>0,IF((AP46+BU47)<L$10,AP46+BU47,L$10),0) -> 82 | ... DX47: =IF(BM46>0,IF((BM46+CR47)<AI$10,BM46+CR47,AI$10),0) -> 0 | DY47: =SUM(CT47:DX47) -> 3587.97 | EA47: =IF(AI45<=0,0,IF(CT46+$C46>AI45+BN46,AI45+BN46-CT46,$C46)) -> 0 | EB47: =IF(AJ45<=0,0,IF($C46<=SUM($EA47:EA47),0,IF(CU46+$C46-SUM($EA47:EA47)>AJ45+BO46,AJ45+BO46-CU46,$C46-SUM($EA47:EA47)))) -> 0 | EC47: =IF(AK45<=0,0,IF($C46<=SUM($EA47:EB47),0,IF(CV46+$C46-SUM($EA47:EB47)>AK45+BP46,AK45+BP46-CV46,$C46-SUM($EA47:EB47)))) -> 0 | ED47: =IF(AL45<=0,0,IF($C46<=SUM($EA47:EC47),0,IF(CW46+$C46-SUM($EA47:EC47)>AL45+BQ46,AL45+BQ46-CW46,$C46-SUM($EA47:EC47)))) -> 0 | EE47: =IF(AM45<=0,0,IF($C46<=SUM($EA47:ED47),0,IF(CX46+$C46-SUM($EA47:ED47)>AM45+BR46,AM45+BR46-CX46,$C46-SUM($EA47:ED47)))) -> 0 | EF47: =IF(AN45<=0,0,IF($C46<=SUM($EA47:EE47),0,IF(CY46+$C46-SUM($EA47:EE47)>AN45+BS46,AN45+BS46-CY46,$C46-SUM($EA47:EE47)))) -> 0 | EG47: =IF(AO45<=0,0,IF($C46<=SUM($EA47:EF47),0,IF(CZ46+$C46-SUM($EA47:EF47)>AO45+BT46,AO45+BT46-CZ46,$C46-SUM($EA47:EF47)))) -> 20.13 | EH47: =IF(AP45<=0,0,IF($C46<=SUM($EA47:EG47),0,IF(DA46+$C46-SUM($EA47:EG47)>AP45+BU46,AP45+BU46-DA46,$C46-SUM($EA47:EG47)))) -> 47.9 | EI47: =IF(AQ45<=0,0,IF($C46<=SUM($EA47:EH47),0,IF(DB46+$C46-SUM($EA47:EH47)>AQ45+BV46,AQ45+BV46-DB46,$C46-SUM($EA47:EH47)))) -> 0 | ... FC47: =IF(BK45<=0,0,IF($C46<=SUM($EA47:FB47),0,IF(DV46+$C46-SUM($EA47:FB47)>BK45+CP46,BK45+CP46-DV46,$C46-SUM($EA47:FB47)))) -> 0
A48: =IF(SUM(AI47:BK47)<=0,"",A47+1) -> 28 | B48: 46478 | C48: =IF(A48="","",IF(Calculator!snowball,IF(($E$5-DY48)<0,0,$E$5-DY48),0)+D48) -> 284.03 | D48: 10 | E48: =CT48+EA49 -> 0 | F48: =CU48+EB49 -> 0 | G48: =CV48+EC49 -> 0 | H48: =CW48+ED49 -> 0 | I48: =CX48+EE49 -> 0 | J48: =CY48+EF49 -> 0 | K48: =CZ48+EG49 -> 0 | L48: =DA48+EH49 -> 366.03 | M48: 151 | N48: =DC48+EJ49 -> 450.08 | O48: =DD48+EK49 -> 695.6 | P48: =DE48+EL49 -> 791.16 | Q48: =DF48+EM49 -> 1467.13 | R48: =DG48+EN49 -> 0 | S48: =DH48+EO49 -> 0 | T48: =DI48+EP49 -> 0 | U48: =DJ48+EQ49 -> 0 | ... AG48: =DV48+FC49 -> 0 | AH48: =SUM(AI48:BK48) -> 232370.52 | AI48: =IF(E$8=0,0,ROUND(AI47-(E48-BN48),2)) -> 0 | AJ48: =IF(F$8=0,0,ROUND(AJ47-(F48-BO48),2)) -> 0 | AK48: =IF(G$8=0,0,ROUND(AK47-(G48-BP48),2)) -> 0 | AL48: =IF(H$8=0,0,ROUND(AL47-(H48-BQ48),2)) -> 0 | AM48: =IF(I$8=0,0,ROUND(AM47-(I48-BR48),2)) -> 0 | AN48: =IF(J$8=0,0,ROUND(AN47-(J48-BS48),2)) -> 0 | AO48: =IF(K$8=0,0,ROUND(AO47-(K48-BT48),2)) -> 0 | AP48: 0 | AQ48: =IF(M$8=0,0,ROUND(AQ47-(M48-BV48),2)) -> 2068.38 | AR48: =IF(N$8=0,0,ROUND(AR47-(N48-BW48),2)) -> 8225.15 | AS48: =IF(O$8=0,0,ROUND(AS47-(O48-BX48),2)) -> 34864.26 | AT48: =IF(P$8=0,0,ROUND(AT47-(P48-BX48),2)) -> 37798.18 | AU48: =IF(Q$8=0,0,ROUND(AU47-(Q48-BY48),2)) -> 149414.55 | AV48: =IF(R$8=0,0,ROUND(AV47-(R48-BZ48),2)) -> 0 | AW48: =IF(S$8=0,0,ROUND(AW47-(S48-CA48),2)) -> 0 | AX48: =IF(T$8=0,0,ROUND(AX47-(T48-CB48),2)) -> 0 | AY48: =IF(U$8=0,0,ROUND(AY47-(U48-CC48),2)) -> 0 | AZ48: =IF(V$8=0,0,ROUND(AZ47-(V48-CD48),2)) -> 0 | BA48: =IF(W$8=0,0,ROUND(BA47-(W48-CE48),2)) -> 0 | ... BK48: =IF(AG$8=0,0,ROUND(BK47-(AG48-CO48),2)) -> 0 | BL48: =SUM(AI48:BK48) -> 232370.52 | BN48: =ROUND(AI47*E$9/12,2) -> 0 | BO48: =ROUND(AJ47*F$9/12,2) -> 0 | BP48: =ROUND(AK47*G$9/12,2) -> 0 | BQ48: =ROUND(AL47*H$9/12,2) -> 0 | BR48: =ROUND(AM47*I$9/12,2) -> 0 | BS48: =ROUND(AN47*J$9/12,2) -> 0 | BT48: =ROUND(AO47*K$9/12,2) -> 0 | BU48: =ROUND(AP47*L$9/12,2) -> 79.81 | ... CP48: =ROUND(BK47*AG$9/12,2) -> 0 | CR48: =SUM(BN48:CP48) -> 1351.2 | CT48: =IF(AI47>0,IF((AI47+BN48)<E$10,AI47+BN48,E$10),0) -> 0 | CU48: =IF(AJ47>0,IF((AJ47+BO48)<F$10,AJ47+BO48,F$10),0) -> 0 | CV48: =IF(AK47>0,IF((AK47+BP48)<G$10,AK47+BP48,G$10),0) -> 0 | CW48: =IF(AL47>0,IF((AL47+BQ48)<H$10,AL47+BQ48,H$10),0) -> 0 | CX48: =IF(AM47>0,IF((AM47+BR48)<I$10,AM47+BR48,I$10),0) -> 0 | CY48: =IF(AN47>0,IF((AN47+BS48)<J$10,AN47+BS48,J$10),0) -> 0 | CZ48: =IF(AO47>0,IF((AO47+BT48)<K$10,AO47+BT48,K$10),0) -> 0 | DA48: =IF(AP47>0,IF((AP47+BU48)<L$10,AP47+BU48,L$10),0) -> 82 | ... DX48: =IF(BM47>0,IF((BM47+CR48)<AI$10,BM47+CR48,AI$10),0) -> 0 | DY48: =SUM(CT48:DX48) -> 3587.97 | EA48: =IF(AI46<=0,0,IF(CT47+$C47>AI46+BN47,AI46+BN47-CT47,$C47)) -> 0 | EB48: =IF(AJ46<=0,0,IF($C47<=SUM($EA48:EA48),0,IF(CU47+$C47-SUM($EA48:EA48)>AJ46+BO47,AJ46+BO47-CU47,$C47-SUM($EA48:EA48)))) -> 0 | EC48: =IF(AK46<=0,0,IF($C47<=SUM($EA48:EB48),0,IF(CV47+$C47-SUM($EA48:EB48)>AK46+BP47,AK46+BP47-CV47,$C47-SUM($EA48:EB48)))) -> 0 | ED48: =IF(AL46<=0,0,IF($C47<=SUM($EA48:EC48),0,IF(CW47+$C47-SUM($EA48:EC48)>AL46+BQ47,AL46+BQ47-CW47,$C47-SUM($EA48:EC48)))) -> 0 | EE48: =IF(AM46<=0,0,IF($C47<=SUM($EA48:ED48),0,IF(CX47+$C47-SUM($EA48:ED48)>AM46+BR47,AM46+BR47-CX47,$C47-SUM($EA48:ED48)))) -> 0 | EF48: =IF(AN46<=0,0,IF($C47<=SUM($EA48:EE48),0,IF(CY47+$C47-SUM($EA48:EE48)>AN46+BS47,AN46+BS47-CY47,$C47-SUM($EA48:EE48)))) -> 0 | EG48: =IF(AO46<=0,0,IF($C47<=SUM($EA48:EF48),0,IF(CZ47+$C47-SUM($EA48:EF48)>AO46+BT47,AO46+BT47-CZ47,$C47-SUM($EA48:EF48)))) -> 0 | EH48: =IF(AP46<=0,0,IF($C47<=SUM($EA48:EG48),0,IF(DA47+$C47-SUM($EA48:EG48)>AP46+BU47,AP46+BU47-DA47,$C47-SUM($EA48:EG48)))) -> 284.03 | EI48: =IF(AQ46<=0,0,IF($C47<=SUM($EA48:EH48),0,IF(DB47+$C47-SUM($EA48:EH48)>AQ46+BV47,AQ46+BV47-DB47,$C47-SUM($EA48:EH48)))) -> 0 | ... FC48: =IF(BK46<=0,0,IF($C47<=SUM($EA48:FB48),0,IF(DV47+$C47-SUM($EA48:FB48)>BK46+CP47,BK46+CP47-DV47,$C47-SUM($EA48:FB48)))) -> 0
A49: =IF(SUM(AI48:BK48)<=0,"",A48+1) -> 29 | B49: 46508 | C49: =IF(A49="","",IF(Calculator!snowball,IF(($E$5-DY49)<0,0,$E$5-DY49),0)+D49) -> 366.03 | D49: 10 | E49: =CT49+EA50 -> 0 | F49: =CU49+EB50 -> 0 | G49: =CV49+EC50 -> 0 | H49: =CW49+ED50 -> 0 | I49: =CX49+EE50 -> 0 | J49: =CY49+EF50 -> 0 | K49: =CZ49+EG50 -> 0 | L49: =DA49+EH50 -> 0 | ... AG49: =DV49+FC50 -> 0 | AH49: =SUM(AI49:BK49) -> 229604.65 | AI49: =IF(E$8=0,0,ROUND(AI48-(E49-BN49),2)) -> 0 | AJ49: =IF(F$8=0,0,ROUND(AJ48-(F49-BO49),2)) -> 0 | AK49: =IF(G$8=0,0,ROUND(AK48-(G49-BP49),2)) -> 0 | AL49: =IF(H$8=0,0,ROUND(AL48-(H49-BQ49),2)) -> 0 | AM49: =IF(I$8=0,0,ROUND(AM48-(I49-BR49),2)) -> 0 | AN49: =IF(J$8=0,0,ROUND(AN48-(J49-BS49),2)) -> 0 | AO49: =IF(K$8=0,0,ROUND(AO48-(K49-BT49),2)) -> 0 | AP49: 0 | AQ49: =IF(M$8=0,0,ROUND(AQ48-(M49-BV49),2)) -> 1651.61 | AR49: =IF(N$8=0,0,ROUND(AR48-(N49-BW49),2)) -> 7898.45 | AS49: =IF(O$8=0,0,ROUND(AS48-(O49-BX49),2)) -> 34488.25 | AT49: =IF(P$8=0,0,ROUND(AT48-(P49-BX49),2)) -> 37326.61 | AU49: =IF(Q$8=0,0,ROUND(AU48-(Q49-BY49),2)) -> 148239.73 | AV49: =IF(R$8=0,0,ROUND(AV48-(R49-BZ49),2)) -> 0 | AW49: =IF(S$8=0,0,ROUND(AW48-(S49-CA49),2)) -> 0 | AX49: =IF(T$8=0,0,ROUND(AX48-(T49-CB49),2)) -> 0 | AY49: =IF(U$8=0,0,ROUND(AY48-(U49-CC49),2)) -> 0 | AZ49: =IF(V$8=0,0,ROUND(AZ48-(V49-CD49),2)) -> 0 | BA49: =IF(W$8=0,0,ROUND(BA48-(W49-CE49),2)) -> 0 | ... BK49: =IF(AG$8=0,0,ROUND(BK48-(AG49-CO49),2)) -> 0 | BL49: =SUM(AI49:BK49) -> 229604.65 | BN49: =ROUND(AI48*E$9/12,2) -> 0 | BO49: =ROUND(AJ48*F$9/12,2) -> 0 | BP49: =ROUND(AK48*G$9/12,2) -> 0 | BQ49: =ROUND(AL48*H$9/12,2) -> 0 | BR49: =ROUND(AM48*I$9/12,2) -> 0 | BS49: =ROUND(AN48*J$9/12,2) -> 0 | BT49: =ROUND(AO48*K$9/12,2) -> 0 | BU49: =ROUND(AP48*L$9/12,2) -> 0 | ... CP49: =ROUND(BK48*AG$9/12,2) -> 0 | CR49: =SUM(BN49:CP49) -> 1253.46 | CT49: =IF(AI48>0,IF((AI48+BN49)<E$10,AI48+BN49,E$10),0) -> 0 | CU49: =IF(AJ48>0,IF((AJ48+BO49)<F$10,AJ48+BO49,F$10),0) -> 0 | CV49: =IF(AK48>0,IF((AK48+BP49)<G$10,AK48+BP49,G$10),0) -> 0 | CW49: =IF(AL48>0,IF((AL48+BQ49)<H$10,AL48+BQ49,H$10),0) -> 0 | CX49: =IF(AM48>0,IF((AM48+BR49)<I$10,AM48+BR49,I$10),0) -> 0 | CY49: =IF(AN48>0,IF((AN48+BS49)<J$10,AN48+BS49,J$10),0) -> 0 | CZ49: =IF(AO48>0,IF((AO48+BT49)<K$10,AO48+BT49,K$10),0) -> 0 | DA49: =IF(AP48>0,IF((AP48+BU49)<L$10,AP48+BU49,L$10),0) -> 0 | ... DX49: =IF(BM48>0,IF((BM48+CR49)<AI$10,BM48+CR49,AI$10),0) -> 0 | DY49: =SUM(CT49:DX49) -> 3505.97 | EA49: =IF(AI47<=0,0,IF(CT48+$C48>AI47+BN48,AI47+BN48-CT48,$C48)) -> 0 | EB49: =IF(AJ47<=0,0,IF($C48<=SUM($EA49:EA49),0,IF(CU48+$C48-SUM($EA49:EA49)>AJ47+BO48,AJ47+BO48-CU48,$C48-SUM($EA49:EA49)))) -> 0 | EC49: =IF(AK47<=0,0,IF($C48<=SUM($EA49:EB49),0,IF(CV48+$C48-SUM($EA49:EB49)>AK47+BP48,AK47+BP48-CV48,$C48-SUM($EA49:EB49)))) -> 0 | ED49: =IF(AL47<=0,0,IF($C48<=SUM($EA49:EC49),0,IF(CW48+$C48-SUM($EA49:EC49)>AL47+BQ48,AL47+BQ48-CW48,$C48-SUM($EA49:EC49)))) -> 0 | EE49: =IF(AM47<=0,0,IF($C48<=SUM($EA49:ED49),0,IF(CX48+$C48-SUM($EA49:ED49)>AM47+BR48,AM47+BR48-CX48,$C48-SUM($EA49:ED49)))) -> 0 | EF49: =IF(AN47<=0,0,IF($C48<=SUM($EA49:EE49),0,IF(CY48+$C48-SUM($EA49:EE49)>AN47+BS48,AN47+BS48-CY48,$C48-SUM($EA49:EE49)))) -> 0 | EG49: =IF(AO47<=0,0,IF($C48<=SUM($EA49:EF49),0,IF(CZ48+$C48-SUM($EA49:EF49)>AO47+BT48,AO47+BT48-CZ48,$C48-SUM($EA49:EF49)))) -> 0 | EH49: =IF(AP47<=0,0,IF($C48<=SUM($EA49:EG49),0,IF(DA48+$C48-SUM($EA49:EG49)>AP47+BU48,AP47+BU48-DA48,$C48-SUM($EA49:EG49)))) -> 284.03 | EI49: =IF(AQ47<=0,0,IF($C48<=SUM($EA49:EH49),0,IF(DB48+$C48-SUM($EA49:EH49)>AQ47+BV48,AQ47+BV48-DB48,$C48-SUM($EA49:EH49)))) -> 0 | ... FC49: =IF(BK47<=0,0,IF($C48<=SUM($EA49:FB49),0,IF(DV48+$C48-SUM($EA49:FB49)>BK47+CP48,BK47+CP48-DV48,$C48-SUM($EA49:FB49)))) -> 0
A50: =IF(SUM(AI49:BK49)<=0,"",A49+1) -> 30 | B50: 46539 | C50: =IF(A50="","",IF(Calculator!snowball,IF(($E$5-DY50)<0,0,$E$5-DY50),0)+D50) -> 366.03 | D50: 10 | E50: =CT50+EA51 -> 0 | F50: =CU50+EB51 -> 0 | G50: =CV50+EC51 -> 0 | H50: =CW50+ED51 -> 0 | I50: =CX50+EE51 -> 0 | J50: =CY50+EF51 -> 0 | K50: =CZ50+EG51 -> 0 | L50: =DA50+EH51 -> 0 | ... AG50: =DV50+FC51 -> 0 | AH50: =SUM(AI50:BK50) -> 226813 | AI50: =IF(E$8=0,0,ROUND(AI49-(E50-BN50),2)) -> 0 | AJ50: =IF(F$8=0,0,ROUND(AJ49-(F50-BO50),2)) -> 0 | AK50: =IF(G$8=0,0,ROUND(AK49-(G50-BP50),2)) -> 0 | AL50: =IF(H$8=0,0,ROUND(AL49-(H50-BQ50),2)) -> 0 | AM50: =IF(I$8=0,0,ROUND(AM49-(I50-BR50),2)) -> 0 | AN50: =IF(J$8=0,0,ROUND(AN49-(J50-BS50),2)) -> 0 | AO50: =IF(K$8=0,0,ROUND(AO49-(K50-BT50),2)) -> 0 | AP50: 0 | AQ50: =IF(M$8=0,0,ROUND(AQ49-(M50-BV50),2)) -> 1224.51 | AR50: =IF(N$8=0,0,ROUND(AR49-(N50-BW50),2)) -> 7566.85 | AS50: =IF(O$8=0,0,ROUND(AS49-(O50-BX50),2)) -> 34108.79 | AT50: =IF(P$8=0,0,ROUND(AT49-(P50-BX50),2)) -> 36851.59 | AU50: =IF(Q$8=0,0,ROUND(AU49-(Q50-BY50),2)) -> 147061.26 | AV50: =IF(R$8=0,0,ROUND(AV49-(R50-BZ50),2)) -> 0 | AW50: =IF(S$8=0,0,ROUND(AW49-(S50-CA50),2)) -> 0 | AX50: =IF(T$8=0,0,ROUND(AX49-(T50-CB50),2)) -> 0 | AY50: =IF(U$8=0,0,ROUND(AY49-(U50-CC50),2)) -> 0 | AZ50: =IF(V$8=0,0,ROUND(AZ49-(V50-CD50),2)) -> 0 | BA50: =IF(W$8=0,0,ROUND(BA49-(W50-CE50),2)) -> 0 | ... BK50: =IF(AG$8=0,0,ROUND(BK49-(AG50-CO50),2)) -> 0 | BL50: =SUM(AI50:BK50) -> 226813 | BN50: =ROUND(AI49*E$9/12,2) -> 0 | BO50: =ROUND(AJ49*F$9/12,2) -> 0 | BP50: =ROUND(AK49*G$9/12,2) -> 0 | BQ50: =ROUND(AL49*H$9/12,2) -> 0 | BR50: =ROUND(AM49*I$9/12,2) -> 0 | BS50: =ROUND(AN49*J$9/12,2) -> 0 | BT50: =ROUND(AO49*K$9/12,2) -> 0 | BU50: =ROUND(AP49*L$9/12,2) -> 0 | ... CP50: =ROUND(BK49*AG$9/12,2) -> 0 | CR50: =SUM(BN50:CP50) -> 1227.46 | CT50: =IF(AI49>0,IF((AI49+BN50)<E$10,AI49+BN50,E$10),0) -> 0 | CU50: =IF(AJ49>0,IF((AJ49+BO50)<F$10,AJ49+BO50,F$10),0) -> 0 | CV50: =IF(AK49>0,IF((AK49+BP50)<G$10,AK49+BP50,G$10),0) -> 0 | CW50: =IF(AL49>0,IF((AL49+BQ50)<H$10,AL49+BQ50,H$10),0) -> 0 | CX50: =IF(AM49>0,IF((AM49+BR50)<I$10,AM49+BR50,I$10),0) -> 0 | CY50: =IF(AN49>0,IF((AN49+BS50)<J$10,AN49+BS50,J$10),0) -> 0 | CZ50: =IF(AO49>0,IF((AO49+BT50)<K$10,AO49+BT50,K$10),0) -> 0 | DA50: =IF(AP49>0,IF((AP49+BU50)<L$10,AP49+BU50,L$10),0) -> 0 | ... DX50: =IF(BM49>0,IF((BM49+CR50)<AI$10,BM49+CR50,AI$10),0) -> 0 | DY50: =SUM(CT50:DX50) -> 3505.97 | EA50: =IF(AI48<=0,0,IF(CT49+$C49>AI48+BN49,AI48+BN49-CT49,$C49)) -> 0 | EB50: =IF(AJ48<=0,0,IF($C49<=SUM($EA50:EA50),0,IF(CU49+$C49-SUM($EA50:EA50)>AJ48+BO49,AJ48+BO49-CU49,$C49-SUM($EA50:EA50)))) -> 0 | EC50: =IF(AK48<=0,0,IF($C49<=SUM($EA50:EB50),0,IF(CV49+$C49-SUM($EA50:EB50)>AK48+BP49,AK48+BP49-CV49,$C49-SUM($EA50:EB50)))) -> 0 | ED50: =IF(AL48<=0,0,IF($C49<=SUM($EA50:EC50),0,IF(CW49+$C49-SUM($EA50:EC50)>AL48+BQ49,AL48+BQ49-CW49,$C49-SUM($EA50:EC50)))) -> 0 | EE50: =IF(AM48<=0,0,IF($C49<=SUM($EA50:ED50),0,IF(CX49+$C49-SUM($EA50:ED50)>AM48+BR49,AM48+BR49-CX49,$C49-SUM($EA50:ED50)))) -> 0 | EF50: =IF(AN48<=0,0,IF($C49<=SUM($EA50:EE50),0,IF(CY49+$C49-SUM($EA50:EE50)>AN48+BS49,AN48+BS49-CY49,$C49-SUM($EA50:EE50)))) -> 0 | EG50: =IF(AO48<=0,0,IF($C49<=SUM($EA50:EF50),0,IF(CZ49+$C49-SUM($EA50:EF50)>AO48+BT49,AO48+BT49-CZ49,$C49-SUM($EA50:EF50)))) -> 0 | EH50: =IF(AP48<=0,0,IF($C49<=SUM($EA50:EG50),0,IF(DA49+$C49-SUM($EA50:EG50)>AP48+BU49,AP48+BU49-DA49,$C49-SUM($EA50:EG50)))) -> 0 | EI50: =IF(AQ48<=0,0,IF($C49<=SUM($EA50:EH50),0,IF(DB49+$C49-SUM($EA50:EH50)>AQ48+BV49,AQ48+BV49-DB49,$C49-SUM($EA50:EH50)))) -> 366.03 | ... FC50: =IF(BK48<=0,0,IF($C49<=SUM($EA50:FB50),0,IF(DV49+$C49-SUM($EA50:FB50)>BK48+CP49,BK48+CP49-DV49,$C49-SUM($EA50:FB50)))) -> 0
A51: =IF(SUM(AI50:BK50)<=0,"",A50+1) -> 31 | B51: 46569 | C51: =IF(A51="","",IF(Calculator!snowball,IF(($E$5-DY51)<0,0,$E$5-DY51),0)+D51) -> 366.03 | D51: 10 | E51: =CT51+EA52 -> 0 | F51: =CU51+EB52 -> 0 | G51: =CV51+EC52 -> 0 | H51: =CW51+ED52 -> 0 | I51: =CX51+EE52 -> 0 | J51: =CY51+EF52 -> 0 | K51: =CZ51+EG52 -> 0 | L51: =DA51+EH52 -> 0 | ... AG51: =DV51+FC52 -> 0 | AH51: =SUM(AI51:BK51) -> 223995.16 | AI51: =IF(E$8=0,0,ROUND(AI50-(E51-BN51),2)) -> 0 | AJ51: =IF(F$8=0,0,ROUND(AJ50-(F51-BO51),2)) -> 0 | AK51: =IF(G$8=0,0,ROUND(AK50-(G51-BP51),2)) -> 0 | AL51: =IF(H$8=0,0,ROUND(AL50-(H51-BQ51),2)) -> 0 | AM51: =IF(I$8=0,0,ROUND(AM50-(I51-BR51),2)) -> 0 | AN51: =IF(J$8=0,0,ROUND(AN50-(J51-BS51),2)) -> 0 | AO51: =IF(K$8=0,0,ROUND(AO50-(K51-BT51),2)) -> 0 | AP51: 0 | AQ51: =IF(M$8=0,0,ROUND(AQ50-(M51-BV51),2)) -> 786.83 | AR51: =IF(N$8=0,0,ROUND(AR50-(N51-BW51),2)) -> 7230.27 | AS51: =IF(O$8=0,0,ROUND(AS50-(O51-BX51),2)) -> 33725.85 | AT51: =IF(P$8=0,0,ROUND(AT50-(P51-BX51),2)) -> 36373.09 | AU51: =IF(Q$8=0,0,ROUND(AU50-(Q51-BY51),2)) -> 145879.12 | AV51: =IF(R$8=0,0,ROUND(AV50-(R51-BZ51),2)) -> 0 | AW51: =IF(S$8=0,0,ROUND(AW50-(S51-CA51),2)) -> 0 | AX51: =IF(T$8=0,0,ROUND(AX50-(T51-CB51),2)) -> 0 | AY51: =IF(U$8=0,0,ROUND(AY50-(U51-CC51),2)) -> 0 | AZ51: =IF(V$8=0,0,ROUND(AZ50-(V51-CD51),2)) -> 0 | BA51: =IF(W$8=0,0,ROUND(BA50-(W51-CE51),2)) -> 0 | ... BK51: =IF(AG$8=0,0,ROUND(BK50-(AG51-CO51),2)) -> 0 | BL51: =SUM(AI51:BK51) -> 223995.16 | BN51: =ROUND(AI50*E$9/12,2) -> 0 | BO51: =ROUND(AJ50*F$9/12,2) -> 0 | BP51: =ROUND(AK50*G$9/12,2) -> 0 | BQ51: =ROUND(AL50*H$9/12,2) -> 0 | BR51: =ROUND(AM50*I$9/12,2) -> 0 | BS51: =ROUND(AN50*J$9/12,2) -> 0 | BT51: =ROUND(AO50*K$9/12,2) -> 0 | BU51: =ROUND(AP50*L$9/12,2) -> 0 | ... CP51: =ROUND(BK50*AG$9/12,2) -> 0 | CR51: =SUM(BN51:CP51) -> 1201.07 | CT51: =IF(AI50>0,IF((AI50+BN51)<E$10,AI50+BN51,E$10),0) -> 0 | CU51: =IF(AJ50>0,IF((AJ50+BO51)<F$10,AJ50+BO51,F$10),0) -> 0 | CV51: =IF(AK50>0,IF((AK50+BP51)<G$10,AK50+BP51,G$10),0) -> 0 | CW51: =IF(AL50>0,IF((AL50+BQ51)<H$10,AL50+BQ51,H$10),0) -> 0 | CX51: =IF(AM50>0,IF((AM50+BR51)<I$10,AM50+BR51,I$10),0) -> 0 | CY51: =IF(AN50>0,IF((AN50+BS51)<J$10,AN50+BS51,J$10),0) -> 0 | CZ51: =IF(AO50>0,IF((AO50+BT51)<K$10,AO50+BT51,K$10),0) -> 0 | DA51: =IF(AP50>0,IF((AP50+BU51)<L$10,AP50+BU51,L$10),0) -> 0 | ... DX51: =IF(BM50>0,IF((BM50+CR51)<AI$10,BM50+CR51,AI$10),0) -> 0 | DY51: =SUM(CT51:DX51) -> 3505.97 | EA51: =IF(AI49<=0,0,IF(CT50+$C50>AI49+BN50,AI49+BN50-CT50,$C50)) -> 0 | EB51: =IF(AJ49<=0,0,IF($C50<=SUM($EA51:EA51),0,IF(CU50+$C50-SUM($EA51:EA51)>AJ49+BO50,AJ49+BO50-CU50,$C50-SUM($EA51:EA51)))) -> 0 | EC51: =IF(AK49<=0,0,IF($C50<=SUM($EA51:EB51),0,IF(CV50+$C50-SUM($EA51:EB51)>AK49+BP50,AK49+BP50-CV50,$C50-SUM($EA51:EB51)))) -> 0 | ED51: =IF(AL49<=0,0,IF($C50<=SUM($EA51:EC51),0,IF(CW50+$C50-SUM($EA51:EC51)>AL49+BQ50,AL49+BQ50-CW50,$C50-SUM($EA51:EC51)))) -> 0 | EE51: =IF(AM49<=0,0,IF($C50<=SUM($EA51:ED51),0,IF(CX50+$C50-SUM($EA51:ED51)>AM49+BR50,AM49+BR50-CX50,$C50-SUM($EA51:ED51)))) -> 0 | EF51: =IF(AN49<=0,0,IF($C50<=SUM($EA51:EE51),0,IF(CY50+$C50-SUM($EA51:EE51)>AN49+BS50,AN49+BS50-CY50,$C50-SUM($EA51:EE51)))) -> 0 | EG51: =IF(AO49<=0,0,IF($C50<=SUM($EA51:EF51),0,IF(CZ50+$C50-SUM($EA51:EF51)>AO49+BT50,AO49+BT50-CZ50,$C50-SUM($EA51:EF51)))) -> 0 | EH51: =IF(AP49<=0,0,IF($C50<=SUM($EA51:EG51),0,IF(DA50+$C50-SUM($EA51:EG51)>AP49+BU50,AP49+BU50-DA50,$C50-SUM($EA51:EG51)))) -> 0 | EI51: =IF(AQ49<=0,0,IF($C50<=SUM($EA51:EH51),0,IF(DB50+$C50-SUM($EA51:EH51)>AQ49+BV50,AQ49+BV50-DB50,$C50-SUM($EA51:EH51)))) -> 366.03 | ... FC51: =IF(BK49<=0,0,IF($C50<=SUM($EA51:FB51),0,IF(DV50+$C50-SUM($EA51:FB51)>BK49+CP50,BK49+CP50-DV50,$C50-SUM($EA51:FB51)))) -> 0
A52: =IF(SUM(AI51:BK51)<=0,"",A51+1) -> 32 | B52: 46600 | C52: =IF(A52="","",IF(Calculator!snowball,IF(($E$5-DY52)<0,0,$E$5-DY52),0)+D52) -> 366.03 | D52: 10 | E52: =CT52+EA53 -> 0 | F52: =CU52+EB53 -> 0 | G52: =CV52+EC53 -> 0 | H52: =CW52+ED53 -> 0 | I52: =CX52+EE53 -> 0 | J52: =CY52+EF53 -> 0 | K52: =CZ52+EG53 -> 0 | L52: =DA52+EH53 -> 0 | ... AG52: =DV52+FC53 -> 0 | AH52: =SUM(AI52:BK52) -> 221150.7 | AI52: =IF(E$8=0,0,ROUND(AI51-(E52-BN52),2)) -> 0 | AJ52: =IF(F$8=0,0,ROUND(AJ51-(F52-BO52),2)) -> 0 | AK52: =IF(G$8=0,0,ROUND(AK51-(G52-BP52),2)) -> 0 | AL52: =IF(H$8=0,0,ROUND(AL51-(H52-BQ52),2)) -> 0 | AM52: =IF(I$8=0,0,ROUND(AM51-(I52-BR52),2)) -> 0 | AN52: =IF(J$8=0,0,ROUND(AN51-(J52-BS52),2)) -> 0 | AO52: =IF(K$8=0,0,ROUND(AO51-(K52-BT52),2)) -> 0 | AP52: 0 | AQ52: =IF(M$8=0,0,ROUND(AQ51-(M52-BV52),2)) -> 338.3 | AR52: =IF(N$8=0,0,ROUND(AR51-(N52-BW52),2)) -> 6888.64 | AS52: =IF(O$8=0,0,ROUND(AS51-(O52-BX52),2)) -> 33339.4 | AT52: =IF(P$8=0,0,ROUND(AT51-(P52-BX52),2)) -> 35891.08 | AU52: =IF(Q$8=0,0,ROUND(AU51-(Q52-BY52),2)) -> 144693.28 | AV52: =IF(R$8=0,0,ROUND(AV51-(R52-BZ52),2)) -> 0 | AW52: =IF(S$8=0,0,ROUND(AW51-(S52-CA52),2)) -> 0 | AX52: =IF(T$8=0,0,ROUND(AX51-(T52-CB52),2)) -> 0 | AY52: =IF(U$8=0,0,ROUND(AY51-(U52-CC52),2)) -> 0 | AZ52: =IF(V$8=0,0,ROUND(AZ51-(V52-CD52),2)) -> 0 | BA52: =IF(W$8=0,0,ROUND(BA51-(W52-CE52),2)) -> 0 | ... BK52: =IF(AG$8=0,0,ROUND(BK51-(AG52-CO52),2)) -> 0 | BL52: =SUM(AI52:BK52) -> 221150.7 | BN52: =ROUND(AI51*E$9/12,2) -> 0 | BO52: =ROUND(AJ51*F$9/12,2) -> 0 | BP52: =ROUND(AK51*G$9/12,2) -> 0 | BQ52: =ROUND(AL51*H$9/12,2) -> 0 | BR52: =ROUND(AM51*I$9/12,2) -> 0 | BS52: =ROUND(AN51*J$9/12,2) -> 0 | BT52: =ROUND(AO51*K$9/12,2) -> 0 | BU52: =ROUND(AP51*L$9/12,2) -> 0 | ... CP52: =ROUND(BK51*AG$9/12,2) -> 0 | CR52: =SUM(BN52:CP52) -> 1174.26 | CT52: =IF(AI51>0,IF((AI51+BN52)<E$10,AI51+BN52,E$10),0) -> 0 | CU52: =IF(AJ51>0,IF((AJ51+BO52)<F$10,AJ51+BO52,F$10),0) -> 0 | CV52: =IF(AK51>0,IF((AK51+BP52)<G$10,AK51+BP52,G$10),0) -> 0 | CW52: =IF(AL51>0,IF((AL51+BQ52)<H$10,AL51+BQ52,H$10),0) -> 0 | CX52: =IF(AM51>0,IF((AM51+BR52)<I$10,AM51+BR52,I$10),0) -> 0 | CY52: =IF(AN51>0,IF((AN51+BS52)<J$10,AN51+BS52,J$10),0) -> 0 | CZ52: =IF(AO51>0,IF((AO51+BT52)<K$10,AO51+BT52,K$10),0) -> 0 | DA52: =IF(AP51>0,IF((AP51+BU52)<L$10,AP51+BU52,L$10),0) -> 0 | ... DX52: =IF(BM51>0,IF((BM51+CR52)<AI$10,BM51+CR52,AI$10),0) -> 0 | DY52: =SUM(CT52:DX52) -> 3505.97 | EA52: =IF(AI50<=0,0,IF(CT51+$C51>AI50+BN51,AI50+BN51-CT51,$C51)) -> 0 | EB52: =IF(AJ50<=0,0,IF($C51<=SUM($EA52:EA52),0,IF(CU51+$C51-SUM($EA52:EA52)>AJ50+BO51,AJ50+BO51-CU51,$C51-SUM($EA52:EA52)))) -> 0 | EC52: =IF(AK50<=0,0,IF($C51<=SUM($EA52:EB52),0,IF(CV51+$C51-SUM($EA52:EB52)>AK50+BP51,AK50+BP51-CV51,$C51-SUM($EA52:EB52)))) -> 0 | ED52: =IF(AL50<=0,0,IF($C51<=SUM($EA52:EC52),0,IF(CW51+$C51-SUM($EA52:EC52)>AL50+BQ51,AL50+BQ51-CW51,$C51-SUM($EA52:EC52)))) -> 0 | EE52: =IF(AM50<=0,0,IF($C51<=SUM($EA52:ED52),0,IF(CX51+$C51-SUM($EA52:ED52)>AM50+BR51,AM50+BR51-CX51,$C51-SUM($EA52:ED52)))) -> 0 | EF52: =IF(AN50<=0,0,IF($C51<=SUM($EA52:EE52),0,IF(CY51+$C51-SUM($EA52:EE52)>AN50+BS51,AN50+BS51-CY51,$C51-SUM($EA52:EE52)))) -> 0 | EG52: =IF(AO50<=0,0,IF($C51<=SUM($EA52:EF52),0,IF(CZ51+$C51-SUM($EA52:EF52)>AO50+BT51,AO50+BT51-CZ51,$C51-SUM($EA52:EF52)))) -> 0 | EH52: =IF(AP50<=0,0,IF($C51<=SUM($EA52:EG52),0,IF(DA51+$C51-SUM($EA52:EG52)>AP50+BU51,AP50+BU51-DA51,$C51-SUM($EA52:EG52)))) -> 0 | EI52: =IF(AQ50<=0,0,IF($C51<=SUM($EA52:EH52),0,IF(DB51+$C51-SUM($EA52:EH52)>AQ50+BV51,AQ50+BV51-DB51,$C51-SUM($EA52:EH52)))) -> 366.03 | ... FC52: =IF(BK50<=0,0,IF($C51<=SUM($EA52:FB52),0,IF(DV51+$C51-SUM($EA52:FB52)>BK50+CP51,BK50+CP51-DV51,$C51-SUM($EA52:FB52)))) -> 0
A53: =IF(SUM(AI52:BK52)<=0,"",A52+1) -> 33 | B53: 46631 | C53: =IF(A53="","",IF(Calculator!snowball,IF(($E$5-DY53)<0,0,$E$5-DY53),0)+D53) -> 366.03 | D53: 10 | E53: =CT53+EA54 -> 0 | F53: =CU53+EB54 -> 0 | G53: =CV53+EC54 -> 0 | H53: =CW53+ED54 -> 0 | I53: =CX53+EE54 -> 0 | J53: =CY53+EF54 -> 0 | K53: =CZ53+EG54 -> 0 | L53: =DA53+EH54 -> 0 | ... AG53: =DV53+FC54 -> 0 | AH53: =SUM(AI53:BK53) -> 218279.19 | AI53: =IF(E$8=0,0,ROUND(AI52-(E53-BN53),2)) -> 0 | AJ53: =IF(F$8=0,0,ROUND(AJ52-(F53-BO53),2)) -> 0 | AK53: =IF(G$8=0,0,ROUND(AK52-(G53-BP53),2)) -> 0 | AL53: =IF(H$8=0,0,ROUND(AL52-(H53-BQ53),2)) -> 0 | AM53: =IF(I$8=0,0,ROUND(AM52-(I53-BR53),2)) -> 0 | AN53: =IF(J$8=0,0,ROUND(AN52-(J53-BS53),2)) -> 0 | AO53: =IF(K$8=0,0,ROUND(AO52-(K53-BT53),2)) -> 0 | AP53: 0 | AQ53: =IF(M$8=0,0,ROUND(AQ52-(M53-BV53),2)) -> 0 | AR53: =IF(N$8=0,0,ROUND(AR52-(N53-BW53),2)) -> 6420.54 | AS53: =IF(O$8=0,0,ROUND(AS52-(O53-BX53),2)) -> 32949.41 | AT53: =IF(P$8=0,0,ROUND(AT52-(P53-BX53),2)) -> 35405.53 | AU53: =IF(Q$8=0,0,ROUND(AU52-(Q53-BY53),2)) -> 143503.71 | AV53: =IF(R$8=0,0,ROUND(AV52-(R53-BZ53),2)) -> 0 | AW53: =IF(S$8=0,0,ROUND(AW52-(S53-CA53),2)) -> 0 | AX53: =IF(T$8=0,0,ROUND(AX52-(T53-CB53),2)) -> 0 | AY53: =IF(U$8=0,0,ROUND(AY52-(U53-CC53),2)) -> 0 | AZ53: =IF(V$8=0,0,ROUND(AZ52-(V53-CD53),2)) -> 0 | BA53: =IF(W$8=0,0,ROUND(BA52-(W53-CE53),2)) -> 0 | ... BK53: =IF(AG$8=0,0,ROUND(BK52-(AG53-CO53),2)) -> 0 | BL53: =SUM(AI53:BK53) -> 218279.19 | BN53: =ROUND(AI52*E$9/12,2) -> 0 | BO53: =ROUND(AJ52*F$9/12,2) -> 0 | BP53: =ROUND(AK52*G$9/12,2) -> 0 | BQ53: =ROUND(AL52*H$9/12,2) -> 0 | BR53: =ROUND(AM52*I$9/12,2) -> 0 | BS53: =ROUND(AN52*J$9/12,2) -> 0 | BT53: =ROUND(AO52*K$9/12,2) -> 0 | BU53: =ROUND(AP52*L$9/12,2) -> 0 | ... CP53: =ROUND(BK52*AG$9/12,2) -> 0 | CR53: =SUM(BN53:CP53) -> 1147.05 | CT53: =IF(AI52>0,IF((AI52+BN53)<E$10,AI52+BN53,E$10),0) -> 0 | CU53: =IF(AJ52>0,IF((AJ52+BO53)<F$10,AJ52+BO53,F$10),0) -> 0 | CV53: =IF(AK52>0,IF((AK52+BP53)<G$10,AK52+BP53,G$10),0) -> 0 | CW53: =IF(AL52>0,IF((AL52+BQ53)<H$10,AL52+BQ53,H$10),0) -> 0 | CX53: =IF(AM52>0,IF((AM52+BR53)<I$10,AM52+BR53,I$10),0) -> 0 | CY53: =IF(AN52>0,IF((AN52+BS53)<J$10,AN52+BS53,J$10),0) -> 0 | CZ53: =IF(AO52>0,IF((AO52+BT53)<K$10,AO52+BT53,K$10),0) -> 0 | DA53: =IF(AP52>0,IF((AP52+BU53)<L$10,AP52+BU53,L$10),0) -> 0 | ... DX53: =IF(BM52>0,IF((BM52+CR53)<AI$10,BM52+CR53,AI$10),0) -> 0 | DY53: =SUM(CT53:DX53) -> 3505.97 | EA53: =IF(AI51<=0,0,IF(CT52+$C52>AI51+BN52,AI51+BN52-CT52,$C52)) -> 0 | EB53: =IF(AJ51<=0,0,IF($C52<=SUM($EA53:EA53),0,IF(CU52+$C52-SUM($EA53:EA53)>AJ51+BO52,AJ51+BO52-CU52,$C52-SUM($EA53:EA53)))) -> 0 | EC53: =IF(AK51<=0,0,IF($C52<=SUM($EA53:EB53),0,IF(CV52+$C52-SUM($EA53:EB53)>AK51+BP52,AK51+BP52-CV52,$C52-SUM($EA53:EB53)))) -> 0 | ED53: =IF(AL51<=0,0,IF($C52<=SUM($EA53:EC53),0,IF(CW52+$C52-SUM($EA53:EC53)>AL51+BQ52,AL51+BQ52-CW52,$C52-SUM($EA53:EC53)))) -> 0 | EE53: =IF(AM51<=0,0,IF($C52<=SUM($EA53:ED53),0,IF(CX52+$C52-SUM($EA53:ED53)>AM51+BR52,AM51+BR52-CX52,$C52-SUM($EA53:ED53)))) -> 0 | EF53: =IF(AN51<=0,0,IF($C52<=SUM($EA53:EE53),0,IF(CY52+$C52-SUM($EA53:EE53)>AN51+BS52,AN51+BS52-CY52,$C52-SUM($EA53:EE53)))) -> 0 | EG53: =IF(AO51<=0,0,IF($C52<=SUM($EA53:EF53),0,IF(CZ52+$C52-SUM($EA53:EF53)>AO51+BT52,AO51+BT52-CZ52,$C52-SUM($EA53:EF53)))) -> 0 | EH53: =IF(AP51<=0,0,IF($C52<=SUM($EA53:EG53),0,IF(DA52+$C52-SUM($EA53:EG53)>AP51+BU52,AP51+BU52-DA52,$C52-SUM($EA53:EG53)))) -> 0 | EI53: =IF(AQ51<=0,0,IF($C52<=SUM($EA53:EH53),0,IF(DB52+$C52-SUM($EA53:EH53)>AQ51+BV52,AQ51+BV52-DB52,$C52-SUM($EA53:EH53)))) -> 366.03 | ... FC53: =IF(BK51<=0,0,IF($C52<=SUM($EA53:FB53),0,IF(DV52+$C52-SUM($EA53:FB53)>BK51+CP52,BK51+CP52-DV52,$C52-SUM($EA53:FB53)))) -> 0
A54: =IF(SUM(AI53:BK53)<=0,"",A53+1) -> 34 | B54: 46661 | C54: =IF(A54="","",IF(Calculator!snowball,IF(($E$5-DY54)<0,0,$E$5-DY54),0)+D54) -> 468.03 | D54: 10 | E54: =CT54+EA55 -> 0 | F54: =CU54+EB55 -> 0 | G54: =CV54+EC55 -> 0 | H54: =CW54+ED55 -> 0 | I54: =CX54+EE55 -> 0 | J54: =CY54+EF55 -> 0 | K54: =CZ54+EG55 -> 0 | L54: =DA54+EH55 -> 0 | ... AG54: =DV54+FC55 -> 0 | AH54: =SUM(AI54:BK54) -> 215381.38 | AI54: =IF(E$8=0,0,ROUND(AI53-(E54-BN54),2)) -> 0 | AJ54: =IF(F$8=0,0,ROUND(AJ53-(F54-BO54),2)) -> 0 | AK54: =IF(G$8=0,0,ROUND(AK53-(G54-BP54),2)) -> 0 | AL54: =IF(H$8=0,0,ROUND(AL53-(H54-BQ54),2)) -> 0 | AM54: =IF(I$8=0,0,ROUND(AM53-(I54-BR54),2)) -> 0 | AN54: =IF(J$8=0,0,ROUND(AN53-(J54-BS54),2)) -> 0 | AO54: =IF(K$8=0,0,ROUND(AO53-(K54-BT54),2)) -> 0 | AP54: 0 | AQ54: =IF(M$8=0,0,ROUND(AQ53-(M54-BV54),2)) -> 0 | AR54: =IF(N$8=0,0,ROUND(AR53-(N54-BW54),2)) -> 5598.74 | AS54: =IF(O$8=0,0,ROUND(AS53-(O54-BX54),2)) -> 32555.85 | AT54: =IF(P$8=0,0,ROUND(AT53-(P54-BX54),2)) -> 34916.41 | AU54: =IF(Q$8=0,0,ROUND(AU53-(Q54-BY54),2)) -> 142310.38 | AV54: =IF(R$8=0,0,ROUND(AV53-(R54-BZ54),2)) -> 0 | AW54: =IF(S$8=0,0,ROUND(AW53-(S54-CA54),2)) -> 0 | AX54: =IF(T$8=0,0,ROUND(AX53-(T54-CB54),2)) -> 0 | AY54: =IF(U$8=0,0,ROUND(AY53-(U54-CC54),2)) -> 0 | AZ54: =IF(V$8=0,0,ROUND(AZ53-(V54-CD54),2)) -> 0 | BA54: =IF(W$8=0,0,ROUND(BA53-(W54-CE54),2)) -> 0 | ... BK54: =IF(AG$8=0,0,ROUND(BK53-(AG54-CO54),2)) -> 0 | BL54: =SUM(AI54:BK54) -> 215381.38 | BN54: =ROUND(AI53*E$9/12,2) -> 0 | BO54: =ROUND(AJ53*F$9/12,2) -> 0 | BP54: =ROUND(AK53*G$9/12,2) -> 0 | BQ54: =ROUND(AL53*H$9/12,2) -> 0 | BR54: =ROUND(AM53*I$9/12,2) -> 0 | BS54: =ROUND(AN53*J$9/12,2) -> 0 | BT54: =ROUND(AO53*K$9/12,2) -> 0 | BU54: =ROUND(AP53*L$9/12,2) -> 0 | ... CP54: =ROUND(BK53*AG$9/12,2) -> 0 | CR54: =SUM(BN54:CP54) -> 1120.6 | CT54: =IF(AI53>0,IF((AI53+BN54)<E$10,AI53+BN54,E$10),0) -> 0 | CU54: =IF(AJ53>0,IF((AJ53+BO54)<F$10,AJ53+BO54,F$10),0) -> 0 | CV54: =IF(AK53>0,IF((AK53+BP54)<G$10,AK53+BP54,G$10),0) -> 0 | CW54: =IF(AL53>0,IF((AL53+BQ54)<H$10,AL53+BQ54,H$10),0) -> 0 | CX54: =IF(AM53>0,IF((AM53+BR54)<I$10,AM53+BR54,I$10),0) -> 0 | CY54: =IF(AN53>0,IF((AN53+BS54)<J$10,AN53+BS54,J$10),0) -> 0 | CZ54: =IF(AO53>0,IF((AO53+BT54)<K$10,AO53+BT54,K$10),0) -> 0 | DA54: =IF(AP53>0,IF((AP53+BU54)<L$10,AP53+BU54,L$10),0) -> 0 | ... DX54: =IF(BM53>0,IF((BM53+CR54)<AI$10,BM53+CR54,AI$10),0) -> 0 | DY54: =SUM(CT54:DX54) -> 3403.97 | EA54: =IF(AI52<=0,0,IF(CT53+$C53>AI52+BN53,AI52+BN53-CT53,$C53)) -> 0 | EB54: =IF(AJ52<=0,0,IF($C53<=SUM($EA54:EA54),0,IF(CU53+$C53-SUM($EA54:EA54)>AJ52+BO53,AJ52+BO53-CU53,$C53-SUM($EA54:EA54)))) -> 0 | EC54: =IF(AK52<=0,0,IF($C53<=SUM($EA54:EB54),0,IF(CV53+$C53-SUM($EA54:EB54)>AK52+BP53,AK52+BP53-CV53,$C53-SUM($EA54:EB54)))) -> 0 | ED54: =IF(AL52<=0,0,IF($C53<=SUM($EA54:EC54),0,IF(CW53+$C53-SUM($EA54:EC54)>AL52+BQ53,AL52+BQ53-CW53,$C53-SUM($EA54:EC54)))) -> 0 | EE54: =IF(AM52<=0,0,IF($C53<=SUM($EA54:ED54),0,IF(CX53+$C53-SUM($EA54:ED54)>AM52+BR53,AM52+BR53-CX53,$C53-SUM($EA54:ED54)))) -> 0 | EF54: =IF(AN52<=0,0,IF($C53<=SUM($EA54:EE54),0,IF(CY53+$C53-SUM($EA54:EE54)>AN52+BS53,AN52+BS53-CY53,$C53-SUM($EA54:EE54)))) -> 0 | EG54: =IF(AO52<=0,0,IF($C53<=SUM($EA54:EF54),0,IF(CZ53+$C53-SUM($EA54:EF54)>AO52+BT53,AO52+BT53-CZ53,$C53-SUM($EA54:EF54)))) -> 0 | EH54: =IF(AP52<=0,0,IF($C53<=SUM($EA54:EG54),0,IF(DA53+$C53-SUM($EA54:EG54)>AP52+BU53,AP52+BU53-DA53,$C53-SUM($EA54:EG54)))) -> 0 | EI54: =IF(AQ52<=0,0,IF($C53<=SUM($EA54:EH54),0,IF(DB53+$C53-SUM($EA54:EH54)>AQ52+BV53,AQ52+BV53-DB53,$C53-SUM($EA54:EH54)))) -> 244.68 | ... FC54: =IF(BK52<=0,0,IF($C53<=SUM($EA54:FB54),0,IF(DV53+$C53-SUM($EA54:FB54)>BK52+CP53,BK52+CP53-DV53,$C53-SUM($EA54:FB54)))) -> 0
A55: =IF(SUM(AI54:BK54)<=0,"",A54+1) -> 35 | B55: 46692 | C55: =IF(A55="","",IF(Calculator!snowball,IF(($E$5-DY55)<0,0,$E$5-DY55),0)+D55) -> 468.03 | D55: 10 | E55: =CT55+EA56 -> 0 | F55: =CU55+EB56 -> 0 | G55: =CV55+EC56 -> 0 | H55: =CW55+ED56 -> 0 | I55: =CX55+EE56 -> 0 | J55: =CY55+EF56 -> 0 | K55: =CZ55+EG56 -> 0 | L55: =DA55+EH56 -> 0 | ... AG55: =DV55+FC56 -> 0 | AH55: =SUM(AI55:BK55) -> 212460.24 | AI55: =IF(E$8=0,0,ROUND(AI54-(E55-BN55),2)) -> 0 | AJ55: =IF(F$8=0,0,ROUND(AJ54-(F55-BO55),2)) -> 0 | AK55: =IF(G$8=0,0,ROUND(AK54-(G55-BP55),2)) -> 0 | AL55: =IF(H$8=0,0,ROUND(AL54-(H55-BQ55),2)) -> 0 | AM55: =IF(I$8=0,0,ROUND(AM54-(I55-BR55),2)) -> 0 | AN55: =IF(J$8=0,0,ROUND(AN54-(J55-BS55),2)) -> 0 | AO55: =IF(K$8=0,0,ROUND(AO54-(K55-BT55),2)) -> 0 | AP55: 0 | AQ55: =IF(M$8=0,0,ROUND(AQ54-(M55-BV55),2)) -> 0 | AR55: =IF(N$8=0,0,ROUND(AR54-(N55-BW55),2)) -> 4764.61 | AS55: =IF(O$8=0,0,ROUND(AS54-(O55-BX55),2)) -> 32158.68 | AT55: =IF(P$8=0,0,ROUND(AT54-(P55-BX55),2)) -> 34423.68 | AU55: =IF(Q$8=0,0,ROUND(AU54-(Q55-BY55),2)) -> 141113.27 | AV55: =IF(R$8=0,0,ROUND(AV54-(R55-BZ55),2)) -> 0 | AW55: =IF(S$8=0,0,ROUND(AW54-(S55-CA55),2)) -> 0 | AX55: =IF(T$8=0,0,ROUND(AX54-(T55-CB55),2)) -> 0 | AY55: =IF(U$8=0,0,ROUND(AY54-(U55-CC55),2)) -> 0 | AZ55: =IF(V$8=0,0,ROUND(AZ54-(V55-CD55),2)) -> 0 | BA55: =IF(W$8=0,0,ROUND(BA54-(W55-CE55),2)) -> 0 | ... BK55: =IF(AG$8=0,0,ROUND(BK54-(AG55-CO55),2)) -> 0 | BL55: =SUM(AI55:BK55) -> 212460.24 | BN55: =ROUND(AI54*E$9/12,2) -> 0 | BO55: =ROUND(AJ54*F$9/12,2) -> 0 | BP55: =ROUND(AK54*G$9/12,2) -> 0 | BQ55: =ROUND(AL54*H$9/12,2) -> 0 | BR55: =ROUND(AM54*I$9/12,2) -> 0 | BS55: =ROUND(AN54*J$9/12,2) -> 0 | BT55: =ROUND(AO54*K$9/12,2) -> 0 | BU55: =ROUND(AP54*L$9/12,2) -> 0 | ... CP55: =ROUND(BK54*AG$9/12,2) -> 0 | CR55: =SUM(BN55:CP55) -> 1097.15 | CT55: =IF(AI54>0,IF((AI54+BN55)<E$10,AI54+BN55,E$10),0) -> 0 | CU55: =IF(AJ54>0,IF((AJ54+BO55)<F$10,AJ54+BO55,F$10),0) -> 0 | CV55: =IF(AK54>0,IF((AK54+BP55)<G$10,AK54+BP55,G$10),0) -> 0 | CW55: =IF(AL54>0,IF((AL54+BQ55)<H$10,AL54+BQ55,H$10),0) -> 0 | CX55: =IF(AM54>0,IF((AM54+BR55)<I$10,AM54+BR55,I$10),0) -> 0 | CY55: =IF(AN54>0,IF((AN54+BS55)<J$10,AN54+BS55,J$10),0) -> 0 | CZ55: =IF(AO54>0,IF((AO54+BT55)<K$10,AO54+BT55,K$10),0) -> 0 | DA55: =IF(AP54>0,IF((AP54+BU55)<L$10,AP54+BU55,L$10),0) -> 0 | ... DX55: =IF(BM54>0,IF((BM54+CR55)<AI$10,BM54+CR55,AI$10),0) -> 0 | DY55: =SUM(CT55:DX55) -> 3403.97 | EA55: =IF(AI53<=0,0,IF(CT54+$C54>AI53+BN54,AI53+BN54-CT54,$C54)) -> 0 | EB55: =IF(AJ53<=0,0,IF($C54<=SUM($EA55:EA55),0,IF(CU54+$C54-SUM($EA55:EA55)>AJ53+BO54,AJ53+BO54-CU54,$C54-SUM($EA55:EA55)))) -> 0 | EC55: =IF(AK53<=0,0,IF($C54<=SUM($EA55:EB55),0,IF(CV54+$C54-SUM($EA55:EB55)>AK53+BP54,AK53+BP54-CV54,$C54-SUM($EA55:EB55)))) -> 0 | ED55: =IF(AL53<=0,0,IF($C54<=SUM($EA55:EC55),0,IF(CW54+$C54-SUM($EA55:EC55)>AL53+BQ54,AL53+BQ54-CW54,$C54-SUM($EA55:EC55)))) -> 0 | EE55: =IF(AM53<=0,0,IF($C54<=SUM($EA55:ED55),0,IF(CX54+$C54-SUM($EA55:ED55)>AM53+BR54,AM53+BR54-CX54,$C54-SUM($EA55:ED55)))) -> 0 | EF55: =IF(AN53<=0,0,IF($C54<=SUM($EA55:EE55),0,IF(CY54+$C54-SUM($EA55:EE55)>AN53+BS54,AN53+BS54-CY54,$C54-SUM($EA55:EE55)))) -> 0 | EG55: =IF(AO53<=0,0,IF($C54<=SUM($EA55:EF55),0,IF(CZ54+$C54-SUM($EA55:EF55)>AO53+BT54,AO53+BT54-CZ54,$C54-SUM($EA55:EF55)))) -> 0 | EH55: =IF(AP53<=0,0,IF($C54<=SUM($EA55:EG55),0,IF(DA54+$C54-SUM($EA55:EG55)>AP53+BU54,AP53+BU54-DA54,$C54-SUM($EA55:EG55)))) -> 0 | EI55: =IF(AQ53<=0,0,IF($C54<=SUM($EA55:EH55),0,IF(DB54+$C54-SUM($EA55:EH55)>AQ53+BV54,AQ53+BV54-DB54,$C54-SUM($EA55:EH55)))) -> 0 | ... FC55: =IF(BK53<=0,0,IF($C54<=SUM($EA55:FB55),0,IF(DV54+$C54-SUM($EA55:FB55)>BK53+CP54,BK53+CP54-DV54,$C54-SUM($EA55:FB55)))) -> 0
A56: =IF(SUM(AI55:BK55)<=0,"",A55+1) -> 36 | B56: 46722 | C56: =IF(A56="","",IF(Calculator!snowball,IF(($E$5-DY56)<0,0,$E$5-DY56),0)+D56) -> 468.03 | D56: 10 | E56: =CT56+EA57 -> 0 | F56: =CU56+EB57 -> 0 | G56: =CV56+EC57 -> 0 | H56: =CW56+ED57 -> 0 | I56: =CX56+EE57 -> 0 | J56: =CY56+EF57 -> 0 | K56: =CZ56+EG57 -> 0 | L56: =DA56+EH57 -> 0 | ... AG56: =DV56+FC57 -> 0 | AH56: =SUM(AI56:BK56) -> 209515.5 | AI56: =IF(E$8=0,0,ROUND(AI55-(E56-BN56),2)) -> 0 | AJ56: =IF(F$8=0,0,ROUND(AJ55-(F56-BO56),2)) -> 0 | AK56: =IF(G$8=0,0,ROUND(AK55-(G56-BP56),2)) -> 0 | AL56: =IF(H$8=0,0,ROUND(AL55-(H56-BQ56),2)) -> 0 | AM56: =IF(I$8=0,0,ROUND(AM55-(I56-BR56),2)) -> 0 | AN56: =IF(J$8=0,0,ROUND(AN55-(J56-BS56),2)) -> 0 | AO56: =IF(K$8=0,0,ROUND(AO55-(K56-BT56),2)) -> 0 | AP56: 0 | AQ56: =IF(M$8=0,0,ROUND(AQ55-(M56-BV56),2)) -> 0 | AR56: =IF(N$8=0,0,ROUND(AR55-(N56-BW56),2)) -> 3917.97 | AS56: =IF(O$8=0,0,ROUND(AS55-(O56-BX56),2)) -> 31757.87 | AT56: =IF(P$8=0,0,ROUND(AT55-(P56-BX56),2)) -> 33927.31 | AU56: =IF(Q$8=0,0,ROUND(AU55-(Q56-BY56),2)) -> 139912.35 | AV56: =IF(R$8=0,0,ROUND(AV55-(R56-BZ56),2)) -> 0 | AW56: =IF(S$8=0,0,ROUND(AW55-(S56-CA56),2)) -> 0 | AX56: =IF(T$8=0,0,ROUND(AX55-(T56-CB56),2)) -> 0 | AY56: =IF(U$8=0,0,ROUND(AY55-(U56-CC56),2)) -> 0 | AZ56: =IF(V$8=0,0,ROUND(AZ55-(V56-CD56),2)) -> 0 | BA56: =IF(W$8=0,0,ROUND(BA55-(W56-CE56),2)) -> 0 | ... BK56: =IF(AG$8=0,0,ROUND(BK55-(AG56-CO56),2)) -> 0 | BL56: =SUM(AI56:BK56) -> 209515.5 | BN56: =ROUND(AI55*E$9/12,2) -> 0 | BO56: =ROUND(AJ55*F$9/12,2) -> 0 | BP56: =ROUND(AK55*G$9/12,2) -> 0 | BQ56: =ROUND(AL55*H$9/12,2) -> 0 | BR56: =ROUND(AM55*I$9/12,2) -> 0 | BS56: =ROUND(AN55*J$9/12,2) -> 0 | BT56: =ROUND(AO55*K$9/12,2) -> 0 | BU56: =ROUND(AP55*L$9/12,2) -> 0 | ... CP56: =ROUND(BK55*AG$9/12,2) -> 0 | CR56: =SUM(BN56:CP56) -> 1073.45 | CT56: =IF(AI55>0,IF((AI55+BN56)<E$10,AI55+BN56,E$10),0) -> 0 | CU56: =IF(AJ55>0,IF((AJ55+BO56)<F$10,AJ55+BO56,F$10),0) -> 0 | CV56: =IF(AK55>0,IF((AK55+BP56)<G$10,AK55+BP56,G$10),0) -> 0 | CW56: =IF(AL55>0,IF((AL55+BQ56)<H$10,AL55+BQ56,H$10),0) -> 0 | CX56: =IF(AM55>0,IF((AM55+BR56)<I$10,AM55+BR56,I$10),0) -> 0 | CY56: =IF(AN55>0,IF((AN55+BS56)<J$10,AN55+BS56,J$10),0) -> 0 | CZ56: =IF(AO55>0,IF((AO55+BT56)<K$10,AO55+BT56,K$10),0) -> 0 | DA56: =IF(AP55>0,IF((AP55+BU56)<L$10,AP55+BU56,L$10),0) -> 0 | ... DX56: =IF(BM55>0,IF((BM55+CR56)<AI$10,BM55+CR56,AI$10),0) -> 0 | DY56: =SUM(CT56:DX56) -> 3403.97 | EA56: =IF(AI54<=0,0,IF(CT55+$C55>AI54+BN55,AI54+BN55-CT55,$C55)) -> 0 | EB56: =IF(AJ54<=0,0,IF($C55<=SUM($EA56:EA56),0,IF(CU55+$C55-SUM($EA56:EA56)>AJ54+BO55,AJ54+BO55-CU55,$C55-SUM($EA56:EA56)))) -> 0 | EC56: =IF(AK54<=0,0,IF($C55<=SUM($EA56:EB56),0,IF(CV55+$C55-SUM($EA56:EB56)>AK54+BP55,AK54+BP55-CV55,$C55-SUM($EA56:EB56)))) -> 0 | ED56: =IF(AL54<=0,0,IF($C55<=SUM($EA56:EC56),0,IF(CW55+$C55-SUM($EA56:EC56)>AL54+BQ55,AL54+BQ55-CW55,$C55-SUM($EA56:EC56)))) -> 0 | EE56: =IF(AM54<=0,0,IF($C55<=SUM($EA56:ED56),0,IF(CX55+$C55-SUM($EA56:ED56)>AM54+BR55,AM54+BR55-CX55,$C55-SUM($EA56:ED56)))) -> 0 | EF56: =IF(AN54<=0,0,IF($C55<=SUM($EA56:EE56),0,IF(CY55+$C55-SUM($EA56:EE56)>AN54+BS55,AN54+BS55-CY55,$C55-SUM($EA56:EE56)))) -> 0 | EG56: =IF(AO54<=0,0,IF($C55<=SUM($EA56:EF56),0,IF(CZ55+$C55-SUM($EA56:EF56)>AO54+BT55,AO54+BT55-CZ55,$C55-SUM($EA56:EF56)))) -> 0 | EH56: =IF(AP54<=0,0,IF($C55<=SUM($EA56:EG56),0,IF(DA55+$C55-SUM($EA56:EG56)>AP54+BU55,AP54+BU55-DA55,$C55-SUM($EA56:EG56)))) -> 0 | EI56: =IF(AQ54<=0,0,IF($C55<=SUM($EA56:EH56),0,IF(DB55+$C55-SUM($EA56:EH56)>AQ54+BV55,AQ54+BV55-DB55,$C55-SUM($EA56:EH56)))) -> 0 | ... FC56: =IF(BK54<=0,0,IF($C55<=SUM($EA56:FB56),0,IF(DV55+$C55-SUM($EA56:FB56)>BK54+CP55,BK54+CP55-DV55,$C55-SUM($EA56:FB56)))) -> 0
A57: =IF(SUM(AI56:BK56)<=0,"",A56+1) -> 37 | B57: 46753 | C57: =IF(A57="","",IF(Calculator!snowball,IF(($E$5-DY57)<0,0,$E$5-DY57),0)+D57) -> 468.03 | D57: 10 | E57: =CT57+EA58 -> 0 | F57: =CU57+EB58 -> 0 | G57: =CV57+EC58 -> 0 | H57: =CW57+ED58 -> 0 | I57: =CX57+EE58 -> 0 | J57: =CY57+EF58 -> 0 | K57: =CZ57+EG58 -> 0 | L57: =DA57+EH58 -> 0 | ... AG57: =DV57+FC58 -> 0 | AH57: =SUM(AI57:BK57) -> 206546.86 | AI57: =IF(E$8=0,0,ROUND(AI56-(E57-BN57),2)) -> 0 | AJ57: =IF(F$8=0,0,ROUND(AJ56-(F57-BO57),2)) -> 0 | AK57: =IF(G$8=0,0,ROUND(AK56-(G57-BP57),2)) -> 0 | AL57: =IF(H$8=0,0,ROUND(AL56-(H57-BQ57),2)) -> 0 | AM57: =IF(I$8=0,0,ROUND(AM56-(I57-BR57),2)) -> 0 | AN57: =IF(J$8=0,0,ROUND(AN56-(J57-BS57),2)) -> 0 | AO57: =IF(K$8=0,0,ROUND(AO56-(K57-BT57),2)) -> 0 | AP57: 0 | AQ57: =IF(M$8=0,0,ROUND(AQ56-(M57-BV57),2)) -> 0 | AR57: =IF(N$8=0,0,ROUND(AR56-(N57-BW57),2)) -> 3058.63 | AS57: =IF(O$8=0,0,ROUND(AS56-(O57-BX57),2)) -> 31353.38 | AT57: =IF(P$8=0,0,ROUND(AT56-(P57-BX57),2)) -> 33427.26 | AU57: =IF(Q$8=0,0,ROUND(AU56-(Q57-BY57),2)) -> 138707.59 | AV57: =IF(R$8=0,0,ROUND(AV56-(R57-BZ57),2)) -> 0 | AW57: =IF(S$8=0,0,ROUND(AW56-(S57-CA57),2)) -> 0 | AX57: =IF(T$8=0,0,ROUND(AX56-(T57-CB57),2)) -> 0 | AY57: =IF(U$8=0,0,ROUND(AY56-(U57-CC57),2)) -> 0 | AZ57: =IF(V$8=0,0,ROUND(AZ56-(V57-CD57),2)) -> 0 | BA57: =IF(W$8=0,0,ROUND(BA56-(W57-CE57),2)) -> 0 | ... BK57: =IF(AG$8=0,0,ROUND(BK56-(AG57-CO57),2)) -> 0 | BL57: =SUM(AI57:BK57) -> 206546.86 | BN57: =ROUND(AI56*E$9/12,2) -> 0 | BO57: =ROUND(AJ56*F$9/12,2) -> 0 | BP57: =ROUND(AK56*G$9/12,2) -> 0 | BQ57: =ROUND(AL56*H$9/12,2) -> 0 | BR57: =ROUND(AM56*I$9/12,2) -> 0 | BS57: =ROUND(AN56*J$9/12,2) -> 0 | BT57: =ROUND(AO56*K$9/12,2) -> 0 | BU57: =ROUND(AP56*L$9/12,2) -> 0 | ... CP57: =ROUND(BK56*AG$9/12,2) -> 0 | CR57: =SUM(BN57:CP57) -> 1049.48 | CT57: =IF(AI56>0,IF((AI56+BN57)<E$10,AI56+BN57,E$10),0) -> 0 | CU57: =IF(AJ56>0,IF((AJ56+BO57)<F$10,AJ56+BO57,F$10),0) -> 0 | CV57: =IF(AK56>0,IF((AK56+BP57)<G$10,AK56+BP57,G$10),0) -> 0 | CW57: =IF(AL56>0,IF((AL56+BQ57)<H$10,AL56+BQ57,H$10),0) -> 0 | CX57: =IF(AM56>0,IF((AM56+BR57)<I$10,AM56+BR57,I$10),0) -> 0 | CY57: =IF(AN56>0,IF((AN56+BS57)<J$10,AN56+BS57,J$10),0) -> 0 | CZ57: =IF(AO56>0,IF((AO56+BT57)<K$10,AO56+BT57,K$10),0) -> 0 | DA57: =IF(AP56>0,IF((AP56+BU57)<L$10,AP56+BU57,L$10),0) -> 0 | ... DX57: =IF(BM56>0,IF((BM56+CR57)<AI$10,BM56+CR57,AI$10),0) -> 0 | DY57: =SUM(CT57:DX57) -> 3403.97 | EA57: =IF(AI55<=0,0,IF(CT56+$C56>AI55+BN56,AI55+BN56-CT56,$C56)) -> 0 | EB57: =IF(AJ55<=0,0,IF($C56<=SUM($EA57:EA57),0,IF(CU56+$C56-SUM($EA57:EA57)>AJ55+BO56,AJ55+BO56-CU56,$C56-SUM($EA57:EA57)))) -> 0 | EC57: =IF(AK55<=0,0,IF($C56<=SUM($EA57:EB57),0,IF(CV56+$C56-SUM($EA57:EB57)>AK55+BP56,AK55+BP56-CV56,$C56-SUM($EA57:EB57)))) -> 0 | ED57: =IF(AL55<=0,0,IF($C56<=SUM($EA57:EC57),0,IF(CW56+$C56-SUM($EA57:EC57)>AL55+BQ56,AL55+BQ56-CW56,$C56-SUM($EA57:EC57)))) -> 0 | EE57: =IF(AM55<=0,0,IF($C56<=SUM($EA57:ED57),0,IF(CX56+$C56-SUM($EA57:ED57)>AM55+BR56,AM55+BR56-CX56,$C56-SUM($EA57:ED57)))) -> 0 | EF57: =IF(AN55<=0,0,IF($C56<=SUM($EA57:EE57),0,IF(CY56+$C56-SUM($EA57:EE57)>AN55+BS56,AN55+BS56-CY56,$C56-SUM($EA57:EE57)))) -> 0 | EG57: =IF(AO55<=0,0,IF($C56<=SUM($EA57:EF57),0,IF(CZ56+$C56-SUM($EA57:EF57)>AO55+BT56,AO55+BT56-CZ56,$C56-SUM($EA57:EF57)))) -> 0 | EH57: =IF(AP55<=0,0,IF($C56<=SUM($EA57:EG57),0,IF(DA56+$C56-SUM($EA57:EG57)>AP55+BU56,AP55+BU56-DA56,$C56-SUM($EA57:EG57)))) -> 0 | EI57: =IF(AQ55<=0,0,IF($C56<=SUM($EA57:EH57),0,IF(DB56+$C56-SUM($EA57:EH57)>AQ55+BV56,AQ55+BV56-DB56,$C56-SUM($EA57:EH57)))) -> 0 | ... FC57: =IF(BK55<=0,0,IF($C56<=SUM($EA57:FB57),0,IF(DV56+$C56-SUM($EA57:FB57)>BK55+CP56,BK55+CP56-DV56,$C56-SUM($EA57:FB57)))) -> 0
A58: =IF(SUM(AI57:BK57)<=0,"",A57+1) -> 38 | B58: 46784 | C58: =IF(A58="","",IF(Calculator!snowball,IF(($E$5-DY58)<0,0,$E$5-DY58),0)+D58) -> 468.03 | D58: 10 | E58: =CT58+EA59 -> 0 | F58: =CU58+EB59 -> 0 | G58: =CV58+EC59 -> 0 | H58: =CW58+ED59 -> 0 | I58: =CX58+EE59 -> 0 | J58: =CY58+EF59 -> 0 | K58: =CZ58+EG59 -> 0 | L58: =DA58+EH59 -> 0 | ... AG58: =DV58+FC59 -> 0 | AH58: =SUM(AI58:BK58) -> 203554.06 | AI58: =IF(E$8=0,0,ROUND(AI57-(E58-BN58),2)) -> 0 | AJ58: =IF(F$8=0,0,ROUND(AJ57-(F58-BO58),2)) -> 0 | AK58: =IF(G$8=0,0,ROUND(AK57-(G58-BP58),2)) -> 0 | AL58: =IF(H$8=0,0,ROUND(AL57-(H58-BQ58),2)) -> 0 | AM58: =IF(I$8=0,0,ROUND(AM57-(I58-BR58),2)) -> 0 | AN58: =IF(J$8=0,0,ROUND(AN57-(J58-BS58),2)) -> 0 | AO58: =IF(K$8=0,0,ROUND(AO57-(K58-BT58),2)) -> 0 | AP58: 0 | AQ58: =IF(M$8=0,0,ROUND(AQ57-(M58-BV58),2)) -> 0 | AR58: =IF(N$8=0,0,ROUND(AR57-(N58-BW58),2)) -> 2186.4 | AS58: =IF(O$8=0,0,ROUND(AS57-(O58-BX58),2)) -> 30945.19 | AT58: =IF(P$8=0,0,ROUND(AT57-(P58-BX58),2)) -> 32923.51 | AU58: =IF(Q$8=0,0,ROUND(AU57-(Q58-BY58),2)) -> 137498.96 | AV58: =IF(R$8=0,0,ROUND(AV57-(R58-BZ58),2)) -> 0 | AW58: =IF(S$8=0,0,ROUND(AW57-(S58-CA58),2)) -> 0 | AX58: =IF(T$8=0,0,ROUND(AX57-(T58-CB58),2)) -> 0 | AY58: =IF(U$8=0,0,ROUND(AY57-(U58-CC58),2)) -> 0 | AZ58: =IF(V$8=0,0,ROUND(AZ57-(V58-CD58),2)) -> 0 | BA58: =IF(W$8=0,0,ROUND(BA57-(W58-CE58),2)) -> 0 | ... BK58: =IF(AG$8=0,0,ROUND(BK57-(AG58-CO58),2)) -> 0 | BL58: =SUM(AI58:BK58) -> 203554.06 | BN58: =ROUND(AI57*E$9/12,2) -> 0 | BO58: =ROUND(AJ57*F$9/12,2) -> 0 | BP58: =ROUND(AK57*G$9/12,2) -> 0 | BQ58: =ROUND(AL57*H$9/12,2) -> 0 | BR58: =ROUND(AM57*I$9/12,2) -> 0 | BS58: =ROUND(AN57*J$9/12,2) -> 0 | BT58: =ROUND(AO57*K$9/12,2) -> 0 | BU58: =ROUND(AP57*L$9/12,2) -> 0 | ... CP58: =ROUND(BK57*AG$9/12,2) -> 0 | CR58: =SUM(BN58:CP58) -> 1025.25 | CT58: =IF(AI57>0,IF((AI57+BN58)<E$10,AI57+BN58,E$10),0) -> 0 | CU58: =IF(AJ57>0,IF((AJ57+BO58)<F$10,AJ57+BO58,F$10),0) -> 0 | CV58: =IF(AK57>0,IF((AK57+BP58)<G$10,AK57+BP58,G$10),0) -> 0 | CW58: =IF(AL57>0,IF((AL57+BQ58)<H$10,AL57+BQ58,H$10),0) -> 0 | CX58: =IF(AM57>0,IF((AM57+BR58)<I$10,AM57+BR58,I$10),0) -> 0 | CY58: =IF(AN57>0,IF((AN57+BS58)<J$10,AN57+BS58,J$10),0) -> 0 | CZ58: =IF(AO57>0,IF((AO57+BT58)<K$10,AO57+BT58,K$10),0) -> 0 | DA58: =IF(AP57>0,IF((AP57+BU58)<L$10,AP57+BU58,L$10),0) -> 0 | ... DX58: =IF(BM57>0,IF((BM57+CR58)<AI$10,BM57+CR58,AI$10),0) -> 0 | DY58: =SUM(CT58:DX58) -> 3403.97 | EA58: =IF(AI56<=0,0,IF(CT57+$C57>AI56+BN57,AI56+BN57-CT57,$C57)) -> 0 | EB58: =IF(AJ56<=0,0,IF($C57<=SUM($EA58:EA58),0,IF(CU57+$C57-SUM($EA58:EA58)>AJ56+BO57,AJ56+BO57-CU57,$C57-SUM($EA58:EA58)))) -> 0 | EC58: =IF(AK56<=0,0,IF($C57<=SUM($EA58:EB58),0,IF(CV57+$C57-SUM($EA58:EB58)>AK56+BP57,AK56+BP57-CV57,$C57-SUM($EA58:EB58)))) -> 0 | ED58: =IF(AL56<=0,0,IF($C57<=SUM($EA58:EC58),0,IF(CW57+$C57-SUM($EA58:EC58)>AL56+BQ57,AL56+BQ57-CW57,$C57-SUM($EA58:EC58)))) -> 0 | EE58: =IF(AM56<=0,0,IF($C57<=SUM($EA58:ED58),0,IF(CX57+$C57-SUM($EA58:ED58)>AM56+BR57,AM56+BR57-CX57,$C57-SUM($EA58:ED58)))) -> 0 | EF58: =IF(AN56<=0,0,IF($C57<=SUM($EA58:EE58),0,IF(CY57+$C57-SUM($EA58:EE58)>AN56+BS57,AN56+BS57-CY57,$C57-SUM($EA58:EE58)))) -> 0 | EG58: =IF(AO56<=0,0,IF($C57<=SUM($EA58:EF58),0,IF(CZ57+$C57-SUM($EA58:EF58)>AO56+BT57,AO56+BT57-CZ57,$C57-SUM($EA58:EF58)))) -> 0 | EH58: =IF(AP56<=0,0,IF($C57<=SUM($EA58:EG58),0,IF(DA57+$C57-SUM($EA58:EG58)>AP56+BU57,AP56+BU57-DA57,$C57-SUM($EA58:EG58)))) -> 0 | EI58: =IF(AQ56<=0,0,IF($C57<=SUM($EA58:EH58),0,IF(DB57+$C57-SUM($EA58:EH58)>AQ56+BV57,AQ56+BV57-DB57,$C57-SUM($EA58:EH58)))) -> 0 | ... FC58: =IF(BK56<=0,0,IF($C57<=SUM($EA58:FB58),0,IF(DV57+$C57-SUM($EA58:FB58)>BK56+CP57,BK56+CP57-DV57,$C57-SUM($EA58:FB58)))) -> 0
A59: =IF(SUM(AI58:BK58)<=0,"",A58+1) -> 39 | B59: 46813 | C59: =IF(A59="","",IF(Calculator!snowball,IF(($E$5-DY59)<0,0,$E$5-DY59),0)+D59) -> 468.03 | D59: 10 | E59: =CT59+EA60 -> 0 | F59: =CU59+EB60 -> 0 | G59: =CV59+EC60 -> 0 | H59: =CW59+ED60 -> 0 | I59: =CX59+EE60 -> 0 | J59: =CY59+EF60 -> 0 | K59: =CZ59+EG60 -> 0 | L59: =DA59+EH60 -> 0 | ... AG59: =DV59+FC60 -> 0 | AH59: =SUM(AI59:BK59) -> 200536.79 | AI59: =IF(E$8=0,0,ROUND(AI58-(E59-BN59),2)) -> 0 | AJ59: =IF(F$8=0,0,ROUND(AJ58-(F59-BO59),2)) -> 0 | AK59: =IF(G$8=0,0,ROUND(AK58-(G59-BP59),2)) -> 0 | AL59: =IF(H$8=0,0,ROUND(AL58-(H59-BQ59),2)) -> 0 | AM59: =IF(I$8=0,0,ROUND(AM58-(I59-BR59),2)) -> 0 | AN59: =IF(J$8=0,0,ROUND(AN58-(J59-BS59),2)) -> 0 | AO59: =IF(K$8=0,0,ROUND(AO58-(K59-BT59),2)) -> 0 | AP59: 0 | AQ59: =IF(M$8=0,0,ROUND(AQ58-(M59-BV59),2)) -> 0 | AR59: =IF(N$8=0,0,ROUND(AR58-(N59-BW59),2)) -> 1301.09 | AS59: =IF(O$8=0,0,ROUND(AS58-(O59-BX59),2)) -> 30533.25 | AT59: =IF(P$8=0,0,ROUND(AT58-(P59-BX59),2)) -> 32416.01 | AU59: =IF(Q$8=0,0,ROUND(AU58-(Q59-BY59),2)) -> 136286.44 | AV59: =IF(R$8=0,0,ROUND(AV58-(R59-BZ59),2)) -> 0 | AW59: =IF(S$8=0,0,ROUND(AW58-(S59-CA59),2)) -> 0 | AX59: =IF(T$8=0,0,ROUND(AX58-(T59-CB59),2)) -> 0 | AY59: =IF(U$8=0,0,ROUND(AY58-(U59-CC59),2)) -> 0 | AZ59: =IF(V$8=0,0,ROUND(AZ58-(V59-CD59),2)) -> 0 | BA59: =IF(W$8=0,0,ROUND(BA58-(W59-CE59),2)) -> 0 | ... BK59: =IF(AG$8=0,0,ROUND(BK58-(AG59-CO59),2)) -> 0 | BL59: =SUM(AI59:BK59) -> 200536.79 | BN59: =ROUND(AI58*E$9/12,2) -> 0 | BO59: =ROUND(AJ58*F$9/12,2) -> 0 | BP59: =ROUND(AK58*G$9/12,2) -> 0 | BQ59: =ROUND(AL58*H$9/12,2) -> 0 | BR59: =ROUND(AM58*I$9/12,2) -> 0 | BS59: =ROUND(AN58*J$9/12,2) -> 0 | BT59: =ROUND(AO58*K$9/12,2) -> 0 | BU59: =ROUND(AP58*L$9/12,2) -> 0 | ... CP59: =ROUND(BK58*AG$9/12,2) -> 0 | CR59: =SUM(BN59:CP59) -> 1000.75 | CT59: =IF(AI58>0,IF((AI58+BN59)<E$10,AI58+BN59,E$10),0) -> 0 | CU59: =IF(AJ58>0,IF((AJ58+BO59)<F$10,AJ58+BO59,F$10),0) -> 0 | CV59: =IF(AK58>0,IF((AK58+BP59)<G$10,AK58+BP59,G$10),0) -> 0 | CW59: =IF(AL58>0,IF((AL58+BQ59)<H$10,AL58+BQ59,H$10),0) -> 0 | CX59: =IF(AM58>0,IF((AM58+BR59)<I$10,AM58+BR59,I$10),0) -> 0 | CY59: =IF(AN58>0,IF((AN58+BS59)<J$10,AN58+BS59,J$10),0) -> 0 | CZ59: =IF(AO58>0,IF((AO58+BT59)<K$10,AO58+BT59,K$10),0) -> 0 | DA59: =IF(AP58>0,IF((AP58+BU59)<L$10,AP58+BU59,L$10),0) -> 0 | ... DX59: =IF(BM58>0,IF((BM58+CR59)<AI$10,BM58+CR59,AI$10),0) -> 0 | DY59: =SUM(CT59:DX59) -> 3403.97 | EA59: =IF(AI57<=0,0,IF(CT58+$C58>AI57+BN58,AI57+BN58-CT58,$C58)) -> 0 | EB59: =IF(AJ57<=0,0,IF($C58<=SUM($EA59:EA59),0,IF(CU58+$C58-SUM($EA59:EA59)>AJ57+BO58,AJ57+BO58-CU58,$C58-SUM($EA59:EA59)))) -> 0 | EC59: =IF(AK57<=0,0,IF($C58<=SUM($EA59:EB59),0,IF(CV58+$C58-SUM($EA59:EB59)>AK57+BP58,AK57+BP58-CV58,$C58-SUM($EA59:EB59)))) -> 0 | ED59: =IF(AL57<=0,0,IF($C58<=SUM($EA59:EC59),0,IF(CW58+$C58-SUM($EA59:EC59)>AL57+BQ58,AL57+BQ58-CW58,$C58-SUM($EA59:EC59)))) -> 0 | EE59: =IF(AM57<=0,0,IF($C58<=SUM($EA59:ED59),0,IF(CX58+$C58-SUM($EA59:ED59)>AM57+BR58,AM57+BR58-CX58,$C58-SUM($EA59:ED59)))) -> 0 | EF59: =IF(AN57<=0,0,IF($C58<=SUM($EA59:EE59),0,IF(CY58+$C58-SUM($EA59:EE59)>AN57+BS58,AN57+BS58-CY58,$C58-SUM($EA59:EE59)))) -> 0 | EG59: =IF(AO57<=0,0,IF($C58<=SUM($EA59:EF59),0,IF(CZ58+$C58-SUM($EA59:EF59)>AO57+BT58,AO57+BT58-CZ58,$C58-SUM($EA59:EF59)))) -> 0 | EH59: =IF(AP57<=0,0,IF($C58<=SUM($EA59:EG59),0,IF(DA58+$C58-SUM($EA59:EG59)>AP57+BU58,AP57+BU58-DA58,$C58-SUM($EA59:EG59)))) -> 0 | EI59: =IF(AQ57<=0,0,IF($C58<=SUM($EA59:EH59),0,IF(DB58+$C58-SUM($EA59:EH59)>AQ57+BV58,AQ57+BV58-DB58,$C58-SUM($EA59:EH59)))) -> 0 | ... FC59: =IF(BK57<=0,0,IF($C58<=SUM($EA59:FB59),0,IF(DV58+$C58-SUM($EA59:FB59)>BK57+CP58,BK57+CP58-DV58,$C58-SUM($EA59:FB59)))) -> 0
A60: =IF(SUM(AI59:BK59)<=0,"",A59+1) -> 40 | B60: 46844 | C60: =IF(A60="","",IF(Calculator!snowball,IF(($E$5-DY60)<0,0,$E$5-DY60),0)+D60) -> 458.03 | E60: =CT60+EA61 -> 0 | F60: =CU60+EB61 -> 0 | G60: =CV60+EC61 -> 0 | H60: =CW60+ED61 -> 0 | I60: =CX60+EE61 -> 0 | J60: =CY60+EF61 -> 0 | K60: =CZ60+EG61 -> 0 | L60: =DA60+EH61 -> 0 | ... AG60: =DV60+FC61 -> 0 | AH60: =SUM(AI60:BK60) -> 197504.77 | AI60: =IF(E$8=0,0,ROUND(AI59-(E60-BN60),2)) -> 0 | AJ60: =IF(F$8=0,0,ROUND(AJ59-(F60-BO60),2)) -> 0 | AK60: =IF(G$8=0,0,ROUND(AK59-(G60-BP60),2)) -> 0 | AL60: =IF(H$8=0,0,ROUND(AL59-(H60-BQ60),2)) -> 0 | AM60: =IF(I$8=0,0,ROUND(AM59-(I60-BR60),2)) -> 0 | AN60: =IF(J$8=0,0,ROUND(AN59-(J60-BS60),2)) -> 0 | AO60: =IF(K$8=0,0,ROUND(AO59-(K60-BT60),2)) -> 0 | AP60: 0 | AQ60: =IF(M$8=0,0,ROUND(AQ59-(M60-BV60),2)) -> 0 | AR60: =IF(N$8=0,0,ROUND(AR59-(N60-BW60),2)) -> 412.5 | AS60: =IF(O$8=0,0,ROUND(AS59-(O60-BX60),2)) -> 30117.54 | AT60: =IF(P$8=0,0,ROUND(AT59-(P60-BX60),2)) -> 31904.74 | AU60: =IF(Q$8=0,0,ROUND(AU59-(Q60-BY60),2)) -> 135069.99 | AV60: =IF(R$8=0,0,ROUND(AV59-(R60-BZ60),2)) -> 0 | AW60: =IF(S$8=0,0,ROUND(AW59-(S60-CA60),2)) -> 0 | AX60: =IF(T$8=0,0,ROUND(AX59-(T60-CB60),2)) -> 0 | AY60: =IF(U$8=0,0,ROUND(AY59-(U60-CC60),2)) -> 0 | AZ60: =IF(V$8=0,0,ROUND(AZ59-(V60-CD60),2)) -> 0 | BA60: =IF(W$8=0,0,ROUND(BA59-(W60-CE60),2)) -> 0 | ... BK60: =IF(AG$8=0,0,ROUND(BK59-(AG60-CO60),2)) -> 0 | BL60: =SUM(AI60:BK60) -> 197504.77 | BN60: =ROUND(AI59*E$9/12,2) -> 0 | BO60: =ROUND(AJ59*F$9/12,2) -> 0 | BP60: =ROUND(AK59*G$9/12,2) -> 0 | BQ60: =ROUND(AL59*H$9/12,2) -> 0 | BR60: =ROUND(AM59*I$9/12,2) -> 0 | BS60: =ROUND(AN59*J$9/12,2) -> 0 | BT60: =ROUND(AO59*K$9/12,2) -> 0 | BU60: =ROUND(AP59*L$9/12,2) -> 0 | ... CP60: =ROUND(BK59*AG$9/12,2) -> 0 | CR60: =SUM(BN60:CP60) -> 975.99 | CT60: =IF(AI59>0,IF((AI59+BN60)<E$10,AI59+BN60,E$10),0) -> 0 | CU60: =IF(AJ59>0,IF((AJ59+BO60)<F$10,AJ59+BO60,F$10),0) -> 0 | CV60: =IF(AK59>0,IF((AK59+BP60)<G$10,AK59+BP60,G$10),0) -> 0 | CW60: =IF(AL59>0,IF((AL59+BQ60)<H$10,AL59+BQ60,H$10),0) -> 0 | CX60: =IF(AM59>0,IF((AM59+BR60)<I$10,AM59+BR60,I$10),0) -> 0 | CY60: =IF(AN59>0,IF((AN59+BS60)<J$10,AN59+BS60,J$10),0) -> 0 | CZ60: =IF(AO59>0,IF((AO59+BT60)<K$10,AO59+BT60,K$10),0) -> 0 | DA60: =IF(AP59>0,IF((AP59+BU60)<L$10,AP59+BU60,L$10),0) -> 0 | ... DX60: =IF(BM59>0,IF((BM59+CR60)<AI$10,BM59+CR60,AI$10),0) -> 0 | DY60: =SUM(CT60:DX60) -> 3403.97 | EA60: =IF(AI58<=0,0,IF(CT59+$C59>AI58+BN59,AI58+BN59-CT59,$C59)) -> 0 | EB60: =IF(AJ58<=0,0,IF($C59<=SUM($EA60:EA60),0,IF(CU59+$C59-SUM($EA60:EA60)>AJ58+BO59,AJ58+BO59-CU59,$C59-SUM($EA60:EA60)))) -> 0 | EC60: =IF(AK58<=0,0,IF($C59<=SUM($EA60:EB60),0,IF(CV59+$C59-SUM($EA60:EB60)>AK58+BP59,AK58+BP59-CV59,$C59-SUM($EA60:EB60)))) -> 0 | ED60: =IF(AL58<=0,0,IF($C59<=SUM($EA60:EC60),0,IF(CW59+$C59-SUM($EA60:EC60)>AL58+BQ59,AL58+BQ59-CW59,$C59-SUM($EA60:EC60)))) -> 0 | EE60: =IF(AM58<=0,0,IF($C59<=SUM($EA60:ED60),0,IF(CX59+$C59-SUM($EA60:ED60)>AM58+BR59,AM58+BR59-CX59,$C59-SUM($EA60:ED60)))) -> 0 | EF60: =IF(AN58<=0,0,IF($C59<=SUM($EA60:EE60),0,IF(CY59+$C59-SUM($EA60:EE60)>AN58+BS59,AN58+BS59-CY59,$C59-SUM($EA60:EE60)))) -> 0 | EG60: =IF(AO58<=0,0,IF($C59<=SUM($EA60:EF60),0,IF(CZ59+$C59-SUM($EA60:EF60)>AO58+BT59,AO58+BT59-CZ59,$C59-SUM($EA60:EF60)))) -> 0 | EH60: =IF(AP58<=0,0,IF($C59<=SUM($EA60:EG60),0,IF(DA59+$C59-SUM($EA60:EG60)>AP58+BU59,AP58+BU59-DA59,$C59-SUM($EA60:EG60)))) -> 0 | EI60: =IF(AQ58<=0,0,IF($C59<=SUM($EA60:EH60),0,IF(DB59+$C59-SUM($EA60:EH60)>AQ58+BV59,AQ58+BV59-DB59,$C59-SUM($EA60:EH60)))) -> 0 | ... FC60: =IF(BK58<=0,0,IF($C59<=SUM($EA60:FB60),0,IF(DV59+$C59-SUM($EA60:FB60)>BK58+CP59,BK58+CP59-DV59,$C59-SUM($EA60:FB60)))) -> 0
A61: =IF(SUM(AI60:BK60)<=0,"",A60+1) -> 41 | B61: 46874 | C61: =IF(A61="","",IF(Calculator!snowball,IF(($E$5-DY61)<0,0,$E$5-DY61),0)+D61) -> 489.42 | E61: =CT61+EA62 -> 0 | F61: =CU61+EB62 -> 0 | G61: =CV61+EC62 -> 0 | H61: =CW61+ED62 -> 0 | I61: =CX61+EE62 -> 0 | J61: =CY61+EF62 -> 0 | K61: =CZ61+EG62 -> 0 | L61: =DA61+EH62 -> 0 | ... AG61: =DV61+FC62 -> 0 | AH61: =SUM(AI61:BK61) -> 194447.85 | AI61: =IF(E$8=0,0,ROUND(AI60-(E61-BN61),2)) -> 0 | AJ61: =IF(F$8=0,0,ROUND(AJ60-(F61-BO61),2)) -> 0 | AK61: =IF(G$8=0,0,ROUND(AK60-(G61-BP61),2)) -> 0 | AL61: =IF(H$8=0,0,ROUND(AL60-(H61-BQ61),2)) -> 0 | AM61: =IF(I$8=0,0,ROUND(AM60-(I61-BR61),2)) -> 0 | AN61: =IF(J$8=0,0,ROUND(AN60-(J61-BS61),2)) -> 0 | AO61: =IF(K$8=0,0,ROUND(AO60-(K61-BT61),2)) -> 0 | AP61: 0 | AQ61: =IF(M$8=0,0,ROUND(AQ60-(M61-BV61),2)) -> 0 | AR61: =IF(N$8=0,0,ROUND(AR60-(N61-BW61),2)) -> 0 | AS61: =IF(O$8=0,0,ROUND(AS60-(O61-BX61),2)) -> 29208.6 | AT61: =IF(P$8=0,0,ROUND(AT60-(P61-BX61),2)) -> 31389.66 | AU61: =IF(Q$8=0,0,ROUND(AU60-(Q61-BY61),2)) -> 133849.59 | AV61: =IF(R$8=0,0,ROUND(AV60-(R61-BZ61),2)) -> 0 | AW61: =IF(S$8=0,0,ROUND(AW60-(S61-CA61),2)) -> 0 | AX61: =IF(T$8=0,0,ROUND(AX60-(T61-CB61),2)) -> 0 | AY61: =IF(U$8=0,0,ROUND(AY60-(U61-CC61),2)) -> 0 | AZ61: =IF(V$8=0,0,ROUND(AZ60-(V61-CD61),2)) -> 0 | BA61: =IF(W$8=0,0,ROUND(BA60-(W61-CE61),2)) -> 0 | ... BK61: =IF(AG$8=0,0,ROUND(BK60-(AG61-CO61),2)) -> 0 | BL61: =SUM(AI61:BK61) -> 194447.85 | BN61: =ROUND(AI60*E$9/12,2) -> 0 | BO61: =ROUND(AJ60*F$9/12,2) -> 0 | BP61: =ROUND(AK60*G$9/12,2) -> 0 | BQ61: =ROUND(AL60*H$9/12,2) -> 0 | BR61: =ROUND(AM60*I$9/12,2) -> 0 | BS61: =ROUND(AN60*J$9/12,2) -> 0 | BT61: =ROUND(AO60*K$9/12,2) -> 0 | BU61: =ROUND(AP60*L$9/12,2) -> 0 | ... CP61: =ROUND(BK60*AG$9/12,2) -> 0 | CR61: =SUM(BN61:CP61) -> 951.09 | CT61: =IF(AI60>0,IF((AI60+BN61)<E$10,AI60+BN61,E$10),0) -> 0 | CU61: =IF(AJ60>0,IF((AJ60+BO61)<F$10,AJ60+BO61,F$10),0) -> 0 | CV61: =IF(AK60>0,IF((AK60+BP61)<G$10,AK60+BP61,G$10),0) -> 0 | CW61: =IF(AL60>0,IF((AL60+BQ61)<H$10,AL60+BQ61,H$10),0) -> 0 | CX61: =IF(AM60>0,IF((AM60+BR61)<I$10,AM60+BR61,I$10),0) -> 0 | CY61: =IF(AN60>0,IF((AN60+BS61)<J$10,AN60+BS61,J$10),0) -> 0 | CZ61: =IF(AO60>0,IF((AO60+BT61)<K$10,AO60+BT61,K$10),0) -> 0 | DA61: =IF(AP60>0,IF((AP60+BU61)<L$10,AP60+BU61,L$10),0) -> 0 | ... DX61: =IF(BM60>0,IF((BM60+CR61)<AI$10,BM60+CR61,AI$10),0) -> 0 | DY61: =SUM(CT61:DX61) -> 3372.58 | EA61: =IF(AI59<=0,0,IF(CT60+$C60>AI59+BN60,AI59+BN60-CT60,$C60)) -> 0 | EB61: =IF(AJ59<=0,0,IF($C60<=SUM($EA61:EA61),0,IF(CU60+$C60-SUM($EA61:EA61)>AJ59+BO60,AJ59+BO60-CU60,$C60-SUM($EA61:EA61)))) -> 0 | EC61: =IF(AK59<=0,0,IF($C60<=SUM($EA61:EB61),0,IF(CV60+$C60-SUM($EA61:EB61)>AK59+BP60,AK59+BP60-CV60,$C60-SUM($EA61:EB61)))) -> 0 | ED61: =IF(AL59<=0,0,IF($C60<=SUM($EA61:EC61),0,IF(CW60+$C60-SUM($EA61:EC61)>AL59+BQ60,AL59+BQ60-CW60,$C60-SUM($EA61:EC61)))) -> 0 | EE61: =IF(AM59<=0,0,IF($C60<=SUM($EA61:ED61),0,IF(CX60+$C60-SUM($EA61:ED61)>AM59+BR60,AM59+BR60-CX60,$C60-SUM($EA61:ED61)))) -> 0 | EF61: =IF(AN59<=0,0,IF($C60<=SUM($EA61:EE61),0,IF(CY60+$C60-SUM($EA61:EE61)>AN59+BS60,AN59+BS60-CY60,$C60-SUM($EA61:EE61)))) -> 0 | EG61: =IF(AO59<=0,0,IF($C60<=SUM($EA61:EF61),0,IF(CZ60+$C60-SUM($EA61:EF61)>AO59+BT60,AO59+BT60-CZ60,$C60-SUM($EA61:EF61)))) -> 0 | EH61: =IF(AP59<=0,0,IF($C60<=SUM($EA61:EG61),0,IF(DA60+$C60-SUM($EA61:EG61)>AP59+BU60,AP59+BU60-DA60,$C60-SUM($EA61:EG61)))) -> 0 | EI61: =IF(AQ59<=0,0,IF($C60<=SUM($EA61:EH61),0,IF(DB60+$C60-SUM($EA61:EH61)>AQ59+BV60,AQ59+BV60-DB60,$C60-SUM($EA61:EH61)))) -> 0 | ... FC61: =IF(BK59<=0,0,IF($C60<=SUM($EA61:FB61),0,IF(DV60+$C60-SUM($EA61:FB61)>BK59+CP60,BK59+CP60-DV60,$C60-SUM($EA61:FB61)))) -> 0
A62: =IF(SUM(AI61:BK61)<=0,"",A61+1) -> 42 | B62: 46905 | C62: =IF(A62="","",IF(Calculator!snowball,IF(($E$5-DY62)<0,0,$E$5-DY62),0)+D62) -> 908.11 | E62: =CT62+EA63 -> 0 | F62: =CU62+EB63 -> 0 | G62: =CV62+EC63 -> 0 | H62: =CW62+ED63 -> 0 | I62: =CX62+EE63 -> 0 | J62: =CY62+EF63 -> 0 | K62: =CZ62+EG63 -> 0 | L62: =DA62+EH63 -> 0 | ... AG62: =DV62+FC63 -> 0 | AH62: =SUM(AI62:BK62) -> 191364.1 | AI62: =IF(E$8=0,0,ROUND(AI61-(E62-BN62),2)) -> 0 | AJ62: =IF(F$8=0,0,ROUND(AJ61-(F62-BO62),2)) -> 0 | AK62: =IF(G$8=0,0,ROUND(AK61-(G62-BP62),2)) -> 0 | AL62: =IF(H$8=0,0,ROUND(AL61-(H62-BQ62),2)) -> 0 | AM62: =IF(I$8=0,0,ROUND(AM61-(I62-BR62),2)) -> 0 | AN62: =IF(J$8=0,0,ROUND(AN61-(J62-BS62),2)) -> 0 | AO62: =IF(K$8=0,0,ROUND(AO61-(K62-BT62),2)) -> 0 | AP62: 0 | AQ62: =IF(M$8=0,0,ROUND(AQ61-(M62-BV62),2)) -> 0 | AR62: =IF(N$8=0,0,ROUND(AR61-(N62-BW62),2)) -> 0 | AS62: =IF(O$8=0,0,ROUND(AS61-(O62-BX62),2)) -> 27872.64 | AT62: =IF(P$8=0,0,ROUND(AT61-(P62-BX62),2)) -> 30866.25 | AU62: =IF(Q$8=0,0,ROUND(AU61-(Q62-BY62),2)) -> 132625.21 | AV62: =IF(R$8=0,0,ROUND(AV61-(R62-BZ62),2)) -> 0 | AW62: =IF(S$8=0,0,ROUND(AW61-(S62-CA62),2)) -> 0 | AX62: =IF(T$8=0,0,ROUND(AX61-(T62-CB62),2)) -> 0 | AY62: =IF(U$8=0,0,ROUND(AY61-(U62-CC62),2)) -> 0 | AZ62: =IF(V$8=0,0,ROUND(AZ61-(V62-CD62),2)) -> 0 | BA62: =IF(W$8=0,0,ROUND(BA61-(W62-CE62),2)) -> 0 | ... BK62: =IF(AG$8=0,0,ROUND(BK61-(AG62-CO62),2)) -> 0 | BL62: =SUM(AI62:BK62) -> 191364.1 | BN62: =ROUND(AI61*E$9/12,2) -> 0 | BO62: =ROUND(AJ61*F$9/12,2) -> 0 | BP62: =ROUND(AK61*G$9/12,2) -> 0 | BQ62: =ROUND(AL61*H$9/12,2) -> 0 | BR62: =ROUND(AM61*I$9/12,2) -> 0 | BS62: =ROUND(AN61*J$9/12,2) -> 0 | BT62: =ROUND(AO61*K$9/12,2) -> 0 | BU62: =ROUND(AP61*L$9/12,2) -> 0 | ... CP62: =ROUND(BK61*AG$9/12,2) -> 0 | CR62: =SUM(BN62:CP62) -> 928.78 | CT62: =IF(AI61>0,IF((AI61+BN62)<E$10,AI61+BN62,E$10),0) -> 0 | CU62: =IF(AJ61>0,IF((AJ61+BO62)<F$10,AJ61+BO62,F$10),0) -> 0 | CV62: =IF(AK61>0,IF((AK61+BP62)<G$10,AK61+BP62,G$10),0) -> 0 | CW62: =IF(AL61>0,IF((AL61+BQ62)<H$10,AL61+BQ62,H$10),0) -> 0 | CX62: =IF(AM61>0,IF((AM61+BR62)<I$10,AM61+BR62,I$10),0) -> 0 | CY62: =IF(AN61>0,IF((AN61+BS62)<J$10,AN61+BS62,J$10),0) -> 0 | CZ62: =IF(AO61>0,IF((AO61+BT62)<K$10,AO61+BT62,K$10),0) -> 0 | DA62: =IF(AP61>0,IF((AP61+BU62)<L$10,AP61+BU62,L$10),0) -> 0 | ... DX62: =IF(BM61>0,IF((BM61+CR62)<AI$10,BM61+CR62,AI$10),0) -> 0 | DY62: =SUM(CT62:DX62) -> 2953.89 | EA62: =IF(AI60<=0,0,IF(CT61+$C61>AI60+BN61,AI60+BN61-CT61,$C61)) -> 0 | EB62: =IF(AJ60<=0,0,IF($C61<=SUM($EA62:EA62),0,IF(CU61+$C61-SUM($EA62:EA62)>AJ60+BO61,AJ60+BO61-CU61,$C61-SUM($EA62:EA62)))) -> 0 | EC62: =IF(AK60<=0,0,IF($C61<=SUM($EA62:EB62),0,IF(CV61+$C61-SUM($EA62:EB62)>AK60+BP61,AK60+BP61-CV61,$C61-SUM($EA62:EB62)))) -> 0 | ED62: =IF(AL60<=0,0,IF($C61<=SUM($EA62:EC62),0,IF(CW61+$C61-SUM($EA62:EC62)>AL60+BQ61,AL60+BQ61-CW61,$C61-SUM($EA62:EC62)))) -> 0 | EE62: =IF(AM60<=0,0,IF($C61<=SUM($EA62:ED62),0,IF(CX61+$C61-SUM($EA62:ED62)>AM60+BR61,AM60+BR61-CX61,$C61-SUM($EA62:ED62)))) -> 0 | EF62: =IF(AN60<=0,0,IF($C61<=SUM($EA62:EE62),0,IF(CY61+$C61-SUM($EA62:EE62)>AN60+BS61,AN60+BS61-CY61,$C61-SUM($EA62:EE62)))) -> 0 | EG62: =IF(AO60<=0,0,IF($C61<=SUM($EA62:EF62),0,IF(CZ61+$C61-SUM($EA62:EF62)>AO60+BT61,AO60+BT61-CZ61,$C61-SUM($EA62:EF62)))) -> 0 | EH62: =IF(AP60<=0,0,IF($C61<=SUM($EA62:EG62),0,IF(DA61+$C61-SUM($EA62:EG62)>AP60+BU61,AP60+BU61-DA61,$C61-SUM($EA62:EG62)))) -> 0 | EI62: =IF(AQ60<=0,0,IF($C61<=SUM($EA62:EH62),0,IF(DB61+$C61-SUM($EA62:EH62)>AQ60+BV61,AQ60+BV61-DB61,$C61-SUM($EA62:EH62)))) -> 0 | ... FC62: =IF(BK60<=0,0,IF($C61<=SUM($EA62:FB62),0,IF(DV61+$C61-SUM($EA62:FB62)>BK60+CP61,BK60+CP61-DV61,$C61-SUM($EA62:FB62)))) -> 0
A63: =IF(SUM(AI62:BK62)<=0,"",A62+1) -> 43 | B63: 46935 | C63: =IF(A63="","",IF(Calculator!snowball,IF(($E$5-DY63)<0,0,$E$5-DY63),0)+D63) -> 908.11 | E63: =CT63+EA64 -> 0 | F63: =CU63+EB64 -> 0 | G63: =CV63+EC64 -> 0 | H63: =CW63+ED64 -> 0 | I63: =CX63+EE64 -> 0 | J63: =CY63+EF64 -> 0 | K63: =CZ63+EG64 -> 0 | L63: =DA63+EH64 -> 0 | ... AG63: =DV63+FC64 -> 0 | AH63: =SUM(AI63:BK63) -> 188251.8 | AI63: =IF(E$8=0,0,ROUND(AI62-(E63-BN63),2)) -> 0 | AJ63: =IF(F$8=0,0,ROUND(AJ62-(F63-BO63),2)) -> 0 | AK63: =IF(G$8=0,0,ROUND(AK62-(G63-BP63),2)) -> 0 | AL63: =IF(H$8=0,0,ROUND(AL62-(H63-BQ63),2)) -> 0 | AM63: =IF(I$8=0,0,ROUND(AM62-(I63-BR63),2)) -> 0 | AN63: =IF(J$8=0,0,ROUND(AN62-(J63-BS63),2)) -> 0 | AO63: =IF(K$8=0,0,ROUND(AO62-(K63-BT63),2)) -> 0 | AP63: 0 | AQ63: =IF(M$8=0,0,ROUND(AQ62-(M63-BV63),2)) -> 0 | AR63: =IF(N$8=0,0,ROUND(AR62-(N63-BW63),2)) -> 0 | AS63: =IF(O$8=0,0,ROUND(AS62-(O63-BX63),2)) -> 26524.43 | AT63: =IF(P$8=0,0,ROUND(AT62-(P63-BX63),2)) -> 30330.59 | AU63: =IF(Q$8=0,0,ROUND(AU62-(Q63-BY63),2)) -> 131396.78 | AV63: =IF(R$8=0,0,ROUND(AV62-(R63-BZ63),2)) -> 0 | AW63: =IF(S$8=0,0,ROUND(AW62-(S63-CA63),2)) -> 0 | AX63: =IF(T$8=0,0,ROUND(AX62-(T63-CB63),2)) -> 0 | AY63: =IF(U$8=0,0,ROUND(AY62-(U63-CC63),2)) -> 0 | AZ63: =IF(V$8=0,0,ROUND(AZ62-(V63-CD63),2)) -> 0 | BA63: =IF(W$8=0,0,ROUND(BA62-(W63-CE63),2)) -> 0 | ... BK63: =IF(AG$8=0,0,ROUND(BK62-(AG63-CO63),2)) -> 0 | BL63: =SUM(AI63:BK63) -> 188251.8 | BN63: =ROUND(AI62*E$9/12,2) -> 0 | BO63: =ROUND(AJ62*F$9/12,2) -> 0 | BP63: =ROUND(AK62*G$9/12,2) -> 0 | BQ63: =ROUND(AL62*H$9/12,2) -> 0 | BR63: =ROUND(AM62*I$9/12,2) -> 0 | BS63: =ROUND(AN62*J$9/12,2) -> 0 | BT63: =ROUND(AO62*K$9/12,2) -> 0 | BU63: =ROUND(AP62*L$9/12,2) -> 0 | ... CP63: =ROUND(BK62*AG$9/12,2) -> 0 | CR63: =SUM(BN63:CP63) -> 908.65 | CT63: =IF(AI62>0,IF((AI62+BN63)<E$10,AI62+BN63,E$10),0) -> 0 | CU63: =IF(AJ62>0,IF((AJ62+BO63)<F$10,AJ62+BO63,F$10),0) -> 0 | CV63: =IF(AK62>0,IF((AK62+BP63)<G$10,AK62+BP63,G$10),0) -> 0 | CW63: =IF(AL62>0,IF((AL62+BQ63)<H$10,AL62+BQ63,H$10),0) -> 0 | CX63: =IF(AM62>0,IF((AM62+BR63)<I$10,AM62+BR63,I$10),0) -> 0 | CY63: =IF(AN62>0,IF((AN62+BS63)<J$10,AN62+BS63,J$10),0) -> 0 | CZ63: =IF(AO62>0,IF((AO62+BT63)<K$10,AO62+BT63,K$10),0) -> 0 | DA63: =IF(AP62>0,IF((AP62+BU63)<L$10,AP62+BU63,L$10),0) -> 0 | ... DX63: =IF(BM62>0,IF((BM62+CR63)<AI$10,BM62+CR63,AI$10),0) -> 0 | DY63: =SUM(CT63:DX63) -> 2953.89 | EA63: =IF(AI61<=0,0,IF(CT62+$C62>AI61+BN62,AI61+BN62-CT62,$C62)) -> 0 | EB63: =IF(AJ61<=0,0,IF($C62<=SUM($EA63:EA63),0,IF(CU62+$C62-SUM($EA63:EA63)>AJ61+BO62,AJ61+BO62-CU62,$C62-SUM($EA63:EA63)))) -> 0 | EC63: =IF(AK61<=0,0,IF($C62<=SUM($EA63:EB63),0,IF(CV62+$C62-SUM($EA63:EB63)>AK61+BP62,AK61+BP62-CV62,$C62-SUM($EA63:EB63)))) -> 0 | ED63: =IF(AL61<=0,0,IF($C62<=SUM($EA63:EC63),0,IF(CW62+$C62-SUM($EA63:EC63)>AL61+BQ62,AL61+BQ62-CW62,$C62-SUM($EA63:EC63)))) -> 0 | EE63: =IF(AM61<=0,0,IF($C62<=SUM($EA63:ED63),0,IF(CX62+$C62-SUM($EA63:ED63)>AM61+BR62,AM61+BR62-CX62,$C62-SUM($EA63:ED63)))) -> 0 | EF63: =IF(AN61<=0,0,IF($C62<=SUM($EA63:EE63),0,IF(CY62+$C62-SUM($EA63:EE63)>AN61+BS62,AN61+BS62-CY62,$C62-SUM($EA63:EE63)))) -> 0 | EG63: =IF(AO61<=0,0,IF($C62<=SUM($EA63:EF63),0,IF(CZ62+$C62-SUM($EA63:EF63)>AO61+BT62,AO61+BT62-CZ62,$C62-SUM($EA63:EF63)))) -> 0 | EH63: =IF(AP61<=0,0,IF($C62<=SUM($EA63:EG63),0,IF(DA62+$C62-SUM($EA63:EG63)>AP61+BU62,AP61+BU62-DA62,$C62-SUM($EA63:EG63)))) -> 0 | EI63: =IF(AQ61<=0,0,IF($C62<=SUM($EA63:EH63),0,IF(DB62+$C62-SUM($EA63:EH63)>AQ61+BV62,AQ61+BV62-DB62,$C62-SUM($EA63:EH63)))) -> 0 | ... FC63: =IF(BK61<=0,0,IF($C62<=SUM($EA63:FB63),0,IF(DV62+$C62-SUM($EA63:FB63)>BK61+CP62,BK61+CP62-DV62,$C62-SUM($EA63:FB63)))) -> 0
A64: =IF(SUM(AI63:BK63)<=0,"",A63+1) -> 44 | B64: 46966 | C64: =IF(A64="","",IF(Calculator!snowball,IF(($E$5-DY64)<0,0,$E$5-DY64),0)+D64) -> 908.11 | E64: =CT64+EA65 -> 0 | F64: =CU64+EB65 -> 0 | G64: =CV64+EC65 -> 0 | H64: =CW64+ED65 -> 0 | I64: =CX64+EE65 -> 0 | J64: =CY64+EF65 -> 0 | K64: =CZ64+EG65 -> 0 | L64: =DA64+EH65 -> 0 | ... AG64: =DV64+FC65 -> 0 | AH64: =SUM(AI64:BK64) -> 185110.64 | AI64: =IF(E$8=0,0,ROUND(AI63-(E64-BN64),2)) -> 0 | AJ64: =IF(F$8=0,0,ROUND(AJ63-(F64-BO64),2)) -> 0 | AK64: =IF(G$8=0,0,ROUND(AK63-(G64-BP64),2)) -> 0 | AL64: =IF(H$8=0,0,ROUND(AL63-(H64-BQ64),2)) -> 0 | AM64: =IF(I$8=0,0,ROUND(AM63-(I64-BR64),2)) -> 0 | AN64: =IF(J$8=0,0,ROUND(AN63-(J64-BS64),2)) -> 0 | AO64: =IF(K$8=0,0,ROUND(AO63-(K64-BT64),2)) -> 0 | AP64: 0 | AQ64: =IF(M$8=0,0,ROUND(AQ63-(M64-BV64),2)) -> 0 | AR64: =IF(N$8=0,0,ROUND(AR63-(N64-BW64),2)) -> 0 | AS64: =IF(O$8=0,0,ROUND(AS63-(O64-BX64),2)) -> 25163.86 | AT64: =IF(P$8=0,0,ROUND(AT63-(P64-BX64),2)) -> 29782.57 | AU64: =IF(Q$8=0,0,ROUND(AU63-(Q64-BY64),2)) -> 130164.21 | AV64: =IF(R$8=0,0,ROUND(AV63-(R64-BZ64),2)) -> 0 | AW64: =IF(S$8=0,0,ROUND(AW63-(S64-CA64),2)) -> 0 | AX64: =IF(T$8=0,0,ROUND(AX63-(T64-CB64),2)) -> 0 | AY64: =IF(U$8=0,0,ROUND(AY63-(U64-CC64),2)) -> 0 | AZ64: =IF(V$8=0,0,ROUND(AZ63-(V64-CD64),2)) -> 0 | BA64: =IF(W$8=0,0,ROUND(BA63-(W64-CE64),2)) -> 0 | ... BK64: =IF(AG$8=0,0,ROUND(BK63-(AG64-CO64),2)) -> 0 | BL64: =SUM(AI64:BK64) -> 185110.64 | BN64: =ROUND(AI63*E$9/12,2) -> 0 | BO64: =ROUND(AJ63*F$9/12,2) -> 0 | BP64: =ROUND(AK63*G$9/12,2) -> 0 | BQ64: =ROUND(AL63*H$9/12,2) -> 0 | BR64: =ROUND(AM63*I$9/12,2) -> 0 | BS64: =ROUND(AN63*J$9/12,2) -> 0 | BT64: =ROUND(AO63*K$9/12,2) -> 0 | BU64: =ROUND(AP63*L$9/12,2) -> 0 | ... CP64: =ROUND(BK63*AG$9/12,2) -> 0 | CR64: =SUM(BN64:CP64) -> 888.31 | CT64: =IF(AI63>0,IF((AI63+BN64)<E$10,AI63+BN64,E$10),0) -> 0 | CU64: =IF(AJ63>0,IF((AJ63+BO64)<F$10,AJ63+BO64,F$10),0) -> 0 | CV64: =IF(AK63>0,IF((AK63+BP64)<G$10,AK63+BP64,G$10),0) -> 0 | CW64: =IF(AL63>0,IF((AL63+BQ64)<H$10,AL63+BQ64,H$10),0) -> 0 | CX64: =IF(AM63>0,IF((AM63+BR64)<I$10,AM63+BR64,I$10),0) -> 0 | CY64: =IF(AN63>0,IF((AN63+BS64)<J$10,AN63+BS64,J$10),0) -> 0 | CZ64: =IF(AO63>0,IF((AO63+BT64)<K$10,AO63+BT64,K$10),0) -> 0 | DA64: =IF(AP63>0,IF((AP63+BU64)<L$10,AP63+BU64,L$10),0) -> 0 | ... DX64: =IF(BM63>0,IF((BM63+CR64)<AI$10,BM63+CR64,AI$10),0) -> 0 | DY64: =SUM(CT64:DX64) -> 2953.89 | EA64: =IF(AI62<=0,0,IF(CT63+$C63>AI62+BN63,AI62+BN63-CT63,$C63)) -> 0 | EB64: =IF(AJ62<=0,0,IF($C63<=SUM($EA64:EA64),0,IF(CU63+$C63-SUM($EA64:EA64)>AJ62+BO63,AJ62+BO63-CU63,$C63-SUM($EA64:EA64)))) -> 0 | EC64: =IF(AK62<=0,0,IF($C63<=SUM($EA64:EB64),0,IF(CV63+$C63-SUM($EA64:EB64)>AK62+BP63,AK62+BP63-CV63,$C63-SUM($EA64:EB64)))) -> 0 | ED64: =IF(AL62<=0,0,IF($C63<=SUM($EA64:EC64),0,IF(CW63+$C63-SUM($EA64:EC64)>AL62+BQ63,AL62+BQ63-CW63,$C63-SUM($EA64:EC64)))) -> 0 | EE64: =IF(AM62<=0,0,IF($C63<=SUM($EA64:ED64),0,IF(CX63+$C63-SUM($EA64:ED64)>AM62+BR63,AM62+BR63-CX63,$C63-SUM($EA64:ED64)))) -> 0 | EF64: =IF(AN62<=0,0,IF($C63<=SUM($EA64:EE64),0,IF(CY63+$C63-SUM($EA64:EE64)>AN62+BS63,AN62+BS63-CY63,$C63-SUM($EA64:EE64)))) -> 0 | EG64: =IF(AO62<=0,0,IF($C63<=SUM($EA64:EF64),0,IF(CZ63+$C63-SUM($EA64:EF64)>AO62+BT63,AO62+BT63-CZ63,$C63-SUM($EA64:EF64)))) -> 0 | EH64: =IF(AP62<=0,0,IF($C63<=SUM($EA64:EG64),0,IF(DA63+$C63-SUM($EA64:EG64)>AP62+BU63,AP62+BU63-DA63,$C63-SUM($EA64:EG64)))) -> 0 | EI64: =IF(AQ62<=0,0,IF($C63<=SUM($EA64:EH64),0,IF(DB63+$C63-SUM($EA64:EH64)>AQ62+BV63,AQ62+BV63-DB63,$C63-SUM($EA64:EH64)))) -> 0 | ... FC64: =IF(BK62<=0,0,IF($C63<=SUM($EA64:FB64),0,IF(DV63+$C63-SUM($EA64:FB64)>BK62+CP63,BK62+CP63-DV63,$C63-SUM($EA64:FB64)))) -> 0
